Workbook

Sheet INV. FEB
A1: INVENTARIO
A2: PRODUCTO | B2: 01/02/25 INICIA | C2: 01/02/25 ENTRA | D2: 01/02/25 SALE | E2: 02/02/25 INICIA | F2: 02/02/25 ENTRA | G2: 02/02/25 SALE | H2: 03/02/25 INICIA | I2: 03/02/25 ENTRA | J2: 03/02/25 SALE | K2: 04/02/25 INICIA | L2: 04/02/25 ENTRA | M2: 04/02/25 SALE | N2: 06/02/25 INICIA | O2: 06/02/25 ENTRA | P2: 06/02/25 SALE | Q2: 07/02/25 INICIA | R2: 07/02/25 ENTRA | S2: 07/02/25 SALE | T2: 08/02/25 INICIA | U2: 08/02/25 SALE | V2: 09/02/25 INICIA | W2: 09/02/25 ENTRA | X2: 09/02/25 SALE | Y2: 10/02/25 INICIA | Z2: 10/02/25 SALE | AA2: 11/02/25 INICIA | AB2: 11/02/25 ENTRA | AC2: 11/02/25 SALE | AD2: 12/02/25 INICIA | AE2: 12/02/25 SALE | AF2: 13/02/25 INICIA | AG2: 13/02/25 SALE | AH2: 14/02/25 INICIA | AI2: 14/02/25 ENTRA | AJ2: 14/02/25 SALE | AK2: 15/02/25 INICIA | AL2: 15/02/25 ENTRA | AM2: 15/02/25 SALE | AN2: 16/02/25 INICIA | AO2: 16/02/25 ENTRA | AP2: 16/02/25 SALE | AQ2: 18/02/25 INICIA | AR2: 18/02/25 ENTRA | AS2: 18/02/25 SALE | AT2: 19/02/25 INICIA | AU2: 19/02/25 ENTRA | AV2: 19/02/25 SALE | AW2: 20/02/25 INICIA | AX2: 20/02/25 ENTRA | AY2: 20/02/25 SALE | AZ2: 21/02/25 INICIA | BA2: 21/02/25 ENTRA | BB2: 21/02/25 SALE | BC2: 22/02/25 INICIA | BD2: 22/02/25 ENTRA | BE2: 22/02/25 SALE | BF2: 23/02/25 INICIA | BG2: 23/02/25 ENTRA | BH2: 23/02/25 SALE | BI2: 24/02/25 INICIA | BJ2: 24/02/25 ENTRA | BK2: 24/02/25 SALE | BL2: 25/02/25 INICIA | BM2: 25/02/25 ENTRA | BN2: 25/02/25 SALE | BO2: 26/02/25 INICIA | BP2: 26/02/25 ENTRA | BQ2: 26/02/25 SALE | BR2: 27/02/25 INICIA | BS2: 27/02/25 ENTRA | BT2: 27/02/25 SALE | BU2: 28/02/25 INICIA | BV2: 28/02/25 ENTRA | BW2: 28/02/25 SALE | BX2: 01/03/25 INICIA
A3: AGUA X24 | B3: 24 | C3: 0 | D3: 3 | E3: =B3+C3-D3 -> 21 | F3: 0 | G3: 1 | H3: =E3+F3-G3 -> 20 | I3: 24 | J3: 0 | K3: =H3+I3-J3 -> 44 | L3: 0 | M3: 1 | N3: =K3+L3-M3 -> 43 | O3: 0 | P3: 5 | Q3: =N3+O3-P3 -> 38 | R3: 0 | S3: 0 | T3: =Q3+R3-S3 -> 38 | U3: 5 | V3: =T3-U3 -> 33 | W3: 0 | X3: 0 | Y3: =V3+W3-X3 -> 33 | Z3: 0 | AA3: =Y3-Z3 -> 33 | AB3: 0 | AC3: 0 | AD3: =AA3+AB3-AC3 -> 33 | AE3: 0 | AF3: =AD3-AE3 -> 33 | AG3: 0 | AH3: 32 | AI3: 0 | AJ3: 1 | AK3: =AH3+AI3-AJ3 -> 31 | AL3: 0 | AM3: 5 | AN3: =AK3+AL3-AM3 -> 26 | AO3: 0 | AP3: 0 | AQ3: =AN3+AO3-AP3 -> 26 | AR3: 0 | AS3: 0 | AT3: =AQ3+AR3-AS3 -> 26 | AU3: 0 | AV3: 1 | AW3: =AT3+AU3-AV3 -> 25 | AX3: 0 | AY3: 2 | AZ3: =AW3+AX3-AY3 -> 23 | BA3: 0 | BB3: 1 | BC3: =AZ3+BA3-BB3 -> 22 | BD3: 0 | BE3: 0 | BF3: =BC3+BD3-BE3 -> 22 | BG3: 0 | BH3: 0 | BI3: =BF3+BG3-BH3 -> 22 | BJ3: 0 | BK3: 0 | BL3: =BI3+BJ3-BK3 -> 22 | BM3: 0 | BN3: 1 | BO3: =BL3+BM3-BN3 -> 21 | BP3: 0 | BQ3: 0 | BR3: =BO3+BP3-BQ3 -> 21 | BS3: 0 | BT3: 6 | BU3: =BR3+BS3-BT3 -> 15 | BV3: 0 | BW3: 1 | BX3: =BU3+BV3-BW3 -> 14
A4: COCA COLA | B4: 20 | C4: 0 | D4: 0 | E4: =B4+C4-D4 -> 20 | F4: 0 | G4: 2 | H4: =E4+F4-G4 -> 18 | I4: 0 | J4: 1 | K4: =H4+I4-J4 -> 17 | L4: 0 | M4: 0 | N4: =K4+L4-M4 -> 17 | O4: 0 | P4: 1 | Q4: =N4+O4-P4 -> 16 | R4: 0 | S4: 1 | T4: =Q4+R4-S4 -> 15 | U4: 1 | V4: =T4-U4 -> 14 | W4: 0 | X4: 0 | Y4: =V4+W4-X4 -> 14 | Z4: 0 | AA4: =Y4-Z4 -> 14 | AB4: 0 | AC4: 0 | AD4: =AA4+AB4-AC4 -> 14 | AE4: 0 | AF4: =AD4-AE4 -> 14 | AG4: 0 | AH4: =AF4-AG4 -> 14 | AI4: 0 | AJ4: 2 | AK4: =AH4+AI4-AJ4 -> 12 | AL4: 0 | AM4: 0 | AN4: =AK4+AL4-AM4 -> 12 | AO4: 0 | AP4: 2 | AQ4: =AN4+AO4-AP4 -> 10 | AR4: 0 | AS4: 0 | AT4: =AQ4+AR4-AS4 -> 10 | AU4: 0 | AV4: 2 | AW4: =AT4+AU4-AV4 -> 8 | AX4: 0 | AY4: 2 | AZ4: =AW4+AX4-AY4 -> 6 | BA4: 0 | BB4: 1 | BC4: =AZ4+BA4-BB4 -> 5 | BD4: 0 | BE4: 0 | BF4: =BC4+BD4-BE4 -> 5 | BG4: 0 | BH4: 2 | BI4: =BF4+BG4-BH4 -> 3 | BJ4: 0 | BK4: 0 | BL4: =BI4+BJ4-BK4 -> 3 | BM4: 0 | BN4: 0 | BO4: =BL4+BM4-BN4 -> 3 | BP4: 12 | BQ4: 1 | BR4: =BO4+BP4-BQ4 -> 14 | BS4: 0 | BT4: 1 | BU4: =BR4+BS4-BT4 -> 13 | BV4: 0 | BW4: 1 | BX4: =BU4+BV4-BW4 -> 12
A5: GATORADE | B5: 1 | C5: 10 | D5: 0 | E5: =B5+C5-D5 -> 11 | F5: 0 | G5: 2 | H5: =E5+F5-G5 -> 9 | I5: 0 | J5: 0 | K5: =H5+I5-J5 -> 9 | L5: 0 | M5: 2 | N5: =K5+L5-M5 -> 7 | O5: 0 | P5: 6 | Q5: =N5+O5-P5 -> 1 | R5: 0 | S5: 0 | T5: =Q5+R5-S5 -> 1 | U5: 0 | V5: =T5-U5 -> 1 | W5: 0 | X5: 0 | Y5: =V5+W5-X5 -> 1 | Z5: 0 | AA5: =Y5-Z5 -> 1 | AB5: 0 | AC5: 1 | AD5: =AA5+AB5-AC5 -> 0 | AE5: 0 | AF5: =AD5-AE5 -> 0 | AG5: 0 | AH5: =AF5-AG5 -> 0 | AI5: 12 | AJ5: 1 | AK5: =AH5+AI5-AJ5 -> 11 | AL5: 0 | AM5: 1 | AN5: =AK5+AL5-AM5 -> 10 | AO5: 0 | AP5: 2 | AQ5: =AN5+AO5-AP5 -> 8 | AR5: 0 | AS5: 0 | AT5: =AQ5+AR5-AS5 -> 8 | AU5: 0 | AV5: 0 | AW5: =AT5+AU5-AV5 -> 8 | AX5: 0 | AY5: 0 | AZ5: =AW5+AX5-AY5 -> 8 | BA5: 0 | BB5: 1 | BC5: =AZ5+BA5-BB5 -> 7 | BD5: 0 | BE5: 1 | BF5: =BC5+BD5-BE5 -> 6 | BG5: 0 | BH5: 1 | BI5: =BF5+BG5-BH5 -> 5 | BJ5: 0 | BK5: 0 | BL5: =BI5+BJ5-BK5 -> 5 | BM5: 0 | BN5: 0 | BO5: =BL5+BM5-BN5 -> 5 | BP5: 12 | BQ5: 0 | BR5: =BO5+BP5-BQ5 -> 17 | BS5: 0 | BT5: 2 | BU5: =BR5+BS5-BT5 -> 15 | BV5: 0 | BW5: 1 | BX5: =BU5+BV5-BW5 -> 14
A6: SMIRNOFF | B6: 5 | C6: 0 | D6: 3 | E6: =B6+C6-D6 -> 2 | F6: 0 | G6: 0 | H6: =E6+F6-G6 -> 2 | I6: 2 | J6: 0 | K6: =H6+I6-J6 -> 4 | L6: 0 | M6: 0 | N6: =K6+L6-M6 -> 4 | O6: 0 | P6: 0 | Q6: =N6+O6-P6 -> 4 | R6: 0 | S6: 0 | T6: =Q6+R6-S6 -> 4 | U6: 0 | V6: =T6-U6 -> 4 | W6: 0 | X6: 0 | Y6: =V6+W6-X6 -> 4 | Z6: 0 | AA6: =Y6-Z6 -> 4 | AB6: 0 | AC6: 0 | AD6: =AA6+AB6-AC6 -> 4 | AE6: 0 | AF6: =AD6-AE6 -> 4 | AG6: 0 | AH6: =AF6-AG6 -> 4 | AI6: 0 | AJ6: 0 | AK6: =AH6+AI6-AJ6 -> 4 | AL6: 0 | AM6: 1 | AN6: =AK6+AL6-AM6 -> 3 | AO6: 0 | AP6: 0 | AQ6: =AN6+AO6-AP6 -> 3 | AR6: 0 | AS6: 0 | AT6: =AQ6+AR6-AS6 -> 3 | AU6: 0 | AV6: 0 | AW6: =AT6+AU6-AV6 -> 3 | AX6: 0 | AY6: 0 | AZ6: =AW6+AX6-AY6 -> 3 | BA6: 0 | BB6: 0 | BC6: =AZ6+BA6-BB6 -> 3 | BD6: 0 | BE6: 0 | BF6: =BC6+BD6-BE6 -> 3 | BG6: 0 | BH6: 0 | BI6: =BF6+BG6-BH6 -> 3 | BJ6: 0 | BK6: 0 | BL6: =BI6+BJ6-BK6 -> 3 | BM6: 0 | BN6: 0 | BO6: =BL6+BM6-BN6 -> 3 | BP6: 0 | BQ6: 0 | BR6: =BO6+BP6-BQ6 -> 3 | BS6: 0 | BT6: 0 | BU6: =BR6+BS6-BT6 -> 3 | BV6: 0 | BW6: 0 | BX6: =BU6+BV6-BW6 -> 3
A7: GASEOSA CUATRO | B7: 5 | C7: 0 | D7: 0 | E7: =B7+C7-D7 -> 5 | F7: 0 | G7: 1 | H7: =E7+F7-G7 -> 4 | I7: 0 | J7: 0 | K7: =H7+I7-J7 -> 4 | L7: 0 | M7: 0 | N7: =K7+L7-M7 -> 4 | O7: 0 | P7: 0 | Q7: =N7+O7-P7 -> 4 | R7: 0 | S7: 0 | T7: =Q7+R7-S7 -> 4 | U7: 0 | V7: =T7-U7 -> 4 | W7: 0 | X7: 0 | Y7: =V7+W7-X7 -> 4 | Z7: 0 | AA7: =Y7-Z7 -> 4 | AB7: 0 | AC7: 0 | AD7: =AA7+AB7-AC7 -> 4 | AE7: 0 | AF7: =AD7-AE7 -> 4 | AG7: 0 | AH7: =AF7-AG7 -> 4 | AI7: 0 | AJ7: 0 | AK7: =AH7+AI7-AJ7 -> 4 | AL7: 0 | AM7: 0 | AN7: =AK7+AL7-AM7 -> 4 | AO7: 0 | AP7: 0 | AQ7: =AN7+AO7-AP7 -> 4 | AR7: 0 | AS7: 0 | AT7: =AQ7+AR7-AS7 -> 4 | AU7: 0 | AV7: 0 | AW7: =AT7+AU7-AV7 -> 4 | AX7: 0 | AY7: 0 | AZ7: =AW7+AX7-AY7 -> 4 | BA7: 0 | BB7: 0 | BC7: =AZ7+BA7-BB7 -> 4 | BD7: 0 | BE7: 0 | BF7: =BC7+BD7-BE7 -> 4 | BG7: 0 | BH7: 0 | BI7: =BF7+BG7-BH7 -> 4 | BJ7: 0 | BK7: 0 | BL7: =BI7+BJ7-BK7 -> 4 | BM7: 0 | BN7: 0 | BO7: =BL7+BM7-BN7 -> 4 | BP7: 0 | BQ7: 0 | BR7: =BO7+BP7-BQ7 -> 4 | BS7: 0 | BT7: 0 | BU7: =BR7+BS7-BT7 -> 4 | BV7: 0 | BW7: 3 | BX7: =BU7+BV7-BW7 -> 1
A8: GASEOSA CANADA DRY | B8: 5 | C8: 0 | D8: 0 | E8: =B8+C8-D8 -> 5 | F8: 0 | G8: 0 | H8: =E8+F8-G8 -> 5 | I8: 0 | J8: 0 | K8: =H8+I8-J8 -> 5 | L8: 0 | M8: 0 | N8: =K8+L8-M8 -> 5 | O8: 0 | P8: 0 | Q8: =N8+O8-P8 -> 5 | R8: 0 | S8: 0 | T8: =Q8+R8-S8 -> 5 | U8: 0 | V8: =T8-U8 -> 5 | W8: 0 | X8: 0 | Y8: =V8+W8-X8 -> 5 | Z8: 0 | AA8: =Y8-Z8 -> 5 | AB8: 0 | AC8: 0 | AD8: =AA8+AB8-AC8 -> 5 | AE8: 0 | AF8: =AD8-AE8 -> 5 | AG8: 0 | AH8: =AF8-AG8 -> 5 | AI8: 0 | AJ8: 0 | AK8: =AH8+AI8-AJ8 -> 5 | AL8: 0 | AM8: 0 | AN8: =AK8+AL8-AM8 -> 5 | AO8: 0 | AP8: 0 | AQ8: =AN8+AO8-AP8 -> 5 | AR8: 0 | AS8: 0 | AT8: =AQ8+AR8-AS8 -> 5 | AU8: 0 | AV8: 0 | AW8: =AT8+AU8-AV8 -> 5 | AX8: 0 | AY8: 0 | AZ8: =AW8+AX8-AY8 -> 5 | BA8: 0 | BB8: 0 | BC8: =AZ8+BA8-BB8 -> 5 | BD8: 0 | BE8: 0 | BF8: =BC8+BD8-BE8 -> 5 | BG8: 0 | BH8: 0 | BI8: =BF8+BG8-BH8 -> 5 | BJ8: 0 | BK8: 0 | BL8: =BI8+BJ8-BK8 -> 5 | BM8: 0 | BN8: 0 | BO8: =BL8+BM8-BN8 -> 5 | BP8: 0 | BQ8: 0 | BR8: =BO8+BP8-BQ8 -> 5 | BS8: 0 | BT8: 1 | BU8: =BR8+BS8-BT8 -> 4 | BV8: 0 | BW8: 0 | BX8: =BU8+BV8-BW8 -> 4
A9: GASEOSA SHWEPPES | B9: 9 | C9: 0 | D9: 0 | E9: =B9+C9-D9 -> 9 | F9: 0 | G9: 0 | H9: =E9+F9-G9 -> 9 | I9: 0 | J9: 0 | K9: =H9+I9-J9 -> 9 | L9: 0 | M9: 0 | N9: =K9+L9-M9 -> 9 | O9: 0 | P9: 0 | Q9: =N9+O9-P9 -> 9 | R9: 0 | S9: 0 | T9: =Q9+R9-S9 -> 9 | U9: 0 | V9: =T9-U9 -> 9 | W9: 0 | X9: 0 | Y9: =V9+W9-X9 -> 9 | Z9: 0 | AA9: =Y9-Z9 -> 9 | AB9: 0 | AC9: 0 | AD9: =AA9+AB9-AC9 -> 9 | AE9: 0 | AF9: =AD9-AE9 -> 9 | AG9: 0 | AH9: =AF9-AG9 -> 9 | AI9: 0 | AJ9: 0 | AK9: =AH9+AI9-AJ9 -> 9 | AL9: 0 | AM9: 0 | AN9: =AK9+AL9-AM9 -> 9 | AO9: 0 | AP9: 0 | AQ9: =AN9+AO9-AP9 -> 9 | AR9: 0 | AS9: 0 | AT9: =AQ9+AR9-AS9 -> 9 | AU9: 0 | AV9: 0 | AW9: =AT9+AU9-AV9 -> 9 | AX9: 0 | AY9: 0 | AZ9: =AW9+AX9-AY9 -> 9 | BA9: 0 | BB9: 0 | BC9: =AZ9+BA9-BB9 -> 9 | BD9: 0 | BE9: 0 | BF9: =BC9+BD9-BE9 -> 9 | BG9: 0 | BH9: 0 | BI9: =BF9+BG9-BH9 -> 9 | BJ9: 0 | BK9: 0 | BL9: =BI9+BJ9-BK9 -> 9 | BM9: 0 | BN9: 0 | BO9: =BL9+BM9-BN9 -> 9 | BP9: 0 | BQ9: 0 | BR9: =BO9+BP9-BQ9 -> 9 | BS9: 0 | BT9: 0 | BU9: =BR9+BS9-BT9 -> 9 | BV9: 0 | BW9: 0 | BX9: =BU9+BV9-BW9 -> 9
A10: BRETAÑA | B10: 0 | C10: 0 | D10: 0 | E10: =B10+C10-D10 -> 0 | F10: 0 | G10: 0 | H10: =E10+F10-G10 -> 0 | I10: 0 | J10: 0 | K10: =H10+I10-J10 -> 0 | L10: 0 | M10: 0 | N10: =K10+L10-M10 -> 0 | O10: 0 | P10: 0 | Q10: =N10+O10-P10 -> 0 | R10: 0 | S10: 0 | T10: =Q10+R10-S10 -> 0 | U10: 0 | V10: =T10-U10 -> 0 | W10: 0 | X10: 0 | Y10: =V10+W10-X10 -> 0 | Z10: 0 | AA10: =Y10-Z10 -> 0 | AB10: 0 | AC10: 0 | AD10: =AA10+AB10-AC10 -> 0 | AE10: 0 | AF10: =AD10-AE10 -> 0 | AG10: 0 | AH10: =AF10-AG10 -> 0 | AI10: 0 | AJ10: 0 | AK10: =AH10+AI10-AJ10 -> 0 | AL10: 0 | AM10: 0 | AN10: =AK10+AL10-AM10 -> 0 | AO10: 0 | AP10: 0 | AQ10: =AN10+AO10-AP10 -> 0 | AR10: 0 | AS10: 0 | AT10: =AQ10+AR10-AS10 -> 0 | AU10: 0 | AV10: 0 | AW10: =AT10+AU10-AV10 -> 0 | AX10: 0 | AY10: 0 | AZ10: =AW10+AX10-AY10 -> 0 | BA10: 0 | BB10: 1 | BC10: =AZ10+BA10-BB10 -> -1 | BD10: 0 | BE10: 0 | BF10: =BC10+BD10-BE10 -> -1 | BG10: 0 | BH10: 0 | BI10: =BF10+BG10-BH10 -> -1 | BJ10: 0 | BK10: 0 | BL10: =BI10+BJ10-BK10 -> -1 | BM10: 0 | BN10: 0 | BO10: =BL10+BM10-BN10 -> -1 | BP10: 12 | BQ10: 0 | BR10: =BO10+BP10-BQ10 -> 11 | BS10: 0 | BT10: 0 | BU10: =BR10+BS10-BT10 -> 11 | BV10: 0 | BW10: 0 | BX10: =BU10+BV10-BW10 -> 11
A11: SPEED MAX | B11: 16 | C11: 0 | D11: 0 | E11: =B11+C11-D11 -> 16 | F11: 0 | G11: 0 | H11: =E11+F11-G11 -> 16 | I11: 0 | J11: 0 | K11: =H11+I11-J11 -> 16 | L11: 0 | M11: 0 | N11: =K11+L11-M11 -> 16 | O11: 0 | P11: 0 | Q11: =N11+O11-P11 -> 16 | R11: 0 | S11: 0 | T11: =Q11+R11-S11 -> 16 | U11: 0 | V11: =T11-U11 -> 16 | W11: 0 | X11: 0 | Y11: =V11+W11-X11 -> 16 | Z11: 0 | AA11: =Y11-Z11 -> 16 | AB11: 0 | AC11: 0 | AD11: =AA11+AB11-AC11 -> 16 | AE11: 0 | AF11: =AD11-AE11 -> 16 | AG11: 0 | AH11: =AF11-AG11 -> 16 | AI11: 0 | AJ11: 0 | AK11: =AH11+AI11-AJ11 -> 16 | AL11: 0 | AM11: 0 | AN11: =AK11+AL11-AM11 -> 16 | AO11: 0 | AP11: 2 | AQ11: =AN11+AO11-AP11 -> 14 | AR11: 0 | AS11: 0 | AT11: =AQ11+AR11-AS11 -> 14 | AU11: 0 | AV11: 0 | AW11: =AT11+AU11-AV11 -> 14 | AX11: 0 | AY11: 0 | AZ11: =AW11+AX11-AY11 -> 14 | BA11: 0 | BB11: 0 | BC11: =AZ11+BA11-BB11 -> 14 | BD11: 0 | BE11: 0 | BF11: =BC11+BD11-BE11 -> 14 | BG11: 0 | BH11: 0 | BI11: =BF11+BG11-BH11 -> 14 | BJ11: 0 | BK11: 0 | BL11: =BI11+BJ11-BK11 -> 14 | BM11: 0 | BN11: 0 | BO11: =BL11+BM11-BN11 -> 14 | BP11: 0 | BQ11: 0 | BR11: =BO11+BP11-BQ11 -> 14 | BS11: 0 | BT11: 0 | BU11: =BR11+BS11-BT11 -> 14 | BV11: 0 | BW11: 0 | BX11: =BU11+BV11-BW11 -> 14
A12: REDBULL | B12: 5 | C12: 0 | D12: 0 | E12: =B12+C12-D12 -> 5 | F12: 0 | G12: 0 | H12: =E12+F12-G12 -> 5 | I12: 0 | J12: 0 | K12: =H12+I12-J12 -> 5 | L12: 0 | M12: 0 | N12: =K12+L12-M12 -> 5 | O12: 0 | P12: 0 | Q12: =N12+O12-P12 -> 5 | R12: 0 | S12: 0 | T12: =Q12+R12-S12 -> 5 | U12: 0 | V12: =T12-U12 -> 5 | W12: 0 | X12: 0 | Y12: =V12+W12-X12 -> 5 | Z12: 0 | AA12: =Y12-Z12 -> 5 | AB12: 0 | AC12: 0 | AD12: =AA12+AB12-AC12 -> 5 | AE12: 0 | AF12: =AD12-AE12 -> 5 | AG12: 0 | AH12: =AF12-AG12 -> 5 | AI12: 0 | AJ12: 0 | AK12: =AH12+AI12-AJ12 -> 5 | AL12: 0 | AM12: 0 | AN12: =AK12+AL12-AM12 -> 5 | AO12: 0 | AP12: 0 | AQ12: =AN12+AO12-AP12 -> 5 | AR12: 0 | AS12: 0 | AT12: =AQ12+AR12-AS12 -> 5 | AU12: 0 | AV12: 0 | AW12: =AT12+AU12-AV12 -> 5 | AX12: 0 | AY12: 0 | AZ12: =AW12+AX12-AY12 -> 5 | BA12: 0 | BB12: 0 | BC12: =AZ12+BA12-BB12 -> 5 | BD12: 0 | BE12: 0 | BF12: =BC12+BD12-BE12 -> 5 | BG12: 0 | BH12: 0 | BI12: =BF12+BG12-BH12 -> 5 | BJ12: 0 | BK12: 0 | BL12: =BI12+BJ12-BK12 -> 5 | BM12: 0 | BN12: 0 | BO12: =BL12+BM12-BN12 -> 5 | BP12: 0 | BQ12: 0 | BR12: =BO12+BP12-BQ12 -> 5 | BS12: 0 | BT12: 0 | BU12: =BR12+BS12-BT12 -> 5 | BV12: 0 | BW12: 0 | BX12: =BU12+BV12-BW12 -> 5
A13: ELECTROLIT | B13: 10 | C13: 0 | D13: 0 | E13: =B13+C13-D13 -> 10 | F13: 0 | G13: 0 | H13: =E13+F13-G13 -> 10 | I13: 0 | J13: 0 | K13: =H13+I13-J13 -> 10 | L13: 0 | M13: 0 | N13: =K13+L13-M13 -> 10 | O13: 0 | P13: 0 | Q13: =N13+O13-P13 -> 10 | R13: 0 | S13: 0 | T13: =Q13+R13-S13 -> 10 | U13: 0 | V13: =T13-U13 -> 10 | W13: 0 | X13: 0 | Y13: =V13+W13-X13 -> 10 | Z13: 0 | AA13: =Y13-Z13 -> 10 | AB13: 0 | AC13: 0 | AD13: =AA13+AB13-AC13 -> 10 | AE13: 0 | AF13: =AD13-AE13 -> 10 | AG13: 0 | AH13: =AF13-AG13 -> 10 | AI13: 0 | AJ13: 0 | AK13: =AH13+AI13-AJ13 -> 10 | AL13: 0 | AM13: 1 | AN13: =AK13+AL13-AM13 -> 9 | AO13: 0 | AP13: 1 | AQ13: =AN13+AO13-AP13 -> 8 | AR13: 0 | AS13: 0 | AT13: =AQ13+AR13-AS13 -> 8 | AU13: 0 | AV13: 0 | AW13: =AT13+AU13-AV13 -> 8 | AX13: 0 | AY13: 0 | AZ13: =AW13+AX13-AY13 -> 8 | BA13: 0 | BB13: 0 | BC13: =AZ13+BA13-BB13 -> 8 | BD13: 0 | BE13: 1 | BF13: =BC13+BD13-BE13 -> 7 | BG13: 0 | BH13: 0 | BI13: =BF13+BG13-BH13 -> 7 | BJ13: 0 | BK13: 0 | BL13: =BI13+BJ13-BK13 -> 7 | BM13: 0 | BN13: 0 | BO13: =BL13+BM13-BN13 -> 7 | BP13: 0 | BQ13: 0 | BR13: =BO13+BP13-BQ13 -> 7 | BS13: 0 | BT13: 0 | BU13: =BR13+BS13-BT13 -> 7 | BV13: 0 | BW13: 0 | BX13: =BU13+BV13-BW13 -> 7
A14: POKER LATA | B14: 11 | C14: 0 | D14: 0 | E14: =B14+C14-D14 -> 11 | F14: 0 | G14: 0 | H14: =E14+F14-G14 -> 11 | I14: 0 | J14: 0 | K14: =H14+I14-J14 -> 11 | L14: 0 | M14: 0 | N14: =K14+L14-M14 -> 11 | O14: 0 | P14: 0 | Q14: =N14+O14-P14 -> 11 | R14: 0 | S14: 0 | T14: =Q14+R14-S14 -> 11 | U14: 1 | V14: =T14-U14 -> 10 | W14: 0 | X14: 0 | Y14: =V14+W14-X14 -> 10 | Z14: 0 | AA14: =Y14-Z14 -> 10 | AB14: 0 | AC14: 0 | AD14: =AA14+AB14-AC14 -> 10 | AE14: 0 | AF14: =AD14-AE14 -> 10 | AG14: 0 | AH14: =AF14-AG14 -> 10 | AI14: 0 | AJ14: 0 | AK14: =AH14+AI14-AJ14 -> 10 | AL14: 0 | AM14: 0 | AN14: =AK14+AL14-AM14 -> 10 | AO14: 0 | AP14: 0 | AQ14: =AN14+AO14-AP14 -> 10 | AR14: 0 | AS14: 0 | AT14: =AQ14+AR14-AS14 -> 10 | AU14: 0 | AV14: 0 | AW14: =AT14+AU14-AV14 -> 10 | AX14: 0 | AY14: 0 | AZ14: =AW14+AX14-AY14 -> 10 | BA14: 0 | BB14: 0 | BC14: =AZ14+BA14-BB14 -> 10 | BD14: 0 | BE14: 0 | BF14: =BC14+BD14-BE14 -> 10 | BG14: 0 | BH14: 0 | BI14: =BF14+BG14-BH14 -> 10 | BJ14: 0 | BK14: 0 | BL14: =BI14+BJ14-BK14 -> 10 | BM14: 0 | BN14: 0 | BO14: =BL14+BM14-BN14 -> 10 | BP14: 0 | BQ14: 0 | BR14: =BO14+BP14-BQ14 -> 10 | BS14: 0 | BT14: 0 | BU14: =BR14+BS14-BT14 -> 10 | BV14: 0 | BW14: 0 | BX14: =BU14+BV14-BW14 -> 10
A15: AGUILA LATA | B15: 0 | C15: 0 | D15: 0 | E15: =B15+C15-D15 -> 0 | F15: 0 | G15: 0 | H15: =E15+F15-G15 -> 0 | I15: 0 | J15: 0 | K15: =H15+I15-J15 -> 0 | L15: 0 | M15: 0 | N15: =K15+L15-M15 -> 0 | O15: 0 | P15: 0 | Q15: =N15+O15-P15 -> 0 | R15: 0 | S15: 0 | T15: =Q15+R15-S15 -> 0 | U15: 0 | V15: =T15-U15 -> 0 | W15: 0 | X15: 0 | Y15: =V15+W15-X15 -> 0 | Z15: 0 | AA15: =Y15-Z15 -> 0 | AB15: 0 | AC15: 0 | AD15: =AA15+AB15-AC15 -> 0 | AE15: 0 | AF15: =AD15-AE15 -> 0 | AG15: 0 | AH15: =AF15-AG15 -> 0 | AI15: 0 | AJ15: 0 | AK15: =AH15+AI15-AJ15 -> 0 | AL15: 0 | AM15: 0 | AN15: =AK15+AL15-AM15 -> 0 | AO15: 0 | AP15: 0 | AQ15: =AN15+AO15-AP15 -> 0 | AR15: 0 | AS15: 0 | AT15: =AQ15+AR15-AS15 -> 0 | AU15: 0 | AV15: 0 | AW15: =AT15+AU15-AV15 -> 0 | AX15: 0 | AY15: 0 | AZ15: =AW15+AX15-AY15 -> 0 | BA15: 0 | BB15: 0 | BC15: =AZ15+BA15-BB15 -> 0 | BD15: 0 | BE15: 0 | BF15: =BC15+BD15-BE15 -> 0 | BG15: 0 | BH15: 0 | BI15: =BF15+BG15-BH15 -> 0 | BJ15: 0 | BK15: 0 | BL15: =BI15+BJ15-BK15 -> 0 | BM15: 0 | BN15: 0 | BO15: =BL15+BM15-BN15 -> 0 | BP15: 0 | BQ15: 0 | BR15: =BO15+BP15-BQ15 -> 0 | BS15: 0 | BT15: 0 | BU15: =BR15+BS15-BT15 -> 0 | BV15: 0 | BW15: 0 | BX15: =BU15+BV15-BW15 -> 0
... A55: BOTELLA AGT. AMARILLO | B55: 1 | C55: 0 | D55: 0 | E55: =B55+C55-D55 -> 1 | F55: 0 | G55: 0 | H55: =E55+F55-G55 -> 1 | I55: 0 | J55: 0 | K55: =H55+I55-J55 -> 1 | L55: 0 | M55: 0 | N55: =K55+L55-M55 -> 1 | O55: 0 | P55: 0 | Q55: =N55+O55-P55 -> 1 | R55: 0 | S55: 0 | T55: =Q55+R55-S55 -> 1 | U55: 0 | V55: =T55-U55 -> 1 | W55: 0 | X55: 0 | Y55: =V55+W55-X55 -> 1 | Z55: 0 | AA55: =Y55-Z55 -> 1 | AB55: 0 | AC55: 0 | AD55: =AA55+AB55-AC55 -> 1 | AE55: 0 | AF55: =AD55-AE55 -> 1 | AG55: 0 | AH55: =AF55-AG55 -> 1 | AI55: 0 | AJ55: 0 | AK55: =AH55+AI55-AJ55 -> 1 | AL55: 0 | AM55: 0 | AN55: =AK55+AL55-AM55 -> 1 | AO55: 0 | AP55: 0 | AQ55: =AN55+AO55-AP55 -> 1 | AR55: 0 | AS55: 0 | AT55: =AQ55+AR55-AS55 -> 1 | AU55: 0 | AV55: 0 | AW55: =AT55+AU55-AV55 -> 1 | AX55: 0 | AY55: 0 | AZ55: =AW55+AX55-AY55 -> 1 | BA55: 0 | BB55: 0 | BC55: =AZ55+BA55-BB55 -> 1 | BD55: 0 | BE55: 0 | BF55: =BC55+BD55-BE55 -> 1 | BG55: 0 | BH55: 0 | BI55: =BF55+BG55-BH55 -> 1 | BJ55: 0 | BK55: 0 | BL55: =BI55+BJ55-BK55 -> 1 | BM55: 0 | BN55: 0 | BO55: =BL55+BM55-BN55 -> 1 | BP55: 0 | BQ55: 0 | BR55: =BO55+BP55-BQ55 -> 1 | BS55: 0 | BT55: 0 | BU55: =BR55+BS55-BT55 -> 1 | BV55: 0 | BW55: 0 | BX55: =BU55+BV55-BW55 -> 1
A56: STELLA | M56: 4 | N56: 0 | O56: 0 | P56: 0 | Q56: 0 | R56: 0 | S56: 0 | T56: =Q56+R56-S56 -> 0 | U56: 0 | V56: =T56-U56 -> 0 | W56: 0 | X56: 0 | Y56: =V56+W56-X56 -> 0 | Z56: 0 | AA56: =Y56-Z56 -> 0 | AB56: 0 | AC56: 0 | AD56: =AA56+AB56-AC56 -> 0 | AE56: 0 | AF56: =AD56-AE56 -> 0 | AG56: 0 | AH56: =AF56-AG56 -> 0

Sheet INV. ENE
A1: INVENTARIO | T1: DANIELA
A2: PRODUCTO | B2: 09/01/25 INICIA | C2: 09/01/25 SALE | D2: 10/01/25 INICIA | E2: 10/01/25 SALE | F2: 11/01/25 INICIA | G2: 11/01/25 SALE | H2: 12/01/25 INICIA | I2: 12/01/25 ENTRA | J2: 12/01/25 SALE | K2: 13/01/25 INICIA | L2: 13/01/25 ENTRA | M2: 13/01/25 SALE | N2: 14/01/25 INICIA | O2: 14/01/25 SALE | P2: 14/01/25 ENTRA | Q2: 15/01/25 INICIA | R2: 15/01/25 SALE | S2: 15/01/25 ENTRA | T2: 16/01/25 INICIA | U2: 16/01/25 SALE | V2: 16/01/25 ENTRA | W2: 17/01/25 INICIA | X2: 17/01/25 ENTRA | Y2: 17/01/25 SALE | Z2: 18/01/25 INICIA | AA2: 18/01/25 ENTRA | AB2: 18/01/25 SALE | AC2: 19/01/25 INICIA | AD2: 19/01/25 ENTRA | AE2: 19/01/25 SALE | AF2: 20/01/25 INICIA | AG2: 20/01/25 ENTRA | AH2: 20/01/25 SALE | AI2: 21/01/25 INICIA | AJ2: 21/01/25 ENTRA | AK2: 21/01/25 SALE | AL2: 22/01/25 INICIA | AM2: 22/01/25 ENTRA | AN2: 22/01/25 SALE | AO2: 23/01/25 INICIA | AP2: 23/01/25 ENTRA | AQ2: 23/01/25 SALE | AR2: 24/01/25 INICIA | AS2: 24/01/25 ENTRA | AT2: 24/01/25 SALE | AU2: 25/01/25 INICIA | AV2: 25/01/25 ENTRA | AW2: 25/01/25 SALE | AX2: 26/01/25 INICIA | AY2: 26/01/25 ENTRA | AZ2: 26/01/25 SALE | BA2: 27/01/25 INICIA | BB2: 27/01/25 ENTRA | BC2: 27/01/25 SALE | BD2: 28/01/25 INICIA | BE2: 28/01/25 ENTRA | BF2: 28/01/25 SALE | BG2: 29/01/25 INICIA | BH2: 29/01/25 ENTRA | BI2: 29/01/25 SALE | BJ2: 30/01/25 INICIA | BK2: 30/01/25 ENTRA | BL2: 30/01/25 SALE | BM2: 31/01/25 INICIA | BN2: 31/01/25 SALE | BO2: 01/02/25 INICIA
A3: AGUA X24 | B3: 66 | C3: 0 | D3: =B3-C3 -> 66 | E3: 0 | F3: =D3-E3 -> 66 | G3: 0 | H3: =F3-G3 -> 66 | I3: 0 | J3: 8 | K3: 57 | L3: 0 | M3: 2 | N3: =K3+L3-M3 -> 55 | O3: 2 | P3: 0 | Q3: =N3+P3-O3 -> 53 | R3: 1 | S3: 0 | T3: =Q3+S3-R3 -> 52 | U3: 0 | V3: 0 | W3: =T3+V3-U3 -> 52 | X3: 0 | Y3: 0 | Z3: =W3+X3-Y3 -> 52 | AA3: 0 | AB3: 1 | AC3: =Z3+AA3-AB3 -> 51 | AD3: 0 | AE3: 0 | AF3: =AC3+AD3-AE3 -> 51 | AG3: 0 | AH3: 0 | AI3: =AF3+AG3-AH3 -> 51 | AJ3: 0 | AK3: 5 | AL3: =AI3+AJ3-AK3 -> 46 | AM3: 0 | AN3: 0 | AO3: =AL3+AM3-AN3 -> 46 | AP3: 0 | AQ3: 12 | AR3: =AO3+AP3-AQ3 -> 34 | AS3: 0 | AT3: 0 | AU3: =AR3+AS3-AT3 -> 34 | AV3: 0 | AW3: 2 | AX3: =AU3+AV3-AW3 -> 32 | AY3: 0 | AZ3: 0 | BA3: =AX3+AY3-AZ3 -> 32 | BB3: 0 | BC3: 3 | BD3: =BA3+BB3-BC3 -> 29 | BE3: 0 | BF3: 0 | BG3: =BD3+BE3-BF3 -> 29 | BH3: 0 | BI3: 1 | BJ3: =BG3+BH3-BI3 -> 28 | BK3: 0 | BL3: 1 | BM3: =BJ3+BK3-BL3 -> 27 | BN3: 3 | BO3: =BM3-BN3 -> 24
A4: COCA COLA | B4: 28 | C4: 1 | D4: =B4-C4 -> 27 | E4: 0 | F4: =D4-E4 -> 27 | G4: 0 | H4: =F4-G4 -> 27 | I4: 0 | J4: 0 | K4: =H4+I4-J4 -> 27 | L4: 0 | M4: 0 | N4: =K4+L4-M4 -> 27 | O4: 0 | P4: 0 | Q4: =N4+P4-O4 -> 27 | R4: 0 | S4: 0 | T4: =Q4+S4-R4 -> 27 | U4: 0 | V4: 0 | W4: =T4+V4-U4 -> 27 | X4: 0 | Y4: 0 | Z4: =W4+X4-Y4 -> 27 | AA4: 0 | AB4: 0 | AC4: =Z4+AA4-AB4 -> 27 | AD4: 0 | AE4: 0 | AF4: =AC4+AD4-AE4 -> 27 | AG4: 0 | AH4: 0 | AI4: =AF4+AG4-AH4 -> 27 | AJ4: 0 | AK4: 0 | AL4: =AI4+AJ4-AK4 -> 27 | AM4: 0 | AN4: 0 | AO4: =AL4+AM4-AN4 -> 27 | AP4: 0 | AQ4: 0 | AR4: =AO4+AP4-AQ4 -> 27 | AS4: 0 | AT4: 0 | AU4: =AR4+AS4-AT4 -> 27 | AV4: 0 | AW4: 1 | AX4: =AU4+AV4-AW4 -> 26 | AY4: 0 | AZ4: 1 | BA4: =AX4+AY4-AZ4 -> 25 | BB4: 0 | BC4: 2 | BD4: =BA4+BB4-BC4 -> 23 | BE4: 0 | BF4: 0 | BG4: =BD4+BE4-BF4 -> 23 | BH4: 0 | BI4: 0 | BJ4: =BG4+BH4-BI4 -> 23 | BK4: 0 | BL4: 0 | BM4: =BJ4+BK4-BL4 -> 23 | BN4: 0 | BO4: =BM4-BN4 -> 23
A5: GATORADE | B5: 5 | C5: 0 | D5: =B5-C5 -> 5 | E5: 1 | F5: =D5-E5 -> 4 | G5: 0 | H5: =F5-G5 -> 4 | I5: 0 | J5: 1 | K5: =H5+I5-J5 -> 3 | L5: 1 | M5: 4 | N5: =K5+L5-M5 -> 0 | O5: 0 | P5: 11 | Q5: =N5+P5-O5 -> 11 | R5: 2 | S5: 0 | T5: =Q5+S5-R5 -> 9 | U5: 1 | V5: 0 | W5: =T5+V5-U5 -> 8 | X5: 0 | Y5: 0 | Z5: =W5+X5-Y5 -> 8 | AA5: 0 | AB5: 1 | AC5: =Z5+AA5-AB5 -> 7 | AD5: 0 | AE5: 0 | AF5: =AC5+AD5-AE5 -> 7 | AG5: 0 | AH5: 2 | AI5: =AF5+AG5-AH5 -> 5 | AJ5: 0 | AK5: 0 | AL5: =AI5+AJ5-AK5 -> 5 | AM5: 0 | AN5: 0 | AO5: =AL5+AM5-AN5 -> 5 | AP5: 0 | AQ5: 0 | AR5: =AO5+AP5-AQ5 -> 5 | AS5: 0 | AT5: 1 | AU5: =AR5+AS5-AT5 -> 4 | AV5: 0 | AW5: 0 | AX5: =AU5+AV5-AW5 -> 4 | AY5: 0 | AZ5: 0 | BA5: =AX5+AY5-AZ5 -> 4 | BB5: 0 | BC5: 0 | BD5: =BA5+BB5-BC5 -> 4 | BE5: 0 | BF5: 2 | BG5: =BD5+BE5-BF5 -> 2 | BH5: 0 | BI5: 0 | BJ5: =BG5+BH5-BI5 -> 2 | BK5: 0 | BL5: 0 | BM5: =BJ5+BK5-BL5 -> 2 | BN5: 1 | BO5: =BM5-BN5 -> 1
A6: SMIRNOFF | B6: 4 | C6: 0 | D6: =B6-C6 -> 4 | E6: 0 | F6: =D6-E6 -> 4 | G6: 0 | H6: =F6-G6 -> 4 | I6: 0 | J6: 0 | K6: =H6+I6-J6 -> 4 | L6: 7 | M6: 3 | N6: =K6+L6-M6 -> 8 | O6: 0 | P6: 0 | Q6: =N6+P6-O6 -> 8 | S6: 0 | T6: =Q6+S6-R6 -> 8 | U6: 0 | V6: 0 | W6: =T6+V6-U6 -> 8 | X6: 0 | Y6: 0 | Z6: =W6+X6-Y6 -> 8 | AA6: 0 | AB6: 1 | AC6: =Z6+AA6-AB6 -> 7 | AD6: 0 | AE6: 0 | AF6: =AC6+AD6-AE6 -> 7 | AG6: 0 | AH6: 0 | AI6: =AF6+AG6-AH6 -> 7 | AJ6: 0 | AK6: 0 | AL6: =AI6+AJ6-AK6 -> 7 | AM6: 0 | AN6: 0 | AO6: =AL6+AM6-AN6 -> 7 | AP6: 0 | AQ6: 1 | AR6: =AO6+AP6-AQ6 -> 6 | AS6: 0 | AT6: 0 | AU6: =AR6+AS6-AT6 -> 6 | AV6: 0 | AW6: 0 | AX6: =AU6+AV6-AW6 -> 6 | AY6: 0 | AZ6: 0 | BA6: =AX6+AY6-AZ6 -> 6 | BB6: 0 | BC6: 0 | BD6: =BA6+BB6-BC6 -> 6 | BE6: 0 | BF6: 1 | BG6: =BD6+BE6-BF6 -> 5 | BH6: 0 | BI6: 0 | BJ6: =BG6+BH6-BI6 -> 5 | BK6: 0 | BL6: 0 | BM6: =BJ6+BK6-BL6 -> 5 | BN6: 0 | BO6: =BM6-BN6 -> 5
A7: GASEOSA CUATRO | B7: 10 | C7: 0 | D7: =B7-C7 -> 10 | E7: 1 | F7: =D7-E7 -> 9 | G7: 1 | H7: =F7-G7 -> 8 | I7: 0 | J7: 1 | K7: =H7+I7-J7 -> 7 | L7: 0 | M7: 0 | N7: =K7+L7-M7 -> 7 | O7: 1 | P7: 0 | Q7: =N7+P7-O7 -> 6 | R7: 0 | S7: 0 | T7: =Q7+S7-R7 -> 6 | U7: 0 | V7: 0 | W7: =T7+V7-U7 -> 6 | X7: 0 | Y7: 0 | Z7: =W7+X7-Y7 -> 6 | AA7: 0 | AB7: 0 | AC7: =Z7+AA7-AB7 -> 6 | AD7: 0 | AE7: 0 | AF7: =AC7+AD7-AE7 -> 6 | AG7: 0 | AH7: 0 | AI7: =AF7+AG7-AH7 -> 6 | AJ7: 0 | AK7: 0 | AL7: =AI7+AJ7-AK7 -> 6 | AM7: 0 | AN7: 0 | AO7: =AL7+AM7-AN7 -> 6 | AP7: 0 | AQ7: 0 | AR7: =AO7+AP7-AQ7 -> 6 | AS7: 0 | AT7: 0 | AU7: =AR7+AS7-AT7 -> 6 | AV7: 0 | AW7: 0 | AX7: =AU7+AV7-AW7 -> 6 | AY7: 0 | AZ7: 0 | BA7: =AX7+AY7-AZ7 -> 6 | BB7: 0 | BC7: 0 | BD7: =BA7+BB7-BC7 -> 6 | BE7: 0 | BF7: 0 | BG7: =BD7+BE7-BF7 -> 6 | BH7: 0 | BI7: 0 | BJ7: =BG7+BH7-BI7 -> 6 | BK7: 0 | BL7: 0 | BM7: =BJ7+BK7-BL7 -> 6 | BN7: 0 | BO7: =BM7-BN7 -> 6
A8: GASEOSA CANADA DRY | B8: 20 | C8: 2 | D8: =B8-C8 -> 18 | E8: 4 | F8: =D8-E8 -> 14 | G8: 0 | H8: =F8-G8 -> 14 | I8: 0 | J8: 0 | K8: =H8+I8-J8 -> 14 | L8: 0 | M8: 0 | N8: =K8+L8-M8 -> 14 | O8: 0 | P8: 0 | Q8: =N8+P8-O8 -> 14 | R8: 1 | S8: 0 | T8: =Q8+S8-R8 -> 13 | U8: 2 | V8: 0 | W8: =T8+V8-U8 -> 11 | X8: 0 | Y8: 1 | Z8: =W8+X8-Y8 -> 10 | AA8: 0 | AB8: 0 | AC8: =Z8+AA8-AB8 -> 10 | AD8: 0 | AE8: 1 | AF8: =AC8+AD8-AE8 -> 9 | AG8: 0 | AH8: 0 | AI8: =AF8+AG8-AH8 -> 9 | AJ8: 0 | AK8: 0 | AL8: =AI8+AJ8-AK8 -> 9 | AM8: 0 | AN8: 1 | AO8: =AL8+AM8-AN8 -> 8 | AP8: 0 | AQ8: 0 | AR8: =AO8+AP8-AQ8 -> 8 | AS8: 0 | AT8: 0 | AU8: =AR8+AS8-AT8 -> 8 | AV8: 0 | AW8: 1 | AX8: =AU8+AV8-AW8 -> 7 | AY8: 0 | AZ8: 0 | BA8: =AX8+AY8-AZ8 -> 7 | BB8: 0 | BC8: 0 | BD8: =BA8+BB8-BC8 -> 7 | BE8: 0 | BF8: 0 | BG8: =BD8+BE8-BF8 -> 7 | BH8: 0 | BI8: 0 | BJ8: =BG8+BH8-BI8 -> 7 | BK8: 0 | BL8: 0 | BM8: =BJ8+BK8-BL8 -> 7 | BN8: 0 | BO8: =BM8-BN8 -> 7
A9: GASEOSA SHWEPPES | B9: 10 | C9: 0 | D9: =B9-C9 -> 10 | E9: 0 | F9: =D9-E9 -> 10 | G9: 0 | H9: =F9-G9 -> 10 | I9: 0 | J9: 0 | K9: =H9+I9-J9 -> 10 | L9: 0 | M9: 0 | N9: =K9+L9-M9 -> 10 | O9: 0 | P9: 0 | Q9: =N9+P9-O9 -> 10 | R9: 0 | S9: 0 | T9: =Q9+S9-R9 -> 10 | U9: 0 | V9: 0 | W9: =T9+V9-U9 -> 10 | X9: 0 | Y9: 0 | Z9: =W9+X9-Y9 -> 10 | AA9: 0 | AB9: 0 | AC9: =Z9+AA9-AB9 -> 10 | AD9: 0 | AE9: 1 | AF9: =AC9+AD9-AE9 -> 9 | AG9: 0 | AH9: 0 | AI9: =AF9+AG9-AH9 -> 9 | AJ9: 0 | AK9: 0 | AL9: =AI9+AJ9-AK9 -> 9 | AM9: 0 | AN9: 0 | AO9: =AL9+AM9-AN9 -> 9 | AP9: 0 | AQ9: 0 | AR9: =AO9+AP9-AQ9 -> 9 | AS9: 0 | AT9: 0 | AU9: =AR9+AS9-AT9 -> 9 | AV9: 0 | AW9: 0 | AX9: =AU9+AV9-AW9 -> 9 | AY9: 0 | AZ9: 0 | BA9: =AX9+AY9-AZ9 -> 9 | BB9: 0 | BC9: 0 | BD9: =BA9+BB9-BC9 -> 9 | BE9: 0 | BF9: 0 | BG9: =BD9+BE9-BF9 -> 9 | BH9: 0 | BI9: 0 | BJ9: =BG9+BH9-BI9 -> 9 | BK9: 0 | BL9: 0 | BM9: =BJ9+BK9-BL9 -> 9 | BN9: 0 | BO9: =BM9-BN9 -> 9
A10: BRETAÑA | B10: 19 | C10: 0 | D10: =B10-C10 -> 19 | E10: 1 | F10: =D10-E10 -> 18 | G10: 0 | H10: =F10-G10 -> 18 | I10: 0 | J10: 1 | K10: =H10+I10-J10 -> 17 | L10: 0 | M10: 0 | N10: =K10+L10-M10 -> 17 | O10: 0 | P10: 0 | Q10: =N10+P10-O10 -> 17 | R10: 0 | S10: 0 | T10: =Q10+S10-R10 -> 17 | U10: 0 | V10: 0 | W10: =T10+V10-U10 -> 17 | X10: 0 | Y10: 0 | Z10: =W10+X10-Y10 -> 17 | AA10: 0 | AB10: 1 | AC10: =Z10+AA10-AB10 -> 16 | AD10: 0 | AE10: 1 | AF10: =AC10+AD10-AE10 -> 15 | AG10: 0 | AH10: 0 | AI10: =AF10+AG10-AH10 -> 15 | AJ10: 0 | AK10: 1 | AL10: =AI10+AJ10-AK10 -> 14 | AM10: 0 | AN10: 0 | AO10: =AL10+AM10-AN10 -> 14 | AP10: 0 | AQ10: 5 | AR10: =AO10+AP10-AQ10 -> 9 | AS10: 0 | AT10: 2 | AU10: =AR10+AS10-AT10 -> 7 | AV10: 0 | AW10: 0 | AX10: =AU10+AV10-AW10 -> 7 | AY10: 0 | AZ10: 1 | BA10: =AX10+AY10-AZ10 -> 6 | BB10: 0 | BC10: 0 | BD10: =BA10+BB10-BC10 -> 6 | BE10: 0 | BF10: 0 | BG10: =BD10+BE10-BF10 -> 6 | BH10: 0 | BI10: 2 | BJ10: =BG10+BH10-BI10 -> 4 | BK10: 0 | BL10: 0 | BM10: =BJ10+BK10-BL10 -> 4 | BN10: 0 | BO10: =BM10-BN10 -> 4
A11: SPEED MAX | B11: 19 | C11: 0 | D11: =B11-C11 -> 19 | E11: 0 | F11: =D11-E11 -> 19 | G11: 0 | H11: =F11-G11 -> 19 | I11: 0 | J11: 0 | K11: =H11+I11-J11 -> 19 | L11: 0 | M11: 0 | N11: =K11+L11-M11 -> 19 | O11: 0 | P11: 0 | Q11: =N11+P11-O11 -> 19 | R11: 0 | S11: 0 | T11: =Q11+S11-R11 -> 19 | U11: 0 | V11: 0 | W11: =T11+V11-U11 -> 19 | X11: 0 | Y11: 0 | Z11: =W11+X11-Y11 -> 19 | AA11: 0 | AB11: 0 | AC11: =Z11+AA11-AB11 -> 19 | AD11: 0 | AE11: 0 | AF11: =AC11+AD11-AE11 -> 19 | AG11: 0 | AH11: 2 | AI11: =AF11+AG11-AH11 -> 17 | AJ11: 0 | AK11: 1 | AL11: =AI11+AJ11-AK11 -> 16 | AM11: 0 | AN11: 0 | AO11: =AL11+AM11-AN11 -> 16 | AP11: 0 | AQ11: 0 | AR11: =AO11+AP11-AQ11 -> 16 | AS11: 0 | AT11: 0 | AU11: =AR11+AS11-AT11 -> 16 | AV11: 0 | AW11: 0 | AX11: =AU11+AV11-AW11 -> 16 | AY11: 0 | AZ11: 0 | BA11: =AX11+AY11-AZ11 -> 16 | BB11: 0 | BC11: 0 | BD11: =BA11+BB11-BC11 -> 16 | BE11: 0 | BF11: 0 | BG11: =BD11+BE11-BF11 -> 16 | BH11: 0 | BI11: 0 | BJ11: =BG11+BH11-BI11 -> 16 | BK11: 0 | BL11: 0 | BM11: =BJ11+BK11-BL11 -> 16 | BN11: 0 | BO11: =BM11-BN11 -> 16
A12: REDBULL | B12: 6 | C12: 0 | D12: =B12-C12 -> 6 | E12: 0 | F12: =D12-E12 -> 6 | G12: 0 | H12: =F12-G12 -> 6 | I12: 0 | J12: 1 | K12: =H12+I12-J12 -> 5 | L12: 0 | M12: 0 | N12: =K12+L12-M12 -> 5 | O12: 0 | P12: 0 | Q12: =N12+P12-O12 -> 5 | R12: 0 | S12: 0 | T12: =Q12+S12-R12 -> 5 | U12: 0 | V12: 0 | W12: =T12+V12-U12 -> 5 | X12: 0 | Y12: 0 | Z12: =W12+X12-Y12 -> 5 | AA12: 0 | AB12: 0 | AC12: =Z12+AA12-AB12 -> 5 | AD12: 0 | AE12: 0 | AF12: =AC12+AD12-AE12 -> 5 | AG12: 0 | AH12: 0 | AI12: =AF12+AG12-AH12 -> 5 | AJ12: 0 | AK12: 0 | AL12: =AI12+AJ12-AK12 -> 5 | AM12: 0 | AN12: 0 | AO12: =AL12+AM12-AN12 -> 5 | AP12: 0 | AQ12: 0 | AR12: =AO12+AP12-AQ12 -> 5 | AS12: 0 | AT12: 0 | AU12: =AR12+AS12-AT12 -> 5 | AV12: 0 | AW12: 0 | AX12: =AU12+AV12-AW12 -> 5 | AY12: 0 | AZ12: 0 | BA12: =AX12+AY12-AZ12 -> 5 | BB12: 0 | BC12: 0 | BD12: =BA12+BB12-BC12 -> 5 | BE12: 0 | BF12: 0 | BG12: =BD12+BE12-BF12 -> 5 | BH12: 0 | BI12: 0 | BJ12: =BG12+BH12-BI12 -> 5 | BK12: 0 | BL12: 0 | BM12: =BJ12+BK12-BL12 -> 5 | BN12: 0 | BO12: =BM12-BN12 -> 5
A13: ELECTROLIT | B13: 13 | C13: 0 | D13: =B13-C13 -> 13 | E13: 0 | F13: =D13-E13 -> 13 | G13: 0 | H13: =F13-G13 -> 13 | I13: 0 | J13: 3 | K13: =H13+I13-J13 -> 10 | L13: 7 | M13: 16 | N13: =K13+L13-M13 -> 1 | O13: 0 | P13: 12 | Q13: =N13+P13-O13 -> 13 | R13: 0 | S13: 0 | T13: =Q13+S13-R13 -> 13 | U13: 0 | V13: 0 | W13: =T13+V13-U13 -> 13 | X13: 0 | Y13: 0 | Z13: =W13+X13-Y13 -> 13 | AA13: 0 | AB13: 0 | AC13: =Z13+AA13-AB13 -> 13 | AD13: 0 | AE13: 0 | AF13: =AC13+AD13-AE13 -> 13 | AG13: 0 | AH13: 1 | AI13: =AF13+AG13-AH13 -> 12 | AJ13: 0 | AK13: 1 | AL13: =AI13+AJ13-AK13 -> 11 | AM13: 0 | AN13: 0 | AO13: =AL13+AM13-AN13 -> 11 | AP13: 0 | AQ13: 0 | AR13: =AO13+AP13-AQ13 -> 11 | AS13: 0 | AT13: 0 | AU13: =AR13+AS13-AT13 -> 11 | AV13: 0 | AW13: 0 | AX13: =AU13+AV13-AW13 -> 11 | AY13: 0 | AZ13: 0 | BA13: =AX13+AY13-AZ13 -> 11 | BB13: 0 | BC13: 0 | BD13: =BA13+BB13-BC13 -> 11 | BE13: 0 | BF13: 0 | BG13: =BD13+BE13-BF13 -> 11 | BH13: 0 | BI13: 1 | BJ13: =BG13+BH13-BI13 -> 10 | BK13: 0 | BL13: 0 | BM13: =BJ13+BK13-BL13 -> 10 | BN13: 0 | BO13: =BM13-BN13 -> 10
A14: POKER LATA | B14: 12 | C14: 0 | D14: =B14-C14 -> 12 | E14: 0 | F14: =D14-E14 -> 12 | G14: 0 | H14: =F14-G14 -> 12 | I14: 0 | J14: 0 | K14: =H14+I14-J14 -> 12 | L14: 0 | M14: 0 | N14: =K14+L14-M14 -> 12 | O14: 1 | P14: 0 | Q14: =N14+P14-O14 -> 11 | R14: 0 | S14: 0 | T14: =Q14+S14-R14 -> 11 | U14: 0 | V14: 0 | W14: =T14+V14-U14 -> 11 | X14: 0 | Y14: 0 | Z14: =W14+X14-Y14 -> 11 | AA14: 0 | AB14: 0 | AC14: =Z14+AA14-AB14 -> 11 | AD14: 0 | AE14: 0 | AF14: =AC14+AD14-AE14 -> 11 | AG14: 0 | AH14: 0 | AI14: =AF14+AG14-AH14 -> 11 | AJ14: 0 | AK14: 0 | AL14: =AI14+AJ14-AK14 -> 11 | AM14: 0 | AN14: 0 | AO14: =AL14+AM14-AN14 -> 11 | AP14: 0 | AQ14: 0 | AR14: =AO14+AP14-AQ14 -> 11 | AS14: 0 | AT14: 0 | AU14: =AR14+AS14-AT14 -> 11 | AV14: 0 | AW14: 0 | AX14: =AU14+AV14-AW14 -> 11 | AY14: 0 | AZ14: 0 | BA14: =AX14+AY14-AZ14 -> 11 | BB14: 0 | BC14: 0 | BD14: =BA14+BB14-BC14 -> 11 | BE14: 0 | BF14: 0 | BG14: =BD14+BE14-BF14 -> 11 | BH14: 0 | BI14: 0 | BJ14: =BG14+BH14-BI14 -> 11 | BK14: 0 | BL14: 0 | BM14: =BJ14+BK14-BL14 -> 11 | BN14: 0 | BO14: =BM14-BN14 -> 11
A15: AGUILA LATA | B15: 4 | C15: 0 | D15: =B15-C15 -> 4 | E15: 0 | F15: =D15-E15 -> 4 | G15: 3 | H15: =F15-G15 -> 1 | I15: 0 | J15: 0 | K15: =H15+I15-J15 -> 1 | L15: 0 | M15: 0 | N15: =K15+L15-M15 -> 1 | O15: 1 | P15: 0 | Q15: =N15+P15-O15 -> 0 | R15: 0 | S15: 0 | T15: =Q15+S15-R15 -> 0 | U15: 0 | V15: 0 | W15: =T15+V15-U15 -> 0 | X15: 0 | Y15: 0 | Z15: =W15+X15-Y15 -> 0 | AA15: 0 | AB15: 0 | AC15: =Z15+AA15-AB15 -> 0 | AD15: 0 | AE15: 0 | AF15: =AC15+AD15-AE15 -> 0 | AG15: 0 | AH15: 0 | AI15: =AF15+AG15-AH15 -> 0 | AJ15: 0 | AK15: 0 | AL15: =AI15+AJ15-AK15 -> 0 | AM15: 0 | AN15: 0 | AO15: =AL15+AM15-AN15 -> 0 | AP15: 0 | AQ15: 0 | AR15: =AO15+AP15-AQ15 -> 0 | AS15: 0 | AT15: 0 | AU15: =AR15+AS15-AT15 -> 0 | AV15: 0 | AW15: 0 | AX15: =AU15+AV15-AW15 -> 0 | AY15: 0 | AZ15: 0 | BA15: =AX15+AY15-AZ15 -> 0 | BB15: 0 | BC15: 0 | BD15: =BA15+BB15-BC15 -> 0 | BE15: 0 | BF15: 0 | BG15: =BD15+BE15-BF15 -> 0 | BH15: 0 | BI15: 0 | BJ15: =BG15+BH15-BI15 -> 0 | BK15: 0 | BL15: 0 | BM15: =BJ15+BK15-BL15 -> 0 | BN15: 0 | BO15: =BM15-BN15 -> 0
A16: CORONITA LATA | B16: 11 | C16: 0 | D16: =B16-C16 -> 11 | E16: 0 | F16: =D16-E16 -> 11 | G16: 0 | H16: =F16-G16 -> 11 | I16: 0 | J16: 0 | K16: =H16+I16-J16 -> 11 | L16: 0 | M16: 0 | N16: =K16+L16-M16 -> 11 | O16: 0 | P16: 0 | Q16: =N16+P16-O16 -> 11 | R16: 0 | S16: 0 | T16: =Q16+S16-R16 -> 11 | U16: 0 | V16: 0 | W16: =T16+V16-U16 -> 11 | X16: 0 | Y16: 0 | Z16: =W16+X16-Y16 -> 11 | AA16: 0 | AB16: 0 | AC16: =Z16+AA16-AB16 -> 11 | AD16: 0 | AE16: 0 | AF16: =AC16+AD16-AE16 -> 11 | AG16: 0 | AH16: 0 | AI16: =AF16+AG16-AH16 -> 11 | AJ16: 0 | AK16: 0 | AL16: =AI16+AJ16-AK16 -> 11 | AM16: 0 | AN16: 0 | AO16: =AL16+AM16-AN16 -> 11 | AP16: 0 | AQ16: 0 | AR16: =AO16+AP16-AQ16 -> 11 | AS16: 0 | AT16: 0 | AU16: =AR16+AS16-AT16 -> 11 | AV16: 0 | AW16: 0 | AX16: =AU16+AV16-AW16 -> 11 | AY16: 0 | AZ16: 0 | BA16: =AX16+AY16-AZ16 -> 11 | BB16: 0 | BC16: 0 | BD16: =BA16+BB16-BC16 -> 11 | BE16: 0 | BF16: 0 | BG16: =BD16+BE16-BF16 -> 11 | BH16: 0 | BI16: 0 | BJ16: =BG16+BH16-BI16 -> 11 | BK16: 0 | BL16: 0 | BM16: =BJ16+BK16-BL16 -> 11 | BN16: 0 | BO16: =BM16-BN16 -> 11
A17: CORONA LATA | B17: 2 | C17: 0 | D17: =B17-C17 -> 2 | E17: 0 | F17: =D17-E17 -> 2 | G17: 0 | H17: =F17-G17 -> 2 | I17: 0 | J17: 0 | K17: =H17+I17-J17 -> 2 | L17: 0 | M17: 0 | N17: =K17+L17-M17 -> 2 | O17: 0 | P17: 0 | Q17: =N17+P17-O17 -> 2 | R17: 0 | S17: 0 | T17: =Q17+S17-R17 -> 2 | U17: 0 | V17: 0 | W17: =T17+V17-U17 -> 2 | X17: 0 | Y17: 0 | Z17: =W17+X17-Y17 -> 2 | AA17: 0 | AB17: 0 | AC17: =Z17+AA17-AB17 -> 2 | AD17: 0 | AE17: 0 | AF17: =AC17+AD17-AE17 -> 2 | AG17: 0 | AH17: 0 | AI17: =AF17+AG17-AH17 -> 2 | AJ17: 0 | AK17: 0 | AL17: =AI17+AJ17-AK17 -> 2 | AM17: 0 | AN17: 0 | AO17: =AL17+AM17-AN17 -> 2 | AP17: 0 | AQ17: 0 | AR17: =AO17+AP17-AQ17 -> 2 | AS17: 0 | AT17: 0 | AU17: =AR17+AS17-AT17 -> 2 | AV17: 0 | AW17: 0 | AX17: =AU17+AV17-AW17 -> 2 | AY17: 0 | AZ17: 0 | BA17: =AX17+AY17-AZ17 -> 2 | BB17: 0 | BC17: 0 | BD17: =BA17+BB17-BC17 -> 2 | BE17: 0 | BF17: 0 | BG17: =BD17+BE17-BF17 -> 2 | BH17: 0 | BI17: 0 | BJ17: =BG17+BH17-BI17 -> 2 | BK17: 0 | BL17: 0 | BM17: =BJ17+BK17-BL17 -> 2 | BN17: 0 | BO17: =BM17-BN17 -> 2
A18: HEINEKEN LATA | B18: 4 | C18: 0 | D18: =B18-C18 -> 4 | E18: 0 | F18: =D18-E18 -> 4 | G18: 0 | H18: =F18-G18 -> 4 | I18: 0 | J18: 0 | K18: =H18+I18-J18 -> 4 | L18: 0 | M18: 0 | N18: =K18+L18-M18 -> 4 | O18: 0 | P18: 0 | Q18: =N18+P18-O18 -> 4 | R18: 0 | S18: 0 | T18: =Q18+S18-R18 -> 4 | U18: 0 | V18: 0 | W18: =T18+V18-U18 -> 4 | X18: 0 | Y18: 0 | Z18: =W18+X18-Y18 -> 4 | AA18: 0 | AB18: 0 | AC18: =Z18+AA18-AB18 -> 4 | AD18: 0 | AE18: 0 | AF18: =AC18+AD18-AE18 -> 4 | AG18: 0 | AH18: 0 | AI18: =AF18+AG18-AH18 -> 4 | AJ18: 0 | AK18: 0 | AL18: =AI18+AJ18-AK18 -> 4 | AM18: 0 | AN18: 0 | AO18: =AL18+AM18-AN18 -> 4 | AP18: 0 | AQ18: 0 | AR18: =AO18+AP18-AQ18 -> 4 | AS18: 0 | AT18: 0 | AU18: =AR18+AS18-AT18 -> 4 | AV18: 0 | AW18: 0 | AX18: =AU18+AV18-AW18 -> 4 | AY18: 0 | AZ18: 0 | BA18: =AX18+AY18-AZ18 -> 4 | BB18: 0 | BC18: 0 | BD18: =BA18+BB18-BC18 -> 4 | BE18: 0 | BF18: 0 | BG18: =BD18+BE18-BF18 -> 4 | BH18: 0 | BI18: 0 | BJ18: =BG18+BH18-BI18 -> 4 | BK18: 0 | BL18: 0 | BM18: =BJ18+BK18-BL18 -> 4 | BN18: 0 | BO18: =BM18-BN18 -> 4
... A24: HEINEKEN BOTELLA | B24: 25 | C24: 5 | D24: =B24-C24 -> 20 | E24: 0 | F24: =D24-E24 -> 20 | G24: 0 | H24: =F24-G24 -> 20 | I24: 0 | J24: 0 | K24: =H24+I24-J24 -> 20 | L24: 0 | M24: 0 | N24: =K24+L24-M24 -> 20 | O24: 0 | P24: 0 | Q24: =N24+P24-O24 -> 20 | R24: 0 | S24: 0 | T24: =Q24+S24-R24 -> 20 | U24: 0 | V24: 0 | W24: =T24+V24-U24 -> 20 | X24: 0 | Y24: 0 | Z24: =W24+X24-Y24 -> 20 | AA24: 0 | AB24: 0 | AC24: =Z24+AA24-AB24 -> 20 | AD24: 0 | AE24: 0 | AF24: =AC24+AD24-AE24 -> 20 | AG24: 0 | AH24: 0 | AI24: =AF24+AG24-AH24 -> 20 | AJ24: 0 | AK24: 0 | AL24: =AI24+AJ24-AK24 -> 20 | AM24: 0 | AN24: 0 | AO24: =AL24+AM24-AN24 -> 20 | AP24: 0 | AQ24: 0 | AR24: =AO24+AP24-AQ24 -> 20 | AS24: 0 | AT24: 4 | AU24: =AR24+AS24-AT24 -> 16 | AV24: 0 | AW24: 0 | AX24: =AU24+AV24-AW24 -> 16 | AY24: 0 | AZ24: 0 | BA24: =AX24+AY24-AZ24 -> 16 | BB24: 0 | BC24: 0 | BD24: =BA24+BB24-BC24 -> 16 | BE24: 0 | BF24: 0 | BG24: =BD24+BE24-BF24 -> 16 | BH24: 0 | BI24: 0 | BJ24: =BG24+BH24-BI24 -> 16 | BK24: 0 | BL24: 0 | BM24: =BJ24+BK24-BL24 -> 16 | BN24: 0 | BO24: =BM24-BN24 -> 16
A25: CORONITA | B25: 44 | C25: 0 | D25: =B25-C25 -> 44 | E25: 0 | F25: =D25-E25 -> 44 | G25: 19 | H25: =F25-G25 -> 25 | I25: 0 | J25: 14 | K25: =H25+I25-J25 -> 11 | L25: 12 | M25: 10 | N25: =K25+L25-M25 -> 13 | O25: 0 | P25: 36 | Q25: =N25+P25-O25 -> 49 | R25: 0 | S25: 0 | T25: 48 | U25: 1 | V25: 0 | W25: =T25+V25-U25 -> 47 | X25: 0 | Y25: 18 | Z25: =W25+X25-Y25 -> 29 | AA25: 24 | AB25: 12 | AC25: =Z25+AA25-AB25 -> 41 | AD25: 0 | AE25: 10 | AF25: =AC25+AD25-AE25 -> 31 | AG25: 0 | AH25: 10 | AI25: =AF25+AG25-AH25 -> 21 | AJ25: 0 | AK25: 16 | AL25: =AI25+AJ25-AK25 -> 5 | AM25: 48 | AN25: 0 | AO25: =AL25+AM25-AN25 -> 53 | AP25: 0 | AQ25: 12 | AR25: =AO25+AP25-AQ25 -> 41 | AS25: 0 | AT25: 0 | AU25: =AR25+AS25-AT25 -> 41 | AV25: 66 | AW25: 103 | AX25: =AU25+AV25-AW25 -> 4 | AY25: 54 | AZ25: 0 | BA25: =AX25+AY25-AZ25 -> 58 | BB25: 0 | BC25: 21 | BD25: =BA25+BB25-BC25 -> 37 | BE25: 0 | BF25: 0 | BG25: =BD25+BE25-BF25 -> 37 | BH25: 0 | BI25: 0 | BJ25: =BG25+BH25-BI25 -> 37 | BK25: 0 | BL25: 0 | BM25: =BJ25+BK25-BL25 -> 37 | BN25: 11 | BO25: =BM25-BN25 -> 26
A26: AGUILA | B26: 186 | C26: 14 | D26: =B26-C26 -> 172 | E26: 58 | F26: =D26-E26 -> 114 | G26: 56 | H26: =F26-G26 -> 58 | I26: 120 | J26: 24 | K26: =H26+I26-J26 -> 154 | L26: 0 | M26: 67 | N26: =K26+L26-M26 -> 87 | O26: 22 | P26: 90 | Q26: =N26+P26-O26 -> 155 | R26: 26 | S26: 0 | T26: =Q26+S26-R26 -> 129 | U26: 40 | V26: 60 | W26: =T26+V26-U26 -> 149 | X26: 30 | Y26: 48 | Z26: =W26+X26-Y26 -> 131 | AA26: 60 | AB26: 90 | AC26: =Z26+AA26-AB26 -> 101 | AD26: 90 | AE26: 55 | AF26: =AC26+AD26-AE26 -> 136 | AG26: 45 | AH26: 19 | AI26: 163 | AJ26: 0 | AK26: 18 | AL26: =AI26+AJ26-AK26 -> 145 | AM26: 0 | AN26: 27 | AO26: =AL26+AM26-AN26 -> 118 | AP26: 120 | AQ26: 93 | AR26: =AO26+AP26-AQ26 -> 145 | AS26: 30 | AT26: 64 | AU26: =AR26+AS26-AT26 -> 111 | AV26: 60 | AW26: 65 | AX26: =AU26+AV26-AW26 -> 106 | AY26: 60 | AZ26: 50 | BA26: =AX26+AY26-AZ26 -> 116 | BB26: 0 | BC26: 39 | BD26: =BA26+BB26-BC26 -> 77 | BE26: 105 | BF26: 38 | BG26: =BD26+BE26-BF26 -> 144 | BH26: 0 | BI26: 47 | BJ26: =BG26+BH26-BI26 -> 97 | BK26: 60 | BL26: 1 | BM26: =BJ26+BK26-BL26 -> 156 | BN26: 15 | BO26: =BM26-BN26 -> 141
A27: LIGTH | B27: 178 | C27: 18 | D27: =B27-C27 -> 160 | E27: 47 | F27: =D27-E27 -> 113 | G27: 14 | H27: 98 | I27: 60 | J27: 55 | K27: =H27+I27-J27 -> 103 | L27: 0 | M27: 27 | N27: =K27+L27-M27 -> 76 | O27: 45 | P27: 90 | Q27: =N27+P27-O27 -> 121 | R27: 13 | S27: 0 | T27: =Q27+S27-R27 -> 108 | U27: 41 | V27: 60 | W27: =T27+V27-U27 -> 127 | X27: 60 | Y27: 25 | Z27: =W27+X27-Y27 -> 162 | AA27: 15 | AB27: 82 | AC27: =Z27+AA27-AB27 -> 95 | AD27: 75 | AE27: 61 | AF27: =AC27+AD27-AE27 -> 109 | AG27: 60 | AH27: 5 | AI27: =AF27+AG27-AH27 -> 164 | AJ27: 0 | AK27: 4 | AL27: =AI27+AJ27-AK27 -> 160 | AM27: 0 | AN27: 14 | AO27: =AL27+AM27-AN27 -> 146 | AP27: 0 | AQ27: 22 | AR27: =AO27+AP27-AQ27 -> 124 | AS27: 60 | AT27: 49 | AU27: =AR27+AS27-AT27 -> 135 | AV27: 60 | AW27: 32 | AX27: =AU27+AV27-AW27 -> 163 | AY27: 60 | AZ27: 74 | BA27: =AX27+AY27-AZ27 -> 149 | BB27: 0 | BC27: 34 | BD27: =BA27+BB27-BC27 -> 115 | BE27: 76 | BF27: 15 | BG27: =BD27+BE27-BF27 -> 176 | BH27: 0 | BI27: 10 | BJ27: =BG27+BH27-BI27 -> 166 | BK27: 0 | BL27: 1 | BM27: =BJ27+BK27-BL27 -> 165 | BN27: 59 | BO27: =BM27-BN27 -> 106
A28: POKER | B28: 83 | C28: 3 | D28: =B28-C28 -> 80 | E28: 0 | F28: =D28-E28 -> 80 | G28: 1 | H28: =F28-G28 -> 79 | I28: 0 | J28: 7 | K28: =H28+I28-J28 -> 72 | L28: 0 | M28: 8 | N28: =K28+L28-M28 -> 64 | O28: 35 | P28: 15 | Q28: =N28+P28-O28 -> 44 | R28: 3 | S28: 0 | T28: 40 | U28: 0 | V28: 0 | W28: =T28+V28-U28 -> 40 | X28: 0 | Y28: 2 | Z28: =W28+X28-Y28 -> 38 | AA28: 0 | AB28: 31 | AC28: =Z28+AA28-AB28 -> 7 | AD28: 75 | AE28: 12 | AF28: =AC28+AD28-AE28 -> 70 | AG28: 0 | AH28: 1 | AI28: =AF28+AG28-AH28 -> 69 | AJ28: 0 | AK28: 13 | AL28: =AI28+AJ28-AK28 -> 56 | AM28: 0 | AN28: 13 | AO28: =AL28+AM28-AN28 -> 43 | AP28: 0 | AQ28: 0 | AR28: =AO28+AP28-AQ28 -> 43 | AS28: 0 | AT28: 0 | AU28: =AR28+AS28-AT28 -> 43 | AV28: 30 | AW28: 6 | AX28: =AU28+AV28-AW28 -> 67 | AY28: 0 | AZ28: 18 | BA28: =AX28+AY28-AZ28 -> 49 | BB28: 0 | BC28: 2 | BD28: =BA28+BB28-BC28 -> 47 | BE28: 30 | BF28: 5 | BG28: =BD28+BE28-BF28 -> 72 | BH28: 0 | BI28: 6 | BJ28: =BG28+BH28-BI28 -> 66 | BK28: 0 | BL28: 2 | BM28: =BJ28+BK28-BL28 -> 64 | BN28: 10 | BO28: =BM28-BN28 -> 54
A29: COSTEÑA | B29: 101 | C29: 0 | D29: =B29-C29 -> 101 | E29: 18 | F29: =D29-E29 -> 83 | G29: 7 | H29: =F29-G29 -> 76 | I29: 0 | J29: 25 | K29: 48 | L29: 0 | M29: 0 | N29: 48 | O29: 0 | P29: 45 | Q29: =N29+P29-O29 -> 93 | R29: 4 | S29: 0 | T29: =Q29+S29-R29 -> 89 | U29: 22 | V29: 0 | W29: =T29+V29-U29 -> 67 | X29: 30 | Y29: 15 | Z29: =W29+X29-Y29 -> 82 | AA29: 15 | AB29: 12 | AC29: =Z29+AA29-AB29 -> 85 | AD29: 15 | AE29: 43 | AF29: =AC29+AD29-AE29 -> 57 | AG29: 30 | AH29: 0 | AI29: =AF29+AG29-AH29 -> 87 | AJ29: 0 | AK29: 3 | AL29: =AI29+AJ29-AK29 -> 84 | AM29: 0 | AN29: 0 | AO29: =AL29+AM29-AN29 -> 84 | AP29: 0 | AQ29: 1 | AR29: =AO29+AP29-AQ29 -> 83 | AS29: 0 | AT29: 1 | AU29: =AR29+AS29-AT29 -> 82 | AV29: 0 | AW29: 0 | AX29: =AU29+AV29-AW29 -> 82 | AY29: 0 | AZ29: 22 | BA29: =AX29+AY29-AZ29 -> 60 | BB29: 0 | BC29: 0 | BD29: =BA29+BB29-BC29 -> 60 | BE29: 30 | BF29: 4 | BG29: =BD29+BE29-BF29 -> 86 | BH29: 0 | BI29: 6 | BJ29: =BG29+BH29-BI29 -> 80 | BK29: 0 | BL29: 4 | BM29: =BJ29+BK29-BL29 -> 76 | BN29: 0 | BO29: =BM29-BN29 -> 76
A30: CLUB | B30: 70 | C30: 5 | D30: =B30-C30 -> 65 | E30: 1 | F30: =D30-E30 -> 64 | G30: 12 | H30: =F30-G30 -> 52 | I30: 0 | J30: 0 | K30: =H30+I30-J30 -> 52 | L30: 0 | M30: 0 | N30: =K30+L30-M30 -> 52 | O30: 0 | P30: 15 | Q30: =N30+P30-O30 -> 67 | R30: 0 | S30: 0 | T30: =Q30+S30-R30 -> 67 | U30: 0 | V30: 0 | W30: =T30+V30-U30 -> 67 | X30: 0 | Y30: 12 | Z30: =W30+X30-Y30 -> 55 | AA30: 15 | AB30: 0 | AC30: =Z30+AA30-AB30 -> 70 | AD30: 0 | AE30: 18 | AF30: =AC30+AD30-AE30 -> 52 | AG30: 15 | AH30: 0 | AI30: =AF30+AG30-AH30 -> 67 | AJ30: 0 | AK30: 11 | AL30: =AI30+AJ30-AK30 -> 56 | AM30: 0 | AN30: 0 | AO30: =AL30+AM30-AN30 -> 56 | AP30: 0 | AQ30: 3 | AR30: =AO30+AP30-AQ30 -> 53 | AS30: 15 | AT30: 0 | AU30: =AR30+AS30-AT30 -> 68 | AV30: 0 | AW30: 25 | AX30: =AU30+AV30-AW30 -> 43 | AY30: 0 | AZ30: 8 | BA30: =AX30+AY30-AZ30 -> 35 | BB30: 0 | BC30: 5 | BD30: =BA30+BB30-BC30 -> 30 | BE30: 30 | BF30: 1 | BG30: =BD30+BE30-BF30 -> 59 | BH30: 0 | BI30: 6 | BJ30: =BG30+BH30-BI30 -> 53 | BK30: 0 | BL30: 0 | BM30: =BJ30+BK30-BL30 -> 53 | BN30: 0 | BO30: =BM30-BN30 -> 53
A31: 1/2 AG. ANTIOQUEÑO VERDE | B31: 5 | C31: 0 | D31: =B31-C31 -> 5 | E31: 1 | F31: =D31-E31 -> 4 | G31: 0 | H31: =F31-G31 -> 4 | I31: 9 | J31: 12 | K31: =H31+I31-J31 -> 1 | L31: 11 | M31: 11 | N31: =K31+L31-M31 -> 1 | O31: 0 | P31: 4 | Q31: =N31+P31-O31 -> 5 | R31: 0 | S31: 0 | T31: =Q31+S31-R31 -> 5 | U31: 0 | V31: 0 | W31: =T31+V31-U31 -> 5 | X31: 0 | Y31: 0 | Z31: =W31+X31-Y31 -> 5 | AA31: 0 | AB31: 0 | AC31: =Z31+AA31-AB31 -> 5 | AD31: 0 | AE31: 1 | AF31: =AC31+AD31-AE31 -> 4 | AG31: 1 | AH31: 2 | AI31: =AF31+AG31-AH31 -> 3 | AJ31: 3 | AK31: 6 | AL31: =AI31+AJ31-AK31 -> 0 | AM31: 5 | AN31: 0 | AO31: =AL31+AM31-AN31 -> 5 | AP31: 0 | AQ31: 0 | AR31: =AO31+AP31-AQ31 -> 5 | AS31: 0 | AT31: 0 | AU31: =AR31+AS31-AT31 -> 5 | AV31: 0 | AW31: 1 | AX31: =AU31+AV31-AW31 -> 4 | AY31: 0 | AZ31: 1 | BA31: =AX31+AY31-AZ31 -> 3 | BB31: 2 | BC31: 0 | BD31: =BA31+BB31-BC31 -> 5 | BE31: 0 | BF31: 0 | BG31: =BD31+BE31-BF31 -> 5 | BH31: 0 | BI31: 0 | BJ31: =BG31+BH31-BI31 -> 5 | BK31: 0 | BL31: 0 | BM31: =BJ31+BK31-BL31 -> 5 | BN31: 1 | BO31: =BM31-BN31 -> 4
A32: 1 BOTELLA AG. ANTIOQUEÑO VERDE | B32: 0 | C32: 0 | D32: =B32-C32 -> 0 | E32: 0 | F32: =D32-E32 -> 0 | G32: 0 | H32: =F32-G32 -> 0 | I32: 1 | J32: 1 | K32: =H32+I32-J32 -> 0 | L32: 9 | M32: 9 | N32: =K32+L32-M32 -> 0 | O32: 0 | P32: 0 | Q32: =N32+P32-O32 -> 0 | R32: 0 | S32: 0 | T32: =Q32+S32-R32 -> 0 | U32: 0 | V32: 0 | W32: =T32+V32-U32 -> 0 | X32: 0 | Y32: 0 | Z32: =W32+X32-Y32 -> 0 | AA32: 0 | AB32: 0 | AC32: =Z32+AA32-AB32 -> 0 | AD32: 0 | AE32: 0 | AF32: =AC32+AD32-AE32 -> 0 | AG32: 0 | AH32: 0 | AI32: =AF32+AG32-AH32 -> 0 | AJ32: 1 | AK32: 1 | AL32: =AI32+AJ32-AK32 -> 0 | AM32: 0 | AN32: 0 | AO32: =AL32+AM32-AN32 -> 0 | AP32: 0 | AQ32: 0 | AR32: =AO32+AP32-AQ32 -> 0 | AS32: 0 | AT32: 0 | AU32: =AR32+AS32-AT32 -> 0 | AV32: 0 | AW32: 0 | AX32: =AU32+AV32-AW32 -> 0 | AY32: 0 | AZ32: 0 | BA32: =AX32+AY32-AZ32 -> 0 | BB32: 0 | BC32: 0 | BD32: =BA32+BB32-BC32 -> 0 | BE32: 0 | BF32: 0 | BG32: =BD32+BE32-BF32 -> 0 | BH32: 0 | BI32: 0 | BJ32: =BG32+BH32-BI32 -> 0 | BK32: 0 | BL32: 0 | BM32: =BJ32+BK32-BL32 -> 0 | BN32: 0 | BO32: =BM32-BN32 -> 0
A33: 1/2 AG. ANTIOQUEÑO AZUL | B33: 0 | C33: 0 | D33: =B33-C33 -> 0 | E33: 0 | F33: =D33-E33 -> 0 | G33: 0 | H33: =F33-G33 -> 0 | I33: 0 | J33: 0 | K33: =H33+I33-J33 -> 0 | L33: 0 | M33: 0 | N33: =K33+L33-M33 -> 0 | O33: 0 | P33: 0 | Q33: =N33+P33-O33 -> 0 | R33: 0 | S33: 0 | T33: =Q33+S33-R33 -> 0 | U33: 0 | V33: 0 | W33: =T33+V33-U33 -> 0 | X33: 0 | Y33: 0 | Z33: =W33+X33-Y33 -> 0 | AA33: 0 | AB33: 0 | AC33: =Z33+AA33-AB33 -> 0 | AD33: 0 | AE33: 0 | AF33: =AC33+AD33-AE33 -> 0 | AG33: 0 | AH33: 0 | AI33: =AF33+AG33-AH33 -> 0 | AJ33: 0 | AK33: 0 | AL33: =AI33+AJ33-AK33 -> 0 | AM33: 0 | AN33: 0 | AO33: =AL33+AM33-AN33 -> 0 | AP33: 0 | AQ33: 0 | AR33: =AO33+AP33-AQ33 -> 0 | AS33: 0 | AT33: 0 | AU33: =AR33+AS33-AT33 -> 0 | AV33: 0 | AW33: 0 | AX33: =AU33+AV33-AW33 -> 0 | AY33: 0 | AZ33: 0 | BA33: =AX33+AY33-AZ33 -> 0 | BB33: 0 | BC33: 0 | BD33: =BA33+BB33-BC33 -> 0 | BE33: 0 | BF33: 0 | BG33: =BD33+BE33-BF33 -> 0 | BH33: 0 | BI33: 0 | BJ33: =BG33+BH33-BI33 -> 0 | BK33: 0 | BL33: 0 | BM33: =BJ33+BK33-BL33 -> 0 | BN33: 0 | BO33: =BM33-BN33 -> 0
A34: 1 BOTELLA AG. ANTIOQUEÑO AZUL | B34: 0 | C34: 0 | D34: =B34-C34 -> 0 | E34: 0 | F34: =D34-E34 -> 0 | G34: 0 | H34: =F34-G34 -> 0 | I34: 0 | J34: 0 | K34: =H34+I34-J34 -> 0 | L34: 0 | M34: 0 | N34: =K34+L34-M34 -> 0 | O34: 0 | P34: 0 | Q34: =N34+P34-O34 -> 0 | R34: 0 | S34: 0 | T34: =Q34+S34-R34 -> 0 | U34: 0 | V34: 0 | W34: =T34+V34-U34 -> 0 | X34: 0 | Y34: 0 | Z34: =W34+X34-Y34 -> 0 | AA34: 0 | AB34: 0 | AC34: =Z34+AA34-AB34 -> 0 | AD34: 0 | AE34: 0 | AF34: =AC34+AD34-AE34 -> 0 | AG34: 0 | AH34: 0 | AI34: =AF34+AG34-AH34 -> 0 | AJ34: 0 | AK34: 0 | AL34: =AI34+AJ34-AK34 -> 0 | AM34: 0 | AN34: 0 | AO34: =AL34+AM34-AN34 -> 0 | AP34: 0 | AQ34: 0 | AR34: =AO34+AP34-AQ34 -> 0 | AS34: 0 | AT34: 0 | AU34: =AR34+AS34-AT34 -> 0 | AV34: 0 | AW34: 0 | AX34: =AU34+AV34-AW34 -> 0 | AY34: 0 | AZ34: 0 | BA34: =AX34+AY34-AZ34 -> 0 | BB34: 0 | BC34: 0 | BD34: =BA34+BB34-BC34 -> 0 | BE34: 0 | BF34: 0 | BG34: =BD34+BE34-BF34 -> 0 | BH34: 0 | BI34: 0 | BJ34: =BG34+BH34-BI34 -> 0 | BK34: 0 | BL34: 0 | BM34: =BJ34+BK34-BL34 -> 0 | BN34: 0 | BO34: =BM34-BN34 -> 0
A35: SMIRNOFF LULO PEQUEÑA | B35: 2 | C35: 0 | D35: =B35-C35 -> 2 | E35: 0 | F35: =D35-E35 -> 2 | G35: 0 | H35: =F35-G35 -> 2 | I35: 0 | J35: 0 | K35: =H35+I35-J35 -> 2 | L35: 0 | M35: 0 | N35: =K35+L35-M35 -> 2 | O35: 0 | P35: 0 | Q35: =N35+P35-O35 -> 2 | R35: 0 | S35: 0 | T35: =Q35+S35-R35 -> 2 | U35: 0 | V35: 0 | W35: =T35+V35-U35 -> 2 | X35: 0 | Y35: 0 | Z35: =W35+X35-Y35 -> 2 | AA35: 0 | AB35: 0 | AC35: =Z35+AA35-AB35 -> 2 | AD35: 0 | AE35: 0 | AF35: =AC35+AD35-AE35 -> 2 | AG35: 0 | AH35: 0 | AI35: =AF35+AG35-AH35 -> 2 | AJ35: 0 | AK35: 0 | AL35: =AI35+AJ35-AK35 -> 2 | AM35: 0 | AN35: 0 | AO35: =AL35+AM35-AN35 -> 2 | AP35: 0 | AQ35: 0 | AR35: =AO35+AP35-AQ35 -> 2 | AS35: 0 | AT35: 0 | AU35: =AR35+AS35-AT35 -> 2 | AV35: 0 | AW35: 0 | AX35: =AU35+AV35-AW35 -> 2 | AY35: 0 | AZ35: 0 | BA35: =AX35+AY35-AZ35 -> 2 | BB35: 0 | BC35: 0 | BD35: =BA35+BB35-BC35 -> 2 | BE35: 0 | BF35: 0 | BG35: =BD35+BE35-BF35 -> 2 | BH35: 0 | BI35: 0 | BJ35: =BG35+BH35-BI35 -> 2 | BK35: 0 | BL35: 0 | BM35: =BJ35+BK35-BL35 -> 2 | BN35: 0 | BO35: =BM35-BN35 -> 2
A36: RON MEDELLIN DORADO GRANDE | B36: 1 | C36: 0 | D36: =B36-C36 -> 1 | E36: 0 | F36: =D36-E36 -> 1 | G36: 0 | H36: =F36-G36 -> 1 | I36: 0 | J36: 0 | K36: =H36+I36-J36 -> 1 | L36: 0 | M36: 0 | N36: =K36+L36-M36 -> 1 | O36: 0 | P36: 0 | Q36: =N36+P36-O36 -> 1 | R36: 0 | S36: 0 | T36: =Q36+S36-R36 -> 1 | U36: 0 | V36: 0 | W36: =T36+V36-U36 -> 1 | X36: 0 | Y36: 0 | Z36: =W36+X36-Y36 -> 1 | AA36: 0 | AB36: 0 | AC36: =Z36+AA36-AB36 -> 1 | AD36: 0 | AE36: 0 | AF36: =AC36+AD36-AE36 -> 1 | AG36: 0 | AH36: 0 | AI36: =AF36+AG36-AH36 -> 1 | AJ36: 0 | AK36: 0 | AL36: =AI36+AJ36-AK36 -> 1 | AM36: 0 | AN36: 0 | AO36: =AL36+AM36-AN36 -> 1 | AP36: 0 | AQ36: 0 | AR36: =AO36+AP36-AQ36 -> 1 | AS36: 0 | AT36: 0 | AU36: =AR36+AS36-AT36 -> 1 | AV36: 0 | AW36: 0 | AX36: =AU36+AV36-AW36 -> 1 | AY36: 0 | AZ36: 0 | BA36: =AX36+AY36-AZ36 -> 1 | BB36: 0 | BC36: 0 | BD36: =BA36+BB36-BC36 -> 1 | BE36: 0 | BF36: 0 | BG36: =BD36+BE36-BF36 -> 1 | BH36: 0 | BI36: 0 | BJ36: =BG36+BH36-BI36 -> 1 | BK36: 0 | BL36: 0 | BM36: =BJ36+BK36-BL36 -> 1 | BN36: 0 | BO36: =BM36-BN36 -> 1
A37: RON MEDELLIN DORADO PEQUEÑA | B37: 1 | C37: 0 | D37: =B37-C37 -> 1 | E37: 0 | F37: =D37-E37 -> 1 | G37: 0 | H37: =F37-G37 -> 1 | I37: 0 | J37: 0 | K37: =H37+I37-J37 -> 1 | L37: 0 | M37: 0 | N37: =K37+L37-M37 -> 1 | O37: 0 | P37: 0 | Q37: =N37+P37-O37 -> 1 | R37: 0 | S37: 0 | T37: =Q37+S37-R37 -> 1 | U37: 0 | V37: 0 | W37: =T37+V37-U37 -> 1 | X37: 0 | Y37: 0 | Z37: =W37+X37-Y37 -> 1 | AA37: 0 | AB37: 0 | AC37: =Z37+AA37-AB37 -> 1 | AD37: 0 | AE37: 0 | AF37: =AC37+AD37-AE37 -> 1 | AG37: 0 | AH37: 0 | AI37: =AF37+AG37-AH37 -> 1 | AJ37: 0 | AK37: 0 | AL37: =AI37+AJ37-AK37 -> 1 | AM37: 0 | AN37: 0 | AO37: =AL37+AM37-AN37 -> 1 | AP37: 0 | AQ37: 0 | AR37: =AO37+AP37-AQ37 -> 1 | AS37: 0 | AT37: 0 | AU37: =AR37+AS37-AT37 -> 1 | AV37: 0 | AW37: 0 | AX37: =AU37+AV37-AW37 -> 1 | AY37: 0 | AZ37: 0 | BA37: =AX37+AY37-AZ37 -> 1 | BB37: 0 | BC37: 0 | BD37: =BA37+BB37-BC37 -> 1 | BE37: 0 | BF37: 0 | BG37: =BD37+BE37-BF37 -> 1 | BH37: 0 | BI37: 0 | BJ37: =BG37+BH37-BI37 -> 1 | BK37: 0 | BL37: 0 | BM37: =BJ37+BK37-BL37 -> 1 | BN37: 0 | BO37: =BM37-BN37 -> 1
A38: SOMETHING SPECIAL PEQUEÑA | B38: 1 | C38: 0 | D38: =B38-C38 -> 1 | E38: 0 | F38: =D38-E38 -> 1 | G38: 0 | H38: =F38-G38 -> 1 | I38: 0 | J38: 0 | K38: =H38+I38-J38 -> 1 | L38: 0 | M38: 0 | N38: =K38+L38-M38 -> 1 | O38: 0 | P38: 0 | Q38: =N38+P38-O38 -> 1 | R38: 0 | S38: 0 | T38: =Q38+S38-R38 -> 1 | U38: 0 | V38: 0 | W38: =T38+V38-U38 -> 1 | X38: 0 | Y38: 0 | Z38: =W38+X38-Y38 -> 1 | AA38: 0 | AB38: 0 | AC38: =Z38+AA38-AB38 -> 1 | AD38: 0 | AE38: 0 | AF38: =AC38+AD38-AE38 -> 1 | AG38: 0 | AH38: 0 | AI38: =AF38+AG38-AH38 -> 1 | AJ38: 0 | AK38: 0 | AL38: =AI38+AJ38-AK38 -> 1 | AM38: 0 | AN38: 0 | AO38: =AL38+AM38-AN38 -> 1 | AP38: 0 | AQ38: 0 | AR38: =AO38+AP38-AQ38 -> 1 | AS38: 0 | AT38: 0 | AU38: =AR38+AS38-AT38 -> 1 | AV38: 0 | AW38: 0 | AX38: =AU38+AV38-AW38 -> 1 | AY38: 0 | AZ38: 0 | BA38: =AX38+AY38-AZ38 -> 1 | BB38: 0 | BC38: 0 | BD38: =BA38+BB38-BC38 -> 1 | BE38: 0 | BF38: 0 | BG38: =BD38+BE38-BF38 -> 1 | BH38: 0 | BI38: 0 | BJ38: =BG38+BH38-BI38 -> 1 | BK38: 0 | BL38: 0 | BM38: =BJ38+BK38-BL38 -> 1 | BN38: 0 | BO38: =BM38-BN38 -> 1
A39: BLACK LABEL | B39: 1 | C39: 0 | D39: =B39-C39 -> 1 | E39: 0 | F39: =D39-E39 -> 1 | G39: 0 | H39: =F39-G39 -> 1 | I39: 0 | J39: 0 | K39: =H39+I39-J39 -> 1 | L39: 0 | M39: 0 | N39: =K39+L39-M39 -> 1 | O39: 0 | P39: 0 | Q39: =N39+P39-O39 -> 1 | R39: 0 | S39: 0 | T39: =Q39+S39-R39 -> 1 | U39: 0 | V39: 0 | W39: =T39+V39-U39 -> 1 | X39: 0 | Y39: 0 | Z39: =W39+X39-Y39 -> 1 | AA39: 0 | AB39: 0 | AC39: =Z39+AA39-AB39 -> 1 | AD39: 0 | AE39: 0 | AF39: =AC39+AD39-AE39 -> 1 | AG39: 0 | AH39: 0 | AI39: =AF39+AG39-AH39 -> 1 | AJ39: 0 | AK39: 0 | AL39: =AI39+AJ39-AK39 -> 1 | AM39: 0 | AN39: 0 | AO39: =AL39+AM39-AN39 -> 1 | AP39: 0 | AQ39: 0 | AR39: =AO39+AP39-AQ39 -> 1 | AS39: 0 | AT39: 0 | AU39: =AR39+AS39-AT39 -> 1 | AV39: 0 | AW39: 0 | AX39: =AU39+AV39-AW39 -> 1 | AY39: 0 | AZ39: 0 | BA39: =AX39+AY39-AZ39 -> 1 | BB39: 0 | BC39: 0 | BD39: =BA39+BB39-BC39 -> 1 | BE39: 0 | BF39: 0 | BG39: =BD39+BE39-BF39 -> 1 | BH39: 0 | BI39: 0 | BJ39: =BG39+BH39-BI39 -> 1 | BK39: 0 | BL39: 0 | BM39: =BJ39+BK39-BL39 -> 1 | BN39: 0 | BO39: =BM39-BN39 -> 1
A40: RED LABEL | B40: 1 | C40: 0 | D40: =B40-C40 -> 1 | E40: 0 | F40: =D40-E40 -> 1 | G40: 0 | H40: =F40-G40 -> 1 | I40: 0 | J40: 0 | K40: =H40+I40-J40 -> 1 | L40: 0 | M40: 0 | N40: =K40+L40-M40 -> 1 | O40: 0 | P40: 0 | Q40: =N40+P40-O40 -> 1 | R40: 0 | S40: 0 | T40: =Q40+S40-R40 -> 1 | U40: 0 | V40: 0 | W40: =T40+V40-U40 -> 1 | X40: 0 | Y40: 0 | Z40: =W40+X40-Y40 -> 1 | AA40: 0 | AB40: 0 | AC40: =Z40+AA40-AB40 -> 1 | AD40: 0 | AE40: 0 | AF40: =AC40+AD40-AE40 -> 1 | AG40: 0 | AH40: 0 | AI40: =AF40+AG40-AH40 -> 1 | AJ40: 0 | AK40: 0 | AL40: =AI40+AJ40-AK40 -> 1 | AM40: 0 | AN40: 0 | AO40: =AL40+AM40-AN40 -> 1 | AP40: 0 | AQ40: 0 | AR40: =AO40+AP40-AQ40 -> 1 | AS40: 0 | AT40: 0 | AU40: =AR40+AS40-AT40 -> 1 | AV40: 0 | AW40: 0 | AX40: =AU40+AV40-AW40 -> 1 | AY40: 0 | AZ40: 0 | BA40: =AX40+AY40-AZ40 -> 1 | BB40: 0 | BC40: 0 | BD40: =BA40+BB40-BC40 -> 1 | BE40: 0 | BF40: 0 | BG40: =BD40+BE40-BF40 -> 1 | BH40: 0 | BI40: 0 | BJ40: =BG40+BH40-BI40 -> 1 | BK40: 0 | BL40: 0 | BM40: =BJ40+BK40-BL40 -> 1 | BN40: 0 | BO40: =BM40-BN40 -> 1
A41: 1/2 MUSTANG | B41: 3 | C41: 1 | D41: =B41-C41 -> 2 | E41: 0 | F41: =D41-E41 -> 2 | G41: 0 | H41: 1 | I41: 0 | J41: 0 | K41: =H41+I41-J41 -> 1 | L41: 5 | M41: 2 | N41: =K41+L41-M41 -> 4 | O41: 0 | P41: 0 | Q41: =N41+P41-O41 -> 4 | R41: 0 | S41: 1 | T41: =Q41+S41-R41 -> 5 | U41: 0 | V41: 1 | W41: 3 | X41: 0 | Y41: 0 | Z41: =W41+X41-Y41 -> 3 | AA41: 0 | AB41: 0 | AC41: =Z41+AA41-AB41 -> 3 | AD41: 0 | AE41: 0 | AF41: =AC41+AD41-AE41 -> 3 | AG41: 0 | AH41: 0 | AI41: =AF41+AG41-AH41 -> 3 | AJ41: 0 | AK41: 0 | AL41: =AI41+AJ41-AK41 -> 3 | AM41: 0 | AN41: 0 | AO41: =AL41+AM41-AN41 -> 3 | AP41: 0 | AQ41: 0 | AR41: =AO41+AP41-AQ41 -> 3 | AS41: 1 | AT41: 1 | AU41: =AR41+AS41-AT41 -> 3 | AV41: 0 | AW41: 1 | AX41: =AU41+AV41-AW41 -> 2 | AY41: 0 | AZ41: 2 | BA41: =AX41+AY41-AZ41 -> 0 | BB41: 3 | BC41: 0 | BD41: =BA41+BB41-BC41 -> 3 | BE41: 0 | BF41: 0 | BG41: =BD41+BE41-BF41 -> 3 | BH41: 0 | BI41: 0 | BJ41: =BG41+BH41-BI41 -> 3 | BK41: 0 | BL41: 0 | BM41: =BJ41+BK41-BL41 -> 3 | BN41: 0 | BO41: =BM41-BN41 -> 3
A42: UND. MUSTANG | B42: 3 | C42: 0 | D42: =B42-C42 -> 3 | E42: 0 | F42: =D42-E42 -> 3 | G42: 11 | H42: 1 | I42: 0 | J42: 0 | K42: =H42+I42-J42 -> 1 | L42: 0 | M42: 7 | N42: =K42+L42-M42 -> -6 | O42: 10 | P42: 0 | Q42: =N42+P42-O42 -> -16 | R42: 5 | S42: 0 | T42: =Q42+S42-R42 -> -21 | U42: 2 | V42: 40 | W42: 39 | X42: 0 | Y42: 5 | Z42: =W42+X42-Y42 -> 34 | AA42: 20 | AB42: 9 | AC42: =Z42+AA42-AB42 -> 45 | AD42: 0 | AE42: 0 | AF42: =AC42+AD42-AE42 -> 45 | AG42: 0 | AH42: 2 | AI42: =AF42+AG42-AH42 -> 43 | AJ42: 0 | AK42: 0 | AL42: =AI42+AJ42-AK42 -> 43 | AM42: 0 | AN42: 0 | AO42: =AL42+AM42-AN42 -> 43 | AP42: 0 | AQ42: 0 | AR42: =AO42+AP42-AQ42 -> 43 | AS42: 0 | AT42: 0 | AU42: =AR42+AS42-AT42 -> 43 | AV42: 0 | AW42: 2 | AX42: =AU42+AV42-AW42 -> 41 | AY42: 0 | AZ42: 16 | BA42: =AX42+AY42-AZ42 -> 25 | BB42: 20 | BC42: 14 | BD42: =BA42+BB42-BC42 -> 31 | BE42: 0 | BF42: 3 | BG42: =BD42+BE42-BF42 -> 28 | BH42: 20 | BI42: 2 | BJ42: =BG42+BH42-BI42 -> 46 | BK42: 0 | BL42: 0 | BM42: =BJ42+BK42-BL42 -> 46 | BN42: 6 | BO42: =BM42-BN42 -> 40
A43: 1/2 LUCKY | B43: 4 | C43: 0 | D43: =B43-C43 -> 4 | E43: 1 | F43: =D43-E43 -> 3 | G43: 0 | H43: 0 | I43: 2 | J43: 4 | K43: =H43+I43-J43 -> -2 | L43: 7 | M43: 0 | N43: =K43+L43-M43 -> 5 | O43: 0 | P43: 0 | Q43: =N43+P43-O43 -> 5 | R43: 0 | S43: 0 | T43: =Q43+S43-R43 -> 5 | U43: 0 | V43: 1 | W43: 2 | X43: 0 | Y43: 1 | Z43: =W43+X43-Y43 -> 1 | AA43: 1 | AB43: 0 | AC43: =Z43+AA43-AB43 -> 2 | AD43: 0 | AE43: 1 | AF43: =AC43+AD43-AE43 -> 1 | AG43: 1 | AH43: 0 | AI43: =AF43+AG43-AH43 -> 2 | AJ43: 0 | AK43: 0 | AL43: =AI43+AJ43-AK43 -> 2 | AM43: 0 | AN43: 1 | AO43: =AL43+AM43-AN43 -> 1 | AP43: 0 | AQ43: 0 | AR43: =AO43+AP43-AQ43 -> 1 | AS43: 1 | AT43: 0 | AU43: =AR43+AS43-AT43 -> 2 | AV43: 0 | AW43: 0 | AX43: =AU43+AV43-AW43 -> 2 | AY43: 0 | AZ43: 0 | BA43: =AX43+AY43-AZ43 -> 2 | BB43: 0 | BC43: 0 | BD43: =BA43+BB43-BC43 -> 2 | BE43: 0 | BF43: 0 | BG43: =BD43+BE43-BF43 -> 2 | BH43: 0 | BI43: 0 | BJ43: =BG43+BH43-BI43 -> 2 | BK43: 0 | BL43: 0 | BM43: =BJ43+BK43-BL43 -> 2 | BN43: 0 | BO43: =BM43-BN43 -> 2
A44: UND. LUCKY | B44: 10 | C44: 4 | D44: =B44-C44 -> 6 | E44: 3 | F44: =D44-E44 -> 3 | G44: 1 | H44: 3 | I44: 0 | J44: 16 | K44: =H44+I44-J44 -> -13 | L44: 0 | M44: 8 | N44: =K44+L44-M44 -> -21 | O44: 7 | P44: 0 | Q44: =N44+P44-O44 -> -28 | R44: 10 | S44: 0 | T44: =Q44+S44-R44 -> -38 | U44: 12 | V44: 40 | W44: 34 | X44: 0 | Y44: 7 | Z44: =W44+X44-Y44 -> 27 | AA44: 20 | AB44: 8 | AC44: =Z44+AA44-AB44 -> 39 | AD44: 0 | AE44: 13 | AF44: =AC44+AD44-AE44 -> 26 | AG44: 0 | AH44: 1 | AI44: 26 | AJ44: 0 | AK44: 12 | AL44: =AI44+AJ44-AK44 -> 14 | AM44: 30 | AN44: 12 | AO44: =AL44+AM44-AN44 -> 32 | AP44: 0 | AQ44: 9 | AR44: =AO44+AP44-AQ44 -> 23 | AS44: 20 | AT44: 11 | AU44: =AR44+AS44-AT44 -> 32 | AV44: 0 | AW44: 13 | AX44: =AU44+AV44-AW44 -> 19 | AY44: 0 | AZ44: 2 | BA44: =AX44+AY44-AZ44 -> 17 | BB44: 0 | BC44: 11 | BD44: =BA44+BB44-BC44 -> 6 | BE44: 0 | BF44: 5 | BG44: =BD44+BE44-BF44 -> 1 | BH44: 20 | BI44: 4 | BJ44: =BG44+BH44-BI44 -> 17 | BK44: 0 | BL44: 0 | BM44: =BJ44+BK44-BL44 -> 17 | BN44: 4 | BO44: =BM44-BN44 -> 13
A45: 1/2 MALBORO ROJO | B45: 4 | C45: 0 | D45: =B45-C45 -> 4 | E45: 0 | F45: =D45-E45 -> 4 | G45: 0 | H45: =F45-G45 -> 4 | I45: 0 | J45: 0 | K45: =H45+I45-J45 -> 4 | L45: 0 | M45: 0 | N45: =K45+L45-M45 -> 4 | O45: 0 | P45: 0 | Q45: =N45+P45-O45 -> 4 | R45: 0 | S45: 0 | T45: =Q45+S45-R45 -> 4 | U45: 0 | V45: 0 | W45: 3 | X45: 0 | Y45: 0 | Z45: =W45+X45-Y45 -> 3 | AA45: 0 | AB45: 0 | AC45: =Z45+AA45-AB45 -> 3 | AD45: 0 | AE45: 0 | AF45: =AC45+AD45-AE45 -> 3 | AG45: 0 | AH45: 0 | AI45: =AF45+AG45-AH45 -> 3 | AJ45: 0 | AK45: 0 | AL45: =AI45+AJ45-AK45 -> 3 | AM45: 0 | AN45: 0 | AO45: =AL45+AM45-AN45 -> 3 | AP45: 0 | AQ45: 0 | AR45: =AO45+AP45-AQ45 -> 3 | AS45: 0 | AT45: 0 | AU45: =AR45+AS45-AT45 -> 3 | AV45: 0 | AW45: 0 | AX45: =AU45+AV45-AW45 -> 3 | AY45: 0 | AZ45: 1 | BA45: =AX45+AY45-AZ45 -> 2 | BB45: 0 | BC45: 0 | BD45: =BA45+BB45-BC45 -> 2 | BE45: 0 | BF45: 0 | BG45: =BD45+BE45-BF45 -> 2 | BH45: 0 | BI45: 0 | BJ45: =BG45+BH45-BI45 -> 2 | BK45: 0 | BL45: 0 | BM45: =BJ45+BK45-BL45 -> 2 | BN45: 0 | BO45: =BM45-BN45 -> 2
A46: UND. MALBORO ROJO | B46: 3 | C46: 1 | D46: =B46-C46 -> 2 | E46: 0 | F46: =D46-E46 -> 2 | G46: 0 | H46: =F46-G46 -> 2 | I46: 0 | J46: 8 | K46: =H46+I46-J46 -> -6 | L46: 0 | M46: 0 | N46: =K46+L46-M46 -> -6 | O46: 1 | P46: 0 | Q46: =N46+P46-O46 -> -7 | R46: 0 | S46: 0 | T46: =Q46+S46-R46 -> -7 | U46: 0 | V46: 0 | W46: 4 | X46: 0 | Y46: 0 | Z46: =W46+X46-Y46 -> 4 | AA46: 0 | AB46: 2 | AC46: =Z46+AA46-AB46 -> 2 | AD46: 0 | AE46: 2 | AF46: =AC46+AD46-AE46 -> 0 | AG46: 0 | AH46: 0 | AI46: =AF46+AG46-AH46 -> 0 | AJ46: 0 | AK46: 0 | AL46: =AI46+AJ46-AK46 -> 0 | AM46: 0 | AN46: 0 | AO46: =AL46+AM46-AN46 -> 0 | AP46: 0 | AQ46: 0 | AR46: =AO46+AP46-AQ46 -> 0 | AS46: 0 | AT46: 0 | AU46: =AR46+AS46-AT46 -> 0 | AV46: 0 | AW46: 0 | AX46: =AU46+AV46-AW46 -> 0 | AY46: 10 | AZ46: 1 | BA46: =AX46+AY46-AZ46 -> 9 | BB46: 0 | BC46: 0 | BD46: =BA46+BB46-BC46 -> 9 | BE46: 0 | BF46: 0 | BG46: =BD46+BE46-BF46 -> 9 | BH46: 0 | BI46: 0 | BJ46: =BG46+BH46-BI46 -> 9 | BK46: 0 | BL46: 4 | BM46: =BJ46+BK46-BL46 -> 5 | BN46: 1 | BO46: =BM46-BN46 -> 4
A47: 1/2 MALBORO FUSION | B47: 1 | C47: 0 | D47: =B47-C47 -> 1 | E47: 0 | F47: =D47-E47 -> 1 | G47: 0 | H47: =F47-G47 -> 1 | I47: 0 | J47: 0 | K47: =H47+I47-J47 -> 1 | L47: 2 | M47: 0 | N47: =K47+L47-M47 -> 3 | O47: 0 | P47: 0 | Q47: =N47+P47-O47 -> 3 | R47: 0 | S47: 0 | T47: =Q47+S47-R47 -> 3 | U47: 0 | V47: 0 | W47: 3 | X47: 0 | Y47: 0 | Z47: =W47+X47-Y47 -> 3 | AA47: 0 | AB47: 0 | AC47: =Z47+AA47-AB47 -> 3 | AD47: 0 | AE47: 0 | AF47: =AC47+AD47-AE47 -> 3 | AG47: 0 | AH47: 0 | AI47: =AF47+AG47-AH47 -> 3 | AJ47: 0 | AK47: 0 | AL47: =AI47+AJ47-AK47 -> 3 | AM47: 0 | AN47: 0 | AO47: =AL47+AM47-AN47 -> 3 | AP47: 0 | AQ47: 0 | AR47: =AO47+AP47-AQ47 -> 3 | AS47: 0 | AT47: 2 | AU47: =AR47+AS47-AT47 -> 1 | AV47: 2 | AW47: 0 | AX47: =AU47+AV47-AW47 -> 3 | AY47: 0 | AZ47: 0 | BA47: =AX47+AY47-AZ47 -> 3 | BB47: 0 | BC47: 0 | BD47: =BA47+BB47-BC47 -> 3 | BE47: 0 | BF47: 0 | BG47: =BD47+BE47-BF47 -> 3 | BH47: 0 | BI47: 0 | BJ47: =BG47+BH47-BI47 -> 3 | BK47: 0 | BL47: 0 | BM47: =BJ47+BK47-BL47 -> 3 | BN47: 0 | BO47: =BM47-BN47 -> 3
A48: UND. MALBORO FUSION | B48: 10 | C48: 2 | D48: =B48-C48 -> 8 | E48: 3 | F48: =D48-E48 -> 5 | G48: 0 | H48: =F48-G48 -> 5 | I48: 0 | J48: 0 | K48: =H48+I48-J48 -> 5 | L48: 0 | M48: 0 | N48: =K48+L48-M48 -> 5 | O48: 0 | P48: 0 | Q48: =N48+P48-O48 -> 5 | R48: 0 | S48: 0 | T48: =Q48+S48-R48 -> 5 | U48: 13 | V48: 20 | W48: 6 | X48: 0 | Y48: 0 | Z48: =W48+X48-Y48 -> 6 | AA48: 20 | AB48: 9 | AC48: =Z48+AA48-AB48 -> 17 | AD48: 0 | AE48: 0 | AF48: =AC48+AD48-AE48 -> 17 | AG48: 0 | AH48: 2 | AI48: 14 | AJ48: 0 | AK48: 0 | AL48: =AI48+AJ48-AK48 -> 14 | AM48: 0 | AN48: 0 | AO48: =AL48+AM48-AN48 -> 14 | AP48: 0 | AQ48: 0 | AR48: =AO48+AP48-AQ48 -> 14 | AS48: 0 | AT48: 10 | AU48: =AR48+AS48-AT48 -> 4 | AV48: 20 | AW48: 3 | AX48: =AU48+AV48-AW48 -> 21 | AY48: 0 | AZ48: 7 | BA48: =AX48+AY48-AZ48 -> 14 | BB48: 0 | BC48: 0 | BD48: =BA48+BB48-BC48 -> 14 | BE48: 0 | BF48: 0 | BG48: =BD48+BE48-BF48 -> 14 | BH48: 0 | BI48: 0 | BJ48: =BG48+BH48-BI48 -> 14 | BK48: 0 | BL48: 0 | BM48: =BJ48+BK48-BL48 -> 14 | BN48: 0 | BO48: =BM48-BN48 -> 14
A49: D.P LIMON | B49: 0 | C49: 0 | D49: =B49-C49 -> 0 | E49: 0 | F49: =D49-E49 -> 0 | G49: 0 | H49: =F49-G49 -> 0 | I49: 0 | J49: 0 | K49: =H49+I49-J49 -> 0 | L49: 0 | M49: 0 | N49: =K49+L49-M49 -> 0 | O49: 0 | P49: 0 | Q49: =N49+P49-O49 -> 0 | R49: 0 | S49: 0 | T49: =Q49+S49-R49 -> 0 | U49: 0 | V49: 0 | W49: =T49+V49-U49 -> 0 | X49: 0 | Y49: 0 | Z49: =W49+X49-Y49 -> 0 | AA49: 0 | AB49: 0 | AC49: =Z49+AA49-AB49 -> 0 | AD49: 0 | AE49: 0 | AF49: =AC49+AD49-AE49 -> 0 | AG49: 6 | AH49: 0 | AI49: =AF49+AG49-AH49 -> 6 | AJ49: 0 | AK49: 0 | AL49: =AI49+AJ49-AK49 -> 6 | AM49: 0 | AN49: 0 | AO49: =AL49+AM49-AN49 -> 6 | AP49: 0 | AQ49: 0 | AR49: =AO49+AP49-AQ49 -> 6 | AS49: 0 | AT49: 0 | AU49: =AR49+AS49-AT49 -> 6 | AV49: 0 | AW49: 0 | AX49: =AU49+AV49-AW49 -> 6 | AY49: 0 | AZ49: 0 | BA49: =AX49+AY49-AZ49 -> 6 | BB49: 0 | BC49: 0 | BD49: =BA49+BB49-BC49 -> 6 | BE49: 0 | BF49: 0 | BG49: =BD49+BE49-BF49 -> 6 | BH49: 0 | BI49: 0 | BJ49: =BG49+BH49-BI49 -> 6 | BK49: 0 | BL49: 0 | BM49: =BJ49+BK49-BL49 -> 6 | BN49: 0 | BO49: =BM49-BN49 -> 6
A50: D.P BBQ | B50: 0 | C50: 0 | D50: =B50-C50 -> 0 | E50: 0 | F50: =D50-E50 -> 0 | G50: 0 | H50: =F50-G50 -> 0 | I50: 0 | J50: 0 | K50: =H50+I50-J50 -> 0 | L50: 0 | M50: 0 | N50: =K50+L50-M50 -> 0 | O50: 0 | P50: 0 | Q50: =N50+P50-O50 -> 0 | R50: 1 | S50: 6 | T50: =Q50+S50-R50 -> 5 | U50: 3 | V50: 0 | W50: =T50+V50-U50 -> 2 | X50: 0 | Y50: 0 | Z50: =W50+X50-Y50 -> 2 | AA50: 0 | AB50: 2 | AC50: =Z50+AA50-AB50 -> 0 | AD50: 0 | AE50: 0 | AF50: =AC50+AD50-AE50 -> 0 | AG50: 6 | AH50: 1 | AI50: =AF50+AG50-AH50 -> 5 | AJ50: 0 | AK50: 2 | AL50: =AI50+AJ50-AK50 -> 3 | AM50: 0 | AN50: 1 | AO50: =AL50+AM50-AN50 -> 2 | AP50: 0 | AQ50: 2 | AR50: =AO50+AP50-AQ50 -> 0 | AS50: 0 | AT50: 0 | AU50: =AR50+AS50-AT50 -> 0 | AV50: 6 | AW50: 1 | AX50: =AU50+AV50-AW50 -> 5 | AY50: 0 | AZ50: 4 | BA50: =AX50+AY50-AZ50 -> 1 | BB50: 0 | BC50: 0 | BD50: =BA50+BB50-BC50 -> 1 | BE50: 0 | BF50: 0 | BG50: =BD50+BE50-BF50 -> 1 | BH50: 0 | BI50: 0 | BJ50: =BG50+BH50-BI50 -> 1 | BK50: 5 | BL50: 0 | BM50: =BJ50+BK50-BL50 -> 6 | BN50: 0 | BO50: =BM50-BN50 -> 6
A51: D.P NATURAL | B51: 2 | C51: 0 | D51: =B51-C51 -> 2 | E51: 1 | F51: =D51-E51 -> 1 | G51: 0 | H51: =F51-G51 -> 1 | I51: 0 | J51: 0 | K51: =H51+I51-J51 -> 1 | L51: 0 | M51: 1 | N51: =K51+L51-M51 -> 0 | O51: 0 | P51: 0 | Q51: =N51+P51-O51 -> 0 | R51: 0 | S51: 6 | T51: =Q51+S51-R51 -> 6 | U51: 0 | V51: 0 | W51: =T51+V51-U51 -> 6 | X51: 0 | Y51: 0 | Z51: =W51+X51-Y51 -> 6 | AA51: 0 | AB51: 2 | AC51: =Z51+AA51-AB51 -> 4 | AD51: 0 | AE51: 3 | AF51: =AC51+AD51-AE51 -> 1 | AG51: 6 | AH51: 0 | AI51: =AF51+AG51-AH51 -> 7 | AJ51: 0 | AK51: 0 | AL51: =AI51+AJ51-AK51 -> 7 | AM51: 0 | AN51: 0 | AO51: =AL51+AM51-AN51 -> 7 | AP51: 0 | AQ51: 2 | AR51: =AO51+AP51-AQ51 -> 5 | AS51: 0 | AT51: 0 | AU51: =AR51+AS51-AT51 -> 5 | AV51: 1 | AW51: 0 | AX51: =AU51+AV51-AW51 -> 6 | AY51: 0 | AZ51: 0 | BA51: =AX51+AY51-AZ51 -> 6 | BB51: 0 | BC51: 0 | BD51: =BA51+BB51-BC51 -> 6 | BE51: 0 | BF51: 0 | BG51: =BD51+BE51-BF51 -> 6 | BH51: 0 | BI51: 0 | BJ51: =BG51+BH51-BI51 -> 6 | BK51: 0 | BL51: 0 | BM51: =BJ51+BK51-BL51 -> 6 | BN51: 0 | BO51: =BM51-BN51 -> 6
A52: D.P MIX | B52: 1 | C52: 1 | D52: =B52-C52 -> 0 | E52: 0 | F52: =D52-E52 -> 0 | G52: 0 | H52: =F52-G52 -> 0 | I52: 0 | J52: 0 | K52: =H52+I52-J52 -> 0 | L52: 0 | M52: 0 | N52: =K52+L52-M52 -> 0 | O52: 0 | P52: 0 | Q52: =N52+P52-O52 -> 0 | R52: 0 | S52: 6 | T52: =Q52+S52-R52 -> 6 | U52: 0 | V52: 0 | W52: =T52+V52-U52 -> 6 | X52: 0 | Y52: 0 | Z52: =W52+X52-Y52 -> 6 | AA52: 0 | AB52: 6 | AC52: =Z52+AA52-AB52 -> 0 | AD52: 0 | AE52: 0 | AF52: =AC52+AD52-AE52 -> 0 | AG52: 6 | AH52: 0 | AI52: =AF52+AG52-AH52 -> 6 | AJ52: 0 | AK52: 0 | AL52: =AI52+AJ52-AK52 -> 6 | AM52: 0 | AN52: 0 | AO52: =AL52+AM52-AN52 -> 6 | AP52: 0 | AQ52: 4 | AR52: =AO52+AP52-AQ52 -> 2 | AS52: 0 | AT52: 0 | AU52: =AR52+AS52-AT52 -> 2 | AV52: 4 | AW52: 1 | AX52: =AU52+AV52-AW52 -> 5 | AY52: 0 | AZ52: 0 | BA52: =AX52+AY52-AZ52 -> 5 | BB52: 0 | BC52: 1 | BD52: =BA52+BB52-BC52 -> 4 | BE52: 0 | BF52: 2 | BG52: =BD52+BE52-BF52 -> 2 | BH52: 0 | BI52: 0 | BJ52: =BG52+BH52-BI52 -> 2 | BK52: 4 | BL52: 0 | BM52: =BJ52+BK52-BL52 -> 6 | BN52: 3 | BO52: =BM52-BN52 -> 3
A53: TRIDENT | B53: 2 | C53: 0 | D53: =B53-C53 -> 2 | E53: 1 | F53: =D53-E53 -> 1 | G53: 0 | H53: =F53-G53 -> 1 | I53: 0 | J53: 1 | K53: =H53+I53-J53 -> 0 | L53: 0 | M53: 0 | N53: =K53+L53-M53 -> 0 | O53: 0 | P53: 0 | Q53: =N53+P53-O53 -> 0 | R53: 0 | S53: 0 | T53: =Q53+S53-R53 -> 0 | U53: 0 | V53: 0 | W53: =T53+V53-U53 -> 0 | X53: 0 | Y53: 0 | Z53: =W53+X53-Y53 -> 0 | AA53: 0 | AB53: 0 | AC53: =Z53+AA53-AB53 -> 0 | AD53: 0 | AE53: 0 | AF53: =AC53+AD53-AE53 -> 0 | AG53: 0 | AH53: 0 | AI53: =AF53+AG53-AH53 -> 0 | AJ53: 0 | AK53: 0 | AL53: =AI53+AJ53-AK53 -> 0 | AM53: 0 | AN53: 0 | AO53: =AL53+AM53-AN53 -> 0 | AP53: 0 | AQ53: 0 | AR53: =AO53+AP53-AQ53 -> 0 | AS53: 0 | AT53: 0 | AU53: =AR53+AS53-AT53 -> 0 | AV53: 0 | AW53: 0 | AX53: =AU53+AV53-AW53 -> 0 | AY53: 0 | AZ53: 0 | BA53: =AX53+AY53-AZ53 -> 0 | BB53: 0 | BC53: 0 | BD53: =BA53+BB53-BC53 -> 0 | BE53: 0 | BF53: 0 | BG53: =BD53+BE53-BF53 -> 0 | BH53: 0 | BI53: 0 | BJ53: =BG53+BH53-BI53 -> 0 | BK53: 0 | BL53: 0 | BM53: =BJ53+BK53-BL53 -> 0 | BN53: 0 | BO53: =BM53-BN53 -> 0
A54: CHICLETS XTIME | B54: 0 | C54: 0 | D54: =B54-C54 -> 0 | E54: 0 | F54: =D54-E54 -> 0 | G54: 0 | H54: =F54-G54 -> 0 | I54: 30 | J54: 23 | K54: =H54+I54-J54 -> 7 | L54: 0 | M54: 1 | N54: =K54+L54-M54 -> 6 | O54: 1 | P54: 0 | Q54: =N54+P54-O54 -> 5 | R54: 0 | S54: 0 | T54: =Q54+S54-R54 -> 5 | U54: 0 | V54: 0 | W54: 0 | X54: 0 | Y54: 0 | Z54: =W54+X54-Y54 -> 0 | AA54: 0 | AB54: 0 | AC54: =Z54+AA54-AB54 -> 0 | AD54: 0 | AE54: 0 | AF54: =AC54+AD54-AE54 -> 0 | AG54: 0 | AH54: 0 | AI54: =AF54+AG54-AH54 -> 0 | AJ54: 0 | AK54: 0 | AL54: =AI54+AJ54-AK54 -> 0 | AM54: 0 | AN54: 0 | AO54: =AL54+AM54-AN54 -> 0 | AP54: 0 | AQ54: 0 | AR54: =AO54+AP54-AQ54 -> 0 | AS54: 0 | AT54: 0 | AU54: =AR54+AS54-AT54 -> 0 | AV54: 0 | AW54: 0 | AX54: =AU54+AV54-AW54 -> 0 | AY54: 0 | AZ54: 0 | BA54: =AX54+AY54-AZ54 -> 0 | BB54: 0 | BC54: 0 | BD54: =BA54+BB54-BC54 -> 0 | BE54: 0 | BF54: 0 | BG54: =BD54+BE54-BF54 -> 0 | BH54: 0 | BI54: 0 | BJ54: =BG54+BH54-BI54 -> 0 | BK54: 0 | BL54: 0 | BM54: =BJ54+BK54-BL54 -> 0 | BN54: 0 | BO54: =BM54-BN54 -> 0
A55: BOMBOMBUM | B55: 14 | C55: 0 | D55: =B55-C55 -> 14 | E55: 0 | F55: =D55-E55 -> 14 | G55: 1 | H55: =F55-G55 -> 13 | I55: 0 | J55: 10 | K55: =H55+I55-J55 -> 3 | L55: 0 | M55: 0 | N55: =K55+L55-M55 -> 3 | O55: 0 | P55: 0 | Q55: =N55+P55-O55 -> 3 | R55: 0 | S55: 0 | T55: =Q55+S55-R55 -> 3 | U55: 0 | V55: 0 | W55: 1 | X55: 0 | Y55: 0 | Z55: =W55+X55-Y55 -> 1 | AA55: 0 | AB55: 0 | AC55: =Z55+AA55-AB55 -> 1 | AD55: 0 | AE55: 0 | AF55: =AC55+AD55-AE55 -> 1 | AG55: 0 | AH55: 0 | AI55: =AF55+AG55-AH55 -> 1 | AJ55: 0 | AK55: 0 | AL55: =AI55+AJ55-AK55 -> 1 | AM55: 0 | AN55: 0 | AO55: =AL55+AM55-AN55 -> 1 | AP55: 0 | AQ55: 0 | AR55: =AO55+AP55-AQ55 -> 1 | AS55: 0 | AT55: 0 | AU55: =AR55+AS55-AT55 -> 1 | AV55: 0 | AW55: 0 | AX55: =AU55+AV55-AW55 -> 1 | AY55: 0 | AZ55: 0 | BA55: =AX55+AY55-AZ55 -> 1 | BB55: 0 | BC55: 0 | BD55: =BA55+BB55-BC55 -> 1 | BE55: 0 | BF55: 0 | BG55: =BD55+BE55-BF55 -> 1 | BH55: 0 | BI55: 0 | BJ55: =BG55+BH55-BI55 -> 1 | BK55: 0 | BL55: 0 | BM55: =BJ55+BK55-BL55 -> 1 | BN55: 0 | BO55: =BM55-BN55 -> 1
A56: BOTELLA AGT. AMARILLO | B56: 0 | C56: 0 | D56: =B56-C56 -> 0 | E56: 0 | F56: =D56-E56 -> 0 | G56: 0 | H56: =F56-G56 -> 0 | I56: 1 | J56: 1 | K56: 0 | L56: 0 | M56: 0 | N56: =K56+L56-M56 -> 0 | O56: 1 | P56: 2 | Q56: =N56+P56-O56 -> 1 | R56: 0 | S56: 0 | T56: =Q56+S56-R56 -> 1 | U56: 0 | V56: 0 | W56: =T56+V56-U56 -> 1 | X56: 0 | Y56: 1 | Z56: =W56+X56-Y56 -> 0 | AA56: 0 | AB56: 0 | AC56: =Z56+AA56-AB56 -> 0 | AD56: 0 | AE56: 0 | AF56: =AC56+AD56-AE56 -> 0 | AG56: 0 | AH56: 0 | AI56: =AF56+AG56-AH56 -> 0 | AJ56: 0 | AK56: 0 | AL56: =AI56+AJ56-AK56 -> 0 | AM56: 0 | AN56: 0 | AO56: =AL56+AM56-AN56 -> 0 | AP56: 0 | AQ56: 0 | AR56: =AO56+AP56-AQ56 -> 0 | AS56: 0 | AT56: 0 | AU56: =AR56+AS56-AT56 -> 0 | AV56: 0 | AW56: 0 | AX56: =AU56+AV56-AW56 -> 0 | AY56: 0 | AZ56: 0 | BA56: =AX56+AY56-AZ56 -> 0 | BB56: 0 | BC56: 0 | BD56: =BA56+BB56-BC56 -> 0 | BE56: 0 | BF56: 0 | BG56: =BD56+BE56-BF56 -> 0 | BH56: 0 | BI56: 0 | BJ56: =BG56+BH56-BI56 -> 0 | BK56: 0 | BL56: 0 | BM56: 1 | BN56: 0 | BO56: =BM56-BN56 -> 1
H58: 1 LIGTH | K58: 3 COSTEÑAS - 1 AGUA
T59: 1 poker falta
T60: 1 coronita

Sheet GANAN. ENE
A1: PRODUCTO | B1: PRECIO | C1: VR UNIDAD | D1: VR VENTA | E1: VR GANANCIA | F1: 09/01/25 VENTA | G1: 09/01/25 GANANCIA | H1: 10/01/25 VENTA | I1: 10/01/25 GANANCIA | J1: 11/01/25 VENTA | K1: 11/01/25 GANANCIA | L1: 12/01/25 VENTA | M1: 12/01/25 GANANCIA | N1: 13/01/25 VENTA | O1: 13/01/25 GANANCIA | P1: 14/01/25 VENTA | Q1: 14/01/25 GANANCIA | R1: 15/01/25 VENTA | S1: 15/01/25 GANANCIA | T1: 16/01/25 VENTA | U1: 16/01/25 GANANCIA | V1: 17/01/25 VENTA | W1: 17/01/25 GANANCIA | X1: 18/01/25 VENTA | Y1: 18/01/25 GANANCIA | Z1: 19/01/25 VENTA | AA1: 19/01/25 GANANCIA | AB1: 20/01/25 VENTA | AC1: 20/01/25 GANANCIA | AD1: 21/01/25 VENTA | AE1: 21/01/25 GANANCIA | AF1: 22/01/25 VENTA | AG1: 22/01/25 GANANCIA | AH1: 23/01/25 VENTA | AI1: 23/01/25 GANANCIA | AJ1: 24/01/25 VENTA | AK1: 24/01/25 GANANCIA | AL1: 25/01/25 VENTA | AM1: 25/01/25 GANANCIA | AN1: 26/01/25 VENTA | AO1: 26/01/25 GANANCIA | AP1: 27/01/25 VENTA | AQ1: 27/01/25 GANANCIA | AR1: 28/01/25 VENTA | AS1: 28/01/25 GANANCIA | AT1: 29/01/25 VENTA | AU1: 29/01/25 GANANCIA | AV1: 30/01/25 VENTA | AW1: 30/01/25 GANANCIA | AX1: 31/01/25 VENTA | AY1: 31/01/25 GANANCIA
A2: AGUA X24 | B2: 27000 | C2: 1125 | D2: 3000 | E2: =D2-C2 -> 1875 | F2: 0 | G2: =F2*E2 -> 0 | H2: 0 | I2: =H2*E2 -> 0 | J2: 0 | K2: =J2*E2 -> 0 | L2: 8 | M2: =L2*E2 -> 15000 | N2: 2 | O2: =N2*E2 -> 3750 | P2: 2 | Q2: =P2*E2 -> 3750 | R2: 1 | S2: =R2*E2 -> 1875 | T2: 0 | U2: =T2*E2 -> 0 | V2: 0 | W2: =V2*E2 -> 0 | X2: 1 | Y2: =X2*E2 -> 1875 | Z2: 0 | AA2: =Z2*E2 -> 0 | AB2: 0 | AC2: =AB2*E2 -> 0 | AD2: 5 | AE2: =AD2*E2 -> 9375 | AF2: 0 | AG2: =AF2*E2 -> 0 | AH2: 12 | AI2: =AH2*E2 -> 22500 | AJ2: 0 | AK2: =AJ2*E2 -> 0 | AL2: 2 | AM2: =AL2*E2 -> 3750 | AN2: 0 | AO2: =AN2*E2 -> 0 | AP2: 3 | AQ2: =AP2*E2 -> 5625 | AR2: 0 | AS2: =AR2*E2 -> 0 | AT2: 1 | AU2: =AT2*E2 -> 1875 | AV2: 1 | AW2: =AV2*E2 -> 1875 | AX2: 3 | AY2: =AX2*E2 -> 5625
A3: COCA COLA | B3: 28000 | C3: 2333 | D3: 3500 | E3: =D3-C3 -> 1167 | F3: 1 | G3: =F3*E3 -> 1167 | H3: 0 | I3: =H3*E3 -> 0 | J3: 0 | K3: =J3*E3 -> 0 | L3: 0 | M3: =L3*E3 -> 0 | N3: 0 | O3: =N3*E3 -> 0 | P3: 0 | Q3: =P3*E3 -> 0 | R3: 0 | S3: =R3*E3 -> 0 | T3: 0 | U3: =T3*E3 -> 0 | V3: 0 | W3: =V3*E3 -> 0 | X3: 0 | Y3: =X3*E3 -> 0 | Z3: 0 | AA3: =Z3*E3 -> 0 | AB3: 0 | AC3: =AB3*E3 -> 0 | AD3: 0 | AE3: =AD3*E3 -> 0 | AF3: 0 | AG3: =AF3*E3 -> 0 | AH3: 0 | AI3: =AH3*E3 -> 0 | AJ3: 0 | AK3: =AJ3*E3 -> 0 | AL3: 1 | AM3: =AL3*E3 -> 1167 | AN3: 1 | AO3: =AN3*E3 -> 1167 | AP3: 2 | AQ3: =AP3*E3 -> 2334 | AR3: 0 | AS3: =AR3*E3 -> 0 | AT3: 0 | AU3: =AT3*E3 -> 0 | AV3: 0 | AW3: =AV3*E3 -> 0 | AX3: 0 | AY3: =AX3*E3 -> 0
A4: GATORADE | B4: 37000 | C4: 3083 | D4: 4000 | E4: =D4-C4 -> 917 | F4: 0 | G4: =F4*E4 -> 0 | H4: 1 | I4: =H4*E4 -> 917 | J4: 0 | K4: =J4*E4 -> 0 | L4: 1 | M4: =L4*E4 -> 917 | N4: 4 | O4: =N4*E4 -> 3668 | P4: 0 | Q4: =P4*E4 -> 0 | R4: 2 | S4: =R4*E4 -> 1834 | T4: 1 | U4: =T4*E4 -> 917 | V4: 0 | W4: =V4*E4 -> 0 | X4: 1 | Y4: =X4*E4 -> 917 | Z4: 0 | AA4: =Z4*E4 -> 0 | AB4: 2 | AC4: =AB4*E4 -> 1834 | AD4: 0 | AE4: =AD4*E4 -> 0 | AF4: 0 | AG4: =AF4*E4 -> 0 | AH4: 0 | AI4: =AH4*E4 -> 0 | AJ4: 1 | AK4: =AJ4*E4 -> 917 | AL4: 0 | AM4: =AL4*E4 -> 0 | AN4: 0 | AO4: =AN4*E4 -> 0 | AP4: 0 | AQ4: =AP4*E4 -> 0 | AR4: 2 | AS4: =AR4*E4 -> 1834 | AT4: 0 | AU4: =AT4*E4 -> 0 | AV4: 0 | AW4: =AV4*E4 -> 0 | AX4: 1 | AY4: =AX4*E4 -> 917
A5: SMIRNOFF | B5: 8000 | C5: 8000 | D5: 12000 | E5: =D5-C5 -> 4000 | F5: 0 | G5: =F5*E5 -> 0 | H5: 0 | I5: =H5*E5 -> 0 | J5: 0 | K5: =J5*E5 -> 0 | L5: 0 | M5: =L5*E5 -> 0 | N5: 3 | O5: =N5*E5 -> 12000 | P5: 0 | Q5: =P5*E5 -> 0 | R5: 0 | S5: =R5*E5 -> 0 | T5: 0 | U5: =T5*E5 -> 0 | V5: 0 | W5: =V5*E5 -> 0 | X5: 1 | Y5: =X5*E5 -> 4000 | Z5: 0 | AA5: =Z5*E5 -> 0 | AB5: 0 | AC5: =AB5*E5 -> 0 | AD5: 0 | AE5: =AD5*E5 -> 0 | AF5: 0 | AG5: =AF5*E5 -> 0 | AH5: 1 | AI5: =AH5*E5 -> 4000 | AJ5: 0 | AK5: =AJ5*E5 -> 0 | AL5: 0 | AM5: =AL5*E5 -> 0 | AN5: 0 | AO5: =AN5*E5 -> 0 | AP5: 0 | AQ5: =AP5*E5 -> 0 | AR5: 1 | AS5: =AR5*E5 -> 4000 | AT5: 0 | AU5: =AT5*E5 -> 0 | AV5: 0 | AW5: =AV5*E5 -> 0 | AX5: 0 | AY5: =AX5*E5 -> 0
A6: GASEOSA CUATRO | B6: 2000 | C6: 2000 | D6: 3000 | E6: =D6-C6 -> 1000 | F6: 0 | G6: =F6*E6 -> 0 | H6: 0 | I6: =H6*E6 -> 0 | J6: 1 | K6: =J6*E6 -> 1000 | L6: 1 | M6: =L6*E6 -> 1000 | N6: 0 | O6: =N6*E6 -> 0 | P6: 1 | Q6: =P6*E6 -> 1000 | R6: 0 | S6: =R6*E6 -> 0 | T6: 0 | U6: =T6*E6 -> 0 | V6: 0 | W6: =V6*E6 -> 0 | X6: 0 | Y6: =X6*E6 -> 0 | Z6: 0 | AA6: =Z6*E6 -> 0 | AB6: 0 | AC6: =AB6*E6 -> 0 | AD6: 0 | AE6: =AD6*E6 -> 0 | AF6: 0 | AG6: =AF6*E6 -> 0 | AH6: 0 | AI6: =AH6*E6 -> 0 | AJ6: 0 | AK6: =AJ6*E6 -> 0 | AL6: 0 | AM6: =AL6*E6 -> 0 | AN6: 0 | AO6: =AN6*E6 -> 0 | AP6: 0 | AQ6: =AP6*E6 -> 0 | AR6: 0 | AS6: =AR6*E6 -> 0 | AT6: 0 | AU6: =AT6*E6 -> 0 | AV6: 0 | AW6: =AV6*E6 -> 0 | AX6: 0 | AY6: =AX6*E6 -> 0
A7: GASEOSA CANADA DRY | B7: 2000 | C7: 2000 | D7: 3000 | E7: =D7-C7 -> 1000 | F7: 1 | G7: =F7*E7 -> 1000 | H7: 4 | I7: =H7*E7 -> 4000 | J7: 0 | K7: =J7*E7 -> 0 | L7: 0 | M7: =L7*E7 -> 0 | N7: 0 | O7: =N7*E7 -> 0 | P7: 0 | Q7: =P7*E7 -> 0 | R7: 0 | S7: =R7*E7 -> 0 | T7: 2 | U7: =T7*E7 -> 2000 | V7: 0 | W7: =V7*E7 -> 0 | X7: 0 | Y7: =X7*E7 -> 0 | Z7: 1 | AA7: =Z7*E7 -> 1000 | AB7: 0 | AC7: =AB7*E7 -> 0 | AD7: 0 | AE7: =AD7*E7 -> 0 | AF7: 0 | AG7: =AF7*E7 -> 0 | AH7: 0 | AI7: =AH7*E7 -> 0 | AJ7: 0 | AK7: =AJ7*E7 -> 0 | AL7: 1 | AM7: =AL7*E7 -> 1000 | AN7: 0 | AO7: =AN7*E7 -> 0 | AP7: 0 | AQ7: =AP7*E7 -> 0 | AR7: 0 | AS7: =AR7*E7 -> 0 | AT7: 0 | AU7: =AT7*E7 -> 0 | AV7: 0 | AW7: =AV7*E7 -> 0 | AX7: 0 | AY7: =AX7*E7 -> 0
A8: GASEOSA SHWEPPES | B8: 2000 | C8: 2000 | D8: 3000 | E8: =D8-C8 -> 1000 | F8: 0 | G8: =F8*E8 -> 0 | H8: 0 | I8: =H8*E8 -> 0 | J8: 0 | K8: =J8*E8 -> 0 | L8: 0 | M8: =L8*E8 -> 0 | N8: 0 | O8: =N8*E8 -> 0 | P8: 0 | Q8: =P8*E8 -> 0 | R8: 0 | S8: =R8*E8 -> 0 | T8: 0 | U8: =T8*E8 -> 0 | V8: 0 | W8: =V8*E8 -> 0 | X8: 0 | Y8: =X8*E8 -> 0 | Z8: 1 | AA8: =Z8*E8 -> 1000 | AB8: 0 | AC8: =AB8*E8 -> 0 | AD8: 0 | AE8: =AD8*E8 -> 0 | AF8: 0 | AG8: =AF8*E8 -> 0 | AH8: 0 | AI8: =AH8*E8 -> 0 | AJ8: 0 | AK8: =AJ8*E8 -> 0 | AL8: 0 | AM8: =AL8*E8 -> 0 | AN8: 0 | AO8: =AN8*E8 -> 0 | AP8: 0 | AQ8: =AP8*E8 -> 0 | AR8: 0 | AS8: =AR8*E8 -> 0 | AT8: 0 | AU8: =AT8*E8 -> 0 | AV8: 0 | AW8: =AV8*E8 -> 0 | AX8: 0 | AY8: =AX8*E8 -> 0
A9: BRETAÑA | B9: 46800 | C9: 1950 | D9: 4000 | E9: =D9-C9 -> 2050 | F9: 0 | G9: =F9*E9 -> 0 | H9: 1 | I9: =H9*E9 -> 2050 | J9: 0 | K9: =J9*E9 -> 0 | L9: 1 | M9: =L9*E9 -> 2050 | N9: 0 | O9: =N9*E9 -> 0 | P9: 0 | Q9: =P9*E9 -> 0 | R9: 0 | S9: =R9*E9 -> 0 | T9: 0 | U9: =T9*E9 -> 0 | V9: 0 | W9: =V9*E9 -> 0 | X9: 1 | Y9: =X9*E9 -> 2050 | Z9: 1 | AA9: =Z9*E9 -> 2050 | AB9: 0 | AC9: =AB9*E9 -> 0 | AD9: 1 | AE9: =AD9*E9 -> 2050 | AF9: 0 | AG9: =AF9*E9 -> 0 | AH9: 5 | AI9: =AH9*E9 -> 10250 | AJ9: 2 | AK9: =AJ9*E9 -> 4100 | AL9: 0 | AM9: =AL9*E9 -> 0 | AN9: 1 | AO9: =AN9*E9 -> 2050 | AP9: 0 | AQ9: =AP9*E9 -> 0 | AR9: 0 | AS9: =AR9*E9 -> 0 | AT9: 2 | AU9: =AT9*E9 -> 4100 | AV9: 0 | AW9: =AV9*E9 -> 0 | AX9: 0 | AY9: =AX9*E9 -> 0
A10: SPEED MAX | B10: 2500 | C10: 2500 | D10: 3500 | E10: =D10-C10 -> 1000 | F10: 0 | G10: =F10*E10 -> 0 | H10: 0 | I10: =H10*E10 -> 0 | J10: 0 | K10: =J10*E10 -> 0 | L10: 0 | M10: =L10*E10 -> 0 | N10: 0 | O10: =N10*E10 -> 0 | P10: 0 | Q10: =P10*E10 -> 0 | R10: 0 | S10: =R10*E10 -> 0 | T10: 0 | U10: =T10*E10 -> 0 | V10: 0 | W10: =V10*E10 -> 0 | X10: 0 | Y10: =X10*E10 -> 0 | Z10: 0 | AA10: =Z10*E10 -> 0 | AB10: 2 | AC10: =AB10*E10 -> 2000 | AD10: 1 | AE10: =AD10*E10 -> 1000 | AF10: 0 | AG10: =AF10*E10 -> 0 | AH10: 0 | AI10: =AH10*E10 -> 0 | AJ10: 0 | AK10: =AJ10*E10 -> 0 | AL10: 0 | AM10: =AL10*E10 -> 0 | AN10: 0 | AO10: =AN10*E10 -> 0 | AP10: 0 | AQ10: =AP10*E10 -> 0 | AR10: 0 | AS10: =AR10*E10 -> 0 | AT10: 0 | AU10: =AT10*E10 -> 0 | AV10: 0 | AW10: =AV10*E10 -> 0 | AX10: 0 | AY10: =AX10*E10 -> 0
A11: REDBULL | B11: 6150 | C11: 6150 | D11: 10000 | E11: =D11-C11 -> 3850 | F11: 0 | G11: =F11*E11 -> 0 | H11: 0 | I11: =H11*E11 -> 0 | J11: 0 | K11: =J11*E11 -> 0 | L11: 1 | M11: =L11*E11 -> 3850 | N11: 0 | O11: =N11*E11 -> 0 | P11: 0 | Q11: =P11*E11 -> 0 | R11: 0 | S11: =R11*E11 -> 0 | T11: 0 | U11: =T11*E11 -> 0 | V11: 0 | W11: =V11*E11 -> 0 | X11: 0 | Y11: =X11*E11 -> 0 | Z11: 0 | AA11: =Z11*E11 -> 0 | AB11: 0 | AC11: =AB11*E11 -> 0 | AD11: 0 | AE11: =AD11*E11 -> 0 | AF11: 0 | AG11: =AF11*E11 -> 0 | AH11: 0 | AI11: =AH11*E11 -> 0 | AJ11: 0 | AK11: =AJ11*E11 -> 0 | AL11: 0 | AM11: =AL11*E11 -> 0 | AN11: 0 | AO11: =AN11*E11 -> 0 | AP11: 0 | AQ11: =AP11*E11 -> 0 | AR11: 0 | AS11: =AR11*E11 -> 0 | AT11: 0 | AU11: =AT11*E11 -> 0 | AV11: 0 | AW11: =AV11*E11 -> 0 | AX11: 0 | AY11: =AX11*E11 -> 0
A12: ELECTROLIT | B12: 6800 | C12: 6800 | D12: 10000 | E12: =D12-C12 -> 3200 | F12: 0 | G12: =F12*E12 -> 0 | H12: 0 | I12: =H12*E12 -> 0 | J12: 0 | K12: =J12*E12 -> 0 | L12: 3 | M12: =L12*E12 -> 9600 | N12: 16 | O12: =N12*E12 -> 51200 | P12: 0 | Q12: =P12*E12 -> 0 | R12: 0 | S12: =R12*E12 -> 0 | T12: 0 | U12: =T12*E12 -> 0 | V12: 0 | W12: =V12*E12 -> 0 | X12: 0 | Y12: =X12*E12 -> 0 | Z12: 0 | AA12: =Z12*E12 -> 0 | AB12: 1 | AC12: =AB12*E12 -> 3200 | AD12: 1 | AE12: =AD12*E12 -> 3200 | AF12: 0 | AG12: =AF12*E12 -> 0 | AH12: 0 | AI12: =AH12*E12 -> 0 | AJ12: 0 | AK12: =AJ12*E12 -> 0 | AL12: 0 | AM12: =AL12*E12 -> 0 | AN12: 0 | AO12: =AN12*E12 -> 0 | AP12: 0 | AQ12: =AP12*E12 -> 0 | AR12: 0 | AS12: =AR12*E12 -> 0 | AT12: 0 | AU12: =AT12*E12 -> 0 | AV12: 0 | AW12: =AV12*E12 -> 0 | AX12: 0 | AY12: =AX12*E12 -> 0
A13: POKER LATA | B13: 60000 | C13: 2500 | D13: 5000 | E13: =D13-C13 -> 2500 | F13: 0 | G13: =F13*E13 -> 0 | H13: 0 | I13: =H13*E13 -> 0 | J13: 0 | K13: =J13*E13 -> 0 | L13: 0 | M13: =L13*E13 -> 0 | N13: 0 | O13: =N13*E13 -> 0 | P13: 1 | Q13: =P13*E13 -> 2500 | R13: 0 | S13: =R13*E13 -> 0 | T13: 0 | U13: =T13*E13 -> 0 | V13: 0 | W13: =V13*E13 -> 0 | X13: 0 | Y13: =X13*E13 -> 0 | Z13: 0 | AA13: =Z13*E13 -> 0 | AB13: 0 | AC13: =AB13*E13 -> 0 | AD13: 0 | AE13: =AD13*E13 -> 0 | AF13: 0 | AG13: =AF13*E13 -> 0 | AH13: 0 | AI13: =AH13*E13 -> 0 | AJ13: 0 | AK13: =AJ13*E13 -> 0 | AL13: 0 | AM13: =AL13*E13 -> 0 | AN13: 0 | AO13: =AN13*E13 -> 0 | AP13: 0 | AQ13: =AP13*E13 -> 0 | AR13: 0 | AS13: =AR13*E13 -> 0 | AT13: 0 | AU13: =AT13*E13 -> 0 | AV13: 0 | AW13: =AV13*E13 -> 0 | AX13: 0 | AY13: =AX13*E13 -> 0
... A15: CORONITA LATA | B15: 56000 | C15: 2333 | D15: 5000 | E15: =D15-C15 -> 2667 | F15: 0 | G15: =F15*E15 -> 0 | H15: 0 | I15: =H15*E15 -> 0 | J15: 0 | K15: =J15*E15 -> 0 | L15: 0 | M15: =L15*E15 -> 0 | N15: 0 | O15: =N15*E15 -> 0 | P15: 0 | Q15: =P15*E15 -> 0 | R15: 0 | S15: =R15*E15 -> 0 | T15: 0 | U15: =T15*E15 -> 0 | V15: 0 | W15: =V15*E15 -> 0 | X15: 0 | Y15: =X15*E15 -> 0 | Z15: 0 | AA15: =Z15*E15 -> 0 | AB15: 0 | AC15: =AB15*E15 -> 0 | AD15: 0 | AE15: =AD15*E15 -> 0 | AF15: 0 | AG15: =AF15*E15 -> 0 | AH15: 0 | AI15: =AH15*E15 -> 0 | AJ15: 0 | AK15: =AJ15*E15 -> 0 | AL15: 0 | AM15: =AL15*E15 -> 0 | AN15: 0 | AO15: =AN15*E15 -> 0 | AP15: 0 | AQ15: =AP15*E15 -> 0 | AR15: 0 | AS15: =AR15*E15 -> 0 | AT15: 0 | AU15: =AT15*E15 -> 0 | AV15: 0 | AW15: =AV15*E15 -> 0 | AX15: 0 | AY15: =AX15*E15 -> 0
A16: CORONA LATA | D16: 7000 | E16: =D16-C16 -> 7000 | F16: 0 | G16: =F16*E16 -> 0 | H16: 0 | I16: =H16*E16 -> 0 | J16: 0 | K16: =J16*E16 -> 0 | L16: 0 | M16: =L16*E16 -> 0 | N16: 0 | O16: =N16*E16 -> 0 | P16: 0 | Q16: =P16*E16 -> 0 | R16: 0 | S16: =R16*E16 -> 0 | T16: 0 | U16: =T16*E16 -> 0 | V16: 0 | W16: =V16*E16 -> 0 | X16: 0 | Y16: =X16*E16 -> 0 | Z16: 0 | AA16: =Z16*E16 -> 0 | AB16: 0 | AC16: =AB16*E16 -> 0 | AD16: 0 | AE16: =AD16*E16 -> 0 | AF16: 0 | AG16: =AF16*E16 -> 0 | AH16: 0 | AI16: =AH16*E16 -> 0 | AJ16: 0 | AK16: =AJ16*E16 -> 0 | AL16: 0 | AM16: =AL16*E16 -> 0 | AN16: 0 | AO16: =AN16*E16 -> 0 | AP16: 0 | AQ16: =AP16*E16 -> 0 | AR16: 0 | AS16: =AR16*E16 -> 0 | AT16: 0 | AU16: =AT16*E16 -> 0 | AV16: 0 | AW16: =AV16*E16 -> 0 | AX16: 0 | AY16: =AX16*E16 -> 0
A17: HEINEKEN LATA X24 | B17: 46000 | C17: 1916 | D17: 6000 | E17: =D17-C17 -> 4084 | F17: 0 | G17: =F17*E17 -> 0 | H17: 0 | I17: =H17*E17 -> 0 | J17: 0 | K17: =J17*E17 -> 0 | L17: 0 | M17: =L17*E17 -> 0 | N17: 0 | O17: =N17*E17 -> 0 | P17: 0 | Q17: =P17*E17 -> 0 | R17: 0 | S17: =R17*E17 -> 0 | T17: 0 | U17: =T17*E17 -> 0 | V17: 0 | W17: =V17*E17 -> 0 | X17: 0 | Y17: =X17*E17 -> 0 | Z17: 0 | AA17: =Z17*E17 -> 0 | AB17: 0 | AC17: =AB17*E17 -> 0 | AD17: 0 | AE17: =AD17*E17 -> 0 | AF17: 0 | AG17: =AF17*E17 -> 0 | AH17: 0 | AI17: =AH17*E17 -> 0 | AJ17: 0 | AK17: =AJ17*E17 -> 0 | AL17: 0 | AM17: =AL17*E17 -> 0 | AN17: 0 | AO17: =AN17*E17 -> 0 | AP17: 0 | AQ17: =AP17*E17 -> 0 | AR17: 0 | AS17: =AR17*E17 -> 0 | AT17: 0 | AU17: =AT17*E17 -> 0 | AV17: 0 | AW17: =AV17*E17 -> 0 | AX17: 0 | AY17: =AX17*E17 -> 0
A18: SOL PEQUEÑA X24 | B18: 55000 | C18: 2291 | D18: 4000 | E18: =D18-C18 -> 1709 | F18: 0 | G18: =F18*E18 -> 0 | H18: 0 | I18: =H18*E18 -> 0 | J18: 0 | K18: =J18*E18 -> 0 | L18: 0 | M18: =L18*E18 -> 0 | N18: 0 | O18: =N18*E18 -> 0 | P18: 0 | Q18: =P18*E18 -> 0 | R18: 0 | S18: =R18*E18 -> 0 | T18: 0 | U18: =T18*E18 -> 0 | V18: 0 | W18: =V18*E18 -> 0 | X18: 0 | Y18: =X18*E18 -> 0 | Z18: 0 | AA18: =Z18*E18 -> 0 | AB18: 0 | AC18: =AB18*E18 -> 0 | AD18: 0 | AE18: =AD18*E18 -> 0 | AF18: 0 | AG18: =AF18*E18 -> 0 | AH18: 0 | AI18: =AH18*E18 -> 0 | AJ18: 0 | AK18: =AJ18*E18 -> 0 | AL18: 0 | AM18: =AL18*E18 -> 0 | AN18: 0 | AO18: =AN18*E18 -> 0 | AP18: 0 | AQ18: =AP18*E18 -> 0 | AR18: 0 | AS18: =AR18*E18 -> 0 | AT18: 0 | AU18: =AT18*E18 -> 0 | AV18: 0 | AW18: =AV18*E18 -> 0 | AX18: 0 | AY18: =AX18*E18 -> 0
A19: SOL GRANDE X24 | B19: 72000 | C19: 3000 | D19: 6000 | E19: =D19-C19 -> 3000 | F19: 0 | G19: =F19*E19 -> 0 | H19: 0 | I19: =H19*E19 -> 0 | J19: 0 | K19: =J19*E19 -> 0 | L19: 0 | M19: =L19*E19 -> 0 | N19: 0 | O19: =N19*E19 -> 0 | P19: 0 | Q19: =P19*E19 -> 0 | R19: 0 | S19: =R19*E19 -> 0 | T19: 0 | U19: =T19*E19 -> 0 | V19: 0 | W19: =V19*E19 -> 0 | X19: 0 | Y19: =X19*E19 -> 0 | Z19: 0 | AA19: =Z19*E19 -> 0 | AB19: 0 | AC19: =AB19*E19 -> 0 | AD19: 0 | AE19: =AD19*E19 -> 0 | AF19: 0 | AG19: =AF19*E19 -> 0 | AH19: 0 | AI19: =AH19*E19 -> 0 | AJ19: 0 | AK19: =AJ19*E19 -> 0 | AL19: 0 | AM19: =AL19*E19 -> 0 | AN19: 0 | AO19: =AN19*E19 -> 0 | AP19: 0 | AQ19: =AP19*E19 -> 0 | AR19: 0 | AS19: =AR19*E19 -> 0 | AT19: 0 | AU19: =AT19*E19 -> 0 | AV19: 0 | AW19: =AV19*E19 -> 0 | AX19: 0 | AY19: =AX19*E19 -> 0
A20: ANDINA PEQUEÑA X6 | B20: 7560 | C20: 1260 | D20: 3000 | E20: =D20-C20 -> 1740 | F20: 0 | G20: =F20*E20 -> 0 | H20: 0 | I20: =H20*E20 -> 0 | J20: 0 | K20: =J20*E20 -> 0 | L20: 0 | M20: =L20*E20 -> 0 | N20: 0 | O20: =N20*E20 -> 0 | P20: 0 | Q20: =P20*E20 -> 0 | R20: 0 | S20: =R20*E20 -> 0 | T20: 0 | U20: =T20*E20 -> 0 | V20: 0 | W20: =V20*E20 -> 0 | X20: 0 | Y20: =X20*E20 -> 0 | Z20: 0 | AA20: =Z20*E20 -> 0 | AB20: 0 | AC20: =AB20*E20 -> 0 | AD20: 0 | AE20: =AD20*E20 -> 0 | AF20: 0 | AG20: =AF20*E20 -> 0 | AH20: 0 | AI20: =AH20*E20 -> 0 | AJ20: 0 | AK20: =AJ20*E20 -> 0 | AL20: 0 | AM20: =AL20*E20 -> 0 | AN20: 0 | AO20: =AN20*E20 -> 0 | AP20: 0 | AQ20: =AP20*E20 -> 0 | AR20: 0 | AS20: =AR20*E20 -> 0 | AT20: 0 | AU20: =AT20*E20 -> 0 | AV20: 0 | AW20: =AV20*E20 -> 0 | AX20: 0 | AY20: =AX20*E20 -> 0
A21: ANDINA GRANDE X30 | B21: 54700 | C21: 1823 | D21: 4000 | E21: =D21-C21 -> 2177 | F21: 0 | G21: =F21*E21 -> 0 | H21: 0 | I21: =H21*E21 -> 0 | J21: 0 | K21: =J21*E21 -> 0 | L21: 0 | M21: =L21*E21 -> 0 | N21: 0 | O21: =N21*E21 -> 0 | P21: 0 | Q21: =P21*E21 -> 0 | R21: 0 | S21: =R21*E21 -> 0 | T21: 0 | U21: =T21*E21 -> 0 | V21: 0 | W21: =V21*E21 -> 0 | X21: 0 | Y21: =X21*E21 -> 0 | Z21: 0 | AA21: =Z21*E21 -> 0 | AB21: 1 | AC21: =AB21*E21 -> 2177 | AD21: 0 | AE21: =AD21*E21 -> 0 | AF21: 0 | AG21: =AF21*E21 -> 0 | AH21: 0 | AI21: =AH21*E21 -> 0 | AJ21: 0 | AK21: =AJ21*E21 -> 0 | AL21: 0 | AM21: =AL21*E21 -> 0 | AN21: 0 | AO21: =AN21*E21 -> 0 | AP21: 0 | AQ21: =AP21*E21 -> 0 | AR21: 0 | AS21: =AR21*E21 -> 0 | AT21: 0 | AU21: =AT21*E21 -> 0 | AV21: 0 | AW21: =AV21*E21 -> 0 | AX21: 0 | AY21: =AX21*E21 -> 0
A22: ANDINA DORADA X30 | B22: 56000 | C22: 1866 | D22: 4000 | E22: =D22-C22 -> 2134 | F22: 0 | G22: =F22*E22 -> 0 | H22: 0 | I22: =H22*E22 -> 0 | J22: 0 | K22: =J22*E22 -> 0 | L22: 0 | M22: =L22*E22 -> 0 | N22: 0 | O22: =N22*E22 -> 0 | P22: 0 | Q22: =P22*E22 -> 0 | R22: 0 | S22: =R22*E22 -> 0 | T22: 0 | U22: =T22*E22 -> 0 | V22: 0 | W22: =V22*E22 -> 0 | X22: 0 | Y22: =X22*E22 -> 0 | Z22: 0 | AA22: =Z22*E22 -> 0 | AB22: 0 | AC22: =AB22*E22 -> 0 | AD22: 0 | AE22: =AD22*E22 -> 0 | AF22: 0 | AG22: =AF22*E22 -> 0 | AH22: 0 | AI22: =AH22*E22 -> 0 | AJ22: 0 | AK22: =AJ22*E22 -> 0 | AL22: 0 | AM22: =AL22*E22 -> 0 | AN22: 0 | AO22: =AN22*E22 -> 0 | AP22: 0 | AQ22: =AP22*E22 -> 0 | AR22: 0 | AS22: =AR22*E22 -> 0 | AT22: 0 | AU22: =AT22*E22 -> 0 | AV22: 0 | AW22: =AV22*E22 -> 0 | AX22: 0 | AY22: =AX22*E22 -> 0
A23: HEINEKEN BOTELLA X24 | B23: 55000 | C23: 2291 | D23: 5000 | E23: =D23-C23 -> 2709 | F23: 5 | G23: =F23*E23 -> 13545 | H23: 0 | I23: =H23*E23 -> 0 | J23: 0 | K23: =J23*E23 -> 0 | L23: 0 | M23: =L23*E23 -> 0 | N23: 0 | O23: =N23*E23 -> 0 | P23: 0 | Q23: =P23*E23 -> 0 | R23: 0 | S23: =R23*E23 -> 0 | T23: 0 | U23: =T23*E23 -> 0 | V23: 0 | W23: =V23*E23 -> 0 | X23: 0 | Y23: =X23*E23 -> 0 | Z23: 0 | AA23: =Z23*E23 -> 0 | AB23: 0 | AC23: =AB23*E23 -> 0 | AD23: 0 | AE23: =AD23*E23 -> 0 | AF23: 0 | AG23: =AF23*E23 -> 0 | AH23: 0 | AI23: =AH23*E23 -> 0 | AJ23: 4 | AK23: =AJ23*E23 -> 10836 | AL23: 0 | AM23: =AL23*E23 -> 0 | AN23: 0 | AO23: =AN23*E23 -> 0 | AP23: 0 | AQ23: =AP23*E23 -> 0 | AR23: 0 | AS23: =AR23*E23 -> 0 | AT23: 0 | AU23: =AT23*E23 -> 0 | AV23: 0 | AW23: =AV23*E23 -> 0 | AX23: 0 | AY23: =AX23*E23 -> 0
A24: CORONITA | B24: 60000 | C24: 2500 | D24: 5000 | E24: =D24-C24 -> 2500 | F24: 0 | G24: =F24*E24 -> 0 | H24: 0 | I24: =H24*E24 -> 0 | J24: 19 | K24: =J24*E24 -> 47500 | L24: 14 | M24: =L24*E24 -> 35000 | N24: 10 | O24: =N24*E24 -> 25000 | P24: 0 | Q24: =P24*E24 -> 0 | R24: 0 | S24: =R24*E24 -> 0 | T24: 0 | U24: =T24*E24 -> 0 | V24: 18 | W24: =V24*E24 -> 45000 | X24: 12 | Y24: =X24*E24 -> 30000 | Z24: 10 | AA24: =Z24*E24 -> 25000 | AB24: 10 | AC24: =AB24*E24 -> 25000 | AD24: 16 | AE24: =AD24*E24 -> 40000 | AF24: 0 | AG24: =AF24*E24 -> 0 | AH24: 12 | AI24: =AH24*E24 -> 30000 | AJ24: 0 | AK24: =AJ24*E24 -> 0 | AL24: 103 | AM24: =AL24*E24 -> 257500 | AN24: 0 | AO24: =AN24*E24 -> 0 | AP24: 21 | AQ24: =AP24*E24 -> 52500 | AR24: 0 | AS24: =AR24*E24 -> 0 | AT24: 0 | AU24: =AT24*E24 -> 0 | AV24: 0 | AW24: =AV24*E24 -> 0 | AX24: 11 | AY24: =AX24*E24 -> 27500
A25: AGUILA | B25: 63500 | C25: 2116 | D25: 3400 | E25: =D25-C25 -> 1284 | F25: 14 | G25: =F25*E25 -> 17976 | H25: 58 | I25: =H25*E25 -> 74472 | J25: 56 | K25: =J25*E25 -> 71904 | L25: 24 | M25: =L25*E25 -> 30816 | N25: 67 | O25: =N25*E25 -> 86028 | P25: 22 | Q25: =P25*E25 -> 28248 | R25: 26 | S25: =R25*E25 -> 33384 | T25: 39 | U25: =T25*E25 -> 50076 | V25: 48 | W25: =V25*E25 -> 61632 | X25: 90 | Y25: =X25*E25 -> 115560 | Z25: 55 | AA25: =Z25*E25 -> 70620 | AB25: 19 | AC25: =AB25*E25 -> 24396 | AD25: 18 | AE25: =AD25*E25 -> 23112 | AF25: 26 | AG25: =AF25*E25 -> 33384 | AH25: 93 | AI25: =AH25*E25 -> 119412 | AJ25: 64 | AK25: =AJ25*E25 -> 82176 | AL25: 65 | AM25: =AL25*E25 -> 83460 | AN25: 50 | AO25: =AN25*E25 -> 64200 | AP25: 39 | AQ25: =AP25*E25 -> 50076 | AR25: 38 | AS25: =AR25*E25 -> 48792 | AT25: 47 | AU25: =AT25*E25 -> 60348 | AV25: 1 | AW25: =AV25*E25 -> 1284 | AX25: 15 | AY25: =AX25*E25 -> 19260
A26: LIGTH | B26: 63500 | C26: 2116 | D26: 3400 | E26: =D26-C26 -> 1284 | F26: 18 | G26: =F26*E26 -> 23112 | H26: 47 | I26: =H26*E26 -> 60348 | J26: 14 | K26: =J26*E26 -> 17976 | L26: 55 | M26: =L26*E26 -> 70620 | N26: 27 | O26: =N26*E26 -> 34668 | P26: 45 | Q26: =P26*E26 -> 57780 | R26: 13 | S26: =R26*E26 -> 16692 | T26: 37 | U26: =T26*E26 -> 47508 | V26: 25 | W26: =V26*E26 -> 32100 | X26: 82 | Y26: =X26*E26 -> 105288 | Z26: 61 | AA26: =Z26*E26 -> 78324 | AB26: 5 | AC26: =AB26*E26 -> 6420 | AD26: 4 | AE26: =AD26*E26 -> 5136 | AF26: 14 | AG26: =AF26*E26 -> 17976 | AH26: 22 | AI26: =AH26*E26 -> 28248 | AJ26: 49 | AK26: =AJ26*E26 -> 62916 | AL26: 32 | AM26: =AL26*E26 -> 41088 | AN26: 74 | AO26: =AN26*E26 -> 95016 | AP26: 34 | AQ26: =AP26*E26 -> 43656 | AR26: 15 | AS26: =AR26*E26 -> 19260 | AT26: 10 | AU26: =AT26*E26 -> 12840 | AV26: 1 | AW26: =AV26*E26 -> 1284 | AX26: 59 | AY26: =AX26*E26 -> 75756
A27: POKER | B27: 63500 | C27: 2116 | D27: 3400 | E27: =D27-C27 -> 1284 | F27: 3 | G27: =F27*E27 -> 3852 | H27: 0 | I27: =H27*E27 -> 0 | J27: 1 | K27: =J27*E27 -> 1284 | L27: 7 | M27: =L27*E27 -> 8988 | N27: 8 | O27: =N27*E27 -> 10272 | P27: 35 | Q27: =P27*E27 -> 44940 | R27: 3 | S27: =R27*E27 -> 3852 | T27: 0 | U27: =T27*E27 -> 0 | V27: 2 | W27: =V27*E27 -> 2568 | X27: 31 | Y27: =X27*E27 -> 39804 | Z27: 12 | AA27: =Z27*E27 -> 15408 | AB27: 1 | AC27: =AB27*E27 -> 1284 | AD27: 13 | AE27: =AD27*E27 -> 16692 | AF27: 13 | AG27: =AF27*E27 -> 16692 | AH27: 0 | AI27: =AH27*E27 -> 0 | AJ27: 0 | AK27: =AJ27*E27 -> 0 | AL27: 6 | AM27: =AL27*E27 -> 7704 | AN27: 18 | AO27: =AN27*E27 -> 23112 | AP27: 2 | AQ27: =AP27*E27 -> 2568 | AR27: 5 | AS27: =AR27*E27 -> 6420 | AT27: 6 | AU27: =AT27*E27 -> 7704 | AV27: 2 | AW27: =AV27*E27 -> 2568 | AX27: 10 | AY27: =AX27*E27 -> 12840
A28: COSTEÑA | B28: 52000 | C28: 1733 | D28: 3400 | E28: =D28-C28 -> 1667 | F28: 0 | G28: =F28*E28 -> 0 | H28: 18 | I28: =H28*E28 -> 30006 | J28: 7 | K28: =J28*E28 -> 11669 | L28: 25 | M28: =L28*E28 -> 41675 | N28: 0 | O28: =N28*E28 -> 0 | P28: 0 | Q28: =P28*E28 -> 0 | R28: 4 | S28: =R28*E28 -> 6668 | T28: 21 | U28: =T28*E28 -> 35007 | V28: 15 | W28: =V28*E28 -> 25005 | X28: 12 | Y28: =X28*E28 -> 20004 | Z28: 43 | AA28: =Z28*E28 -> 71681 | AB28: 0 | AC28: =AB28*E28 -> 0 | AD28: 3 | AE28: =AD28*E28 -> 5001 | AF28: 0 | AG28: =AF28*E28 -> 0 | AH28: 1 | AI28: =AH28*E28 -> 1667 | AJ28: 1 | AK28: =AJ28*E28 -> 1667 | AL28: 0 | AM28: =AL28*E28 -> 0 | AN28: 22 | AO28: =AN28*E28 -> 36674 | AP28: 0 | AQ28: =AP28*E28 -> 0 | AR28: 4 | AS28: =AR28*E28 -> 6668 | AT28: 6 | AU28: =AT28*E28 -> 10002 | AV28: 4 | AW28: =AV28*E28 -> 6668 | AX28: 0 | AY28: =AX28*E28 -> 0
... A33: 1 BOTELLA AG. ANTIOQUEÑO AZUL | B33: 43150 | C33: 43150 | D33: 85000 | E33: =D33-C33 -> 41850 | F33: 0 | G33: =F33*E33 -> 0 | H33: 0 | I33: =H33*E33 -> 0 | J33: 0 | K33: =J33*E33 -> 0 | L33: 0 | M33: =L33*E33 -> 0 | N33: 0 | O33: =N33*E33 -> 0 | P33: 0 | Q33: =P33*E33 -> 0 | R33: 0 | S33: =R33*E33 -> 0 | T33: 0 | U33: =T33*E33 -> 0 | V33: 0 | W33: =V33*E33 -> 0 | X33: 0 | Y33: =X33*E33 -> 0 | Z33: 0 | AA33: =Z33*E33 -> 0 | AB33: 0 | AC33: =AB33*E33 -> 0 | AD33: 0 | AE33: =AD33*E33 -> 0 | AF33: 0 | AG33: =AF33*E33 -> 0 | AH33: 0 | AI33: =AH33*E33 -> 0 | AJ33: 0 | AK33: =AJ33*E33 -> 0 | AL33: 0 | AM33: =AL33*E33 -> 0 | AN33: 0 | AO33: =AN33*E33 -> 0 | AP33: 0 | AQ33: =AP33*E33 -> 0 | AR33: 0 | AS33: =AR33*E33 -> 0 | AT33: 0 | AU33: =AT33*E33 -> 0 | AV33: 0 | AW33: =AV33*E33 -> 0 | AX33: 0 | AY33: =AX33*E33 -> 0
A34: SMIRNOFF LULO PEQUEÑA | D34: 50000 | E34: =D34-C34 -> 50000 | F34: 0 | G34: =F34*E34 -> 0 | H34: 0 | I34: =H34*E34 -> 0 | J34: 0 | K34: =J34*E34 -> 0 | L34: 0 | M34: =L34*E34 -> 0 | N34: 0 | O34: =N34*E34 -> 0 | P34: 0 | Q34: =P34*E34 -> 0 | R34: 0 | S34: =R34*E34 -> 0 | T34: 0 | U34: =T34*E34 -> 0 | V34: 0 | W34: =V34*E34 -> 0 | X34: 0 | Y34: =X34*E34 -> 0 | Z34: 0 | AA34: =Z34*E34 -> 0 | AB34: 0 | AC34: =AB34*E34 -> 0 | AD34: 0 | AE34: =AD34*E34 -> 0 | AF34: 0 | AG34: =AF34*E34 -> 0 | AH34: 0 | AI34: =AH34*E34 -> 0 | AJ34: 0 | AK34: =AJ34*E34 -> 0 | AL34: 0 | AM34: =AL34*E34 -> 0 | AN34: 0 | AO34: =AN34*E34 -> 0 | AP34: 0 | AQ34: =AP34*E34 -> 0 | AR34: 0 | AS34: =AR34*E34 -> 0 | AT34: 0 | AU34: =AT34*E34 -> 0 | AV34: 0 | AW34: =AV34*E34 -> 0 | AX34: 0 | AY34: =AX34*E34 -> 0
A35: RON MEDELLIN DORADO GRANDE | D35: 45000 | E35: =D35-C35 -> 45000 | F35: 0 | G35: =F35*E35 -> 0 | H35: 0 | I35: =H35*E35 -> 0 | J35: 0 | K35: =J35*E35 -> 0 | L35: 0 | M35: =L35*E35 -> 0 | N35: 0 | O35: =N35*E35 -> 0 | P35: 0 | Q35: =P35*E35 -> 0 | R35: 0 | S35: =R35*E35 -> 0 | T35: 0 | U35: =T35*E35 -> 0 | V35: 0 | W35: =V35*E35 -> 0 | X35: 0 | Y35: =X35*E35 -> 0 | Z35: 0 | AA35: =Z35*E35 -> 0 | AB35: 0 | AC35: =AB35*E35 -> 0 | AD35: 0 | AE35: =AD35*E35 -> 0 | AF35: 0 | AG35: =AF35*E35 -> 0 | AH35: 0 | AI35: =AH35*E35 -> 0 | AJ35: 0 | AK35: =AJ35*E35 -> 0 | AL35: 0 | AM35: =AL35*E35 -> 0 | AN35: 0 | AO35: =AN35*E35 -> 0 | AP35: 0 | AQ35: =AP35*E35 -> 0 | AR35: 0 | AS35: =AR35*E35 -> 0 | AT35: 0 | AU35: =AT35*E35 -> 0 | AV35: 0 | AW35: =AV35*E35 -> 0 | AX35: 0 | AY35: =AX35*E35 -> 0
A36: RON MEDELLIN DORADO PEQUEÑA | D36: 85000 | E36: =D36-C36 -> 85000 | F36: 0 | G36: =F36*E36 -> 0 | H36: 0 | I36: =H36*E36 -> 0 | J36: 0 | K36: =J36*E36 -> 0 | L36: 0 | M36: =L36*E36 -> 0 | N36: 0 | O36: =N36*E36 -> 0 | P36: 0 | Q36: =P36*E36 -> 0 | R36: 0 | S36: =R36*E36 -> 0 | T36: 0 | U36: =T36*E36 -> 0 | V36: 0 | W36: =V36*E36 -> 0 | X36: 0 | Y36: =X36*E36 -> 0 | Z36: 0 | AA36: =Z36*E36 -> 0 | AB36: 0 | AC36: =AB36*E36 -> 0 | AD36: 0 | AE36: =AD36*E36 -> 0 | AF36: 0 | AG36: =AF36*E36 -> 0 | AH36: 0 | AI36: =AH36*E36 -> 0 | AJ36: 0 | AK36: =AJ36*E36 -> 0 | AL36: 0 | AM36: =AL36*E36 -> 0 | AN36: 0 | AO36: =AN36*E36 -> 0 | AP36: 0 | AQ36: =AP36*E36 -> 0 | AR36: 0 | AS36: =AR36*E36 -> 0 | AT36: 0 | AU36: =AT36*E36 -> 0 | AV36: 0 | AW36: =AV36*E36 -> 0 | AX36: 0 | AY36: =AX36*E36 -> 0
A37: SOMETHING SPECIAL PEQUEÑA | E37: =D37-C37 -> 0 | F37: 0 | G37: =F37*E37 -> 0 | H37: 0 | I37: =H37*E37 -> 0 | J37: 0 | K37: =J37*E37 -> 0 | L37: 0 | M37: =L37*E37 -> 0 | N37: 0 | O37: =N37*E37 -> 0 | P37: 0 | Q37: =P37*E37 -> 0 | R37: 0 | S37: =R37*E37 -> 0 | T37: 0 | U37: =T37*E37 -> 0 | V37: 0 | W37: =V37*E37 -> 0 | X37: 0 | Y37: =X37*E37 -> 0 | Z37: 0 | AA37: =Z37*E37 -> 0 | AB37: 0 | AC37: =AB37*E37 -> 0 | AD37: 0 | AE37: =AD37*E37 -> 0 | AF37: 0 | AG37: =AF37*E37 -> 0 | AH37: 0 | AI37: =AH37*E37 -> 0 | AJ37: 0 | AK37: =AJ37*E37 -> 0 | AL37: 0 | AM37: =AL37*E37 -> 0 | AN37: 0 | AO37: =AN37*E37 -> 0 | AP37: 0 | AQ37: =AP37*E37 -> 0 | AR37: 0 | AS37: =AR37*E37 -> 0 | AT37: 0 | AU37: =AT37*E37 -> 0 | AV37: 0 | AW37: =AV37*E37 -> 0 | AX37: 0 | AY37: =AX37*E37 -> 0
A38: BLACK LABEL | E38: =D38-C38 -> 0 | F38: 0 | G38: =F38*E38 -> 0 | H38: 0 | I38: =H38*E38 -> 0 | J38: 0 | K38: =J38*E38 -> 0 | L38: 0 | M38: =L38*E38 -> 0 | N38: 0 | O38: =N38*E38 -> 0 | P38: 0 | Q38: =P38*E38 -> 0 | R38: 0 | S38: =R38*E38 -> 0 | T38: 0 | U38: =T38*E38 -> 0 | V38: 0 | W38: =V38*E38 -> 0 | X38: 0 | Y38: =X38*E38 -> 0 | Z38: 0 | AA38: =Z38*E38 -> 0 | AB38: 0 | AC38: =AB38*E38 -> 0 | AD38: 0 | AE38: =AD38*E38 -> 0 | AF38: 0 | AG38: =AF38*E38 -> 0 | AH38: 0 | AI38: =AH38*E38 -> 0 | AJ38: 0 | AK38: =AJ38*E38 -> 0 | AL38: 0 | AM38: =AL38*E38 -> 0 | AN38: 0 | AO38: =AN38*E38 -> 0 | AP38: 0 | AQ38: =AP38*E38 -> 0 | AR38: 0 | AS38: =AR38*E38 -> 0 | AT38: 0 | AU38: =AT38*E38 -> 0 | AV38: 0 | AW38: =AV38*E38 -> 0 | AX38: 0 | AY38: =AX38*E38 -> 0
A39: RED LABEL | E39: =D39-C39 -> 0 | F39: 0 | G39: =F39*E39 -> 0 | H39: 0 | I39: =H39*E39 -> 0 | J39: 0 | K39: =J39*E39 -> 0 | L39: 0 | M39: =L39*E39 -> 0 | N39: 0 | O39: =N39*E39 -> 0 | P39: 0 | Q39: =P39*E39 -> 0 | R39: 0 | S39: =R39*E39 -> 0 | T39: 0 | U39: =T39*E39 -> 0 | V39: 0 | W39: =V39*E39 -> 0 | X39: 0 | Y39: =X39*E39 -> 0 | Z39: 0 | AA39: =Z39*E39 -> 0 | AB39: 0 | AC39: =AB39*E39 -> 0 | AD39: 0 | AE39: =AD39*E39 -> 0 | AF39: 0 | AG39: =AF39*E39 -> 0 | AH39: 0 | AI39: =AH39*E39 -> 0 | AJ39: 0 | AK39: =AJ39*E39 -> 0 | AL39: 0 | AM39: =AL39*E39 -> 0 | AN39: 0 | AO39: =AN39*E39 -> 0 | AP39: 0 | AQ39: =AP39*E39 -> 0 | AR39: 0 | AS39: =AR39*E39 -> 0 | AT39: 0 | AU39: =AT39*E39 -> 0 | AV39: 0 | AW39: =AV39*E39 -> 0 | AX39: 0 | AY39: =AX39*E39 -> 0
A40: 1/2 MUSTANG | B40: 5500 | C40: 5500 | D40: 10000 | E40: =D40-C40 -> 4500 | F40: 1 | G40: =F40*E40 -> 4500 | H40: 0 | I40: =H40*E40 -> 0 | J40: 0 | K40: =J40*E40 -> 0 | L40: 0 | M40: =L40*E40 -> 0 | N40: 2 | O40: =N40*E40 -> 9000 | P40: 0 | Q40: =P40*E40 -> 0 | R40: 0 | S40: =R40*E40 -> 0 | T40: 0 | U40: =T40*E40 -> 0 | V40: 0 | W40: =V40*E40 -> 0 | X40: 0 | Y40: =X40*E40 -> 0 | Z40: 0 | AA40: =Z40*E40 -> 0 | AB40: 0 | AC40: =AB40*E40 -> 0 | AD40: 0 | AE40: =AD40*E40 -> 0 | AF40: 0 | AG40: =AF40*E40 -> 0 | AH40: 0 | AI40: =AH40*E40 -> 0 | AJ40: 1 | AK40: =AJ40*E40 -> 4500 | AL40: 1 | AM40: =AL40*E40 -> 4500 | AN40: 3 | AO40: =AN40*E40 -> 13500 | AP40: 0 | AQ40: =AP40*E40 -> 0 | AR40: 0 | AS40: =AR40*E40 -> 0 | AT40: 0 | AU40: =AT40*E40 -> 0 | AV40: 0 | AW40: =AV40*E40 -> 0 | AX40: 0 | AY40: =AX40*E40 -> 0
A41: UND. MUSTANG | B41: 5500 | C41: 550 | D41: 1000 | E41: =D41-C41 -> 450 | F41: 0 | G41: =F41*E41 -> 0 | H41: 0 | I41: =H41*E41 -> 0 | J41: 11 | K41: =J41*E41 -> 4950 | L41: 0 | M41: =L41*E41 -> 0 | N41: 7 | O41: =N41*E41 -> 3150 | P41: 10 | Q41: =P41*E41 -> 4500 | R41: 5 | S41: =R41*E41 -> 2250 | T41: 2 | U41: =T41*E41 -> 900 | V41: 5 | W41: =V41*E41 -> 2250 | X41: 9 | Y41: =X41*E41 -> 4050 | Z41: 0 | AA41: =Z41*E41 -> 0 | AB41: 2 | AC41: =AB41*E41 -> 900 | AD41: 0 | AE41: =AD41*E41 -> 0 | AF41: 0 | AG41: =AF41*E41 -> 0 | AH41: 0 | AI41: =AH41*E41 -> 0 | AJ41: 0 | AK41: =AJ41*E41 -> 0 | AL41: 2 | AM41: =AL41*E41 -> 900 | AN41: 6 | AO41: =AN41*E41 -> 2700 | AP41: 14 | AQ41: =AP41*E41 -> 6300 | AR41: 3 | AS41: =AR41*E41 -> 1350 | AT41: 2 | AU41: =AT41*E41 -> 900 | AV41: 0 | AW41: =AV41*E41 -> 0 | AX41: 6 | AY41: =AX41*E41 -> 2700
A42: 1/2 LUCKY | B42: 6500 | C42: 6500 | D42: 10000 | E42: =D42-C42 -> 3500 | F42: 0 | G42: =F42*E42 -> 0 | H42: 1 | I42: =H42*E42 -> 3500 | J42: 0 | K42: =J42*E42 -> 0 | L42: 4 | M42: =L42*E42 -> 14000 | N42: 0 | O42: =N42*E42 -> 0 | P42: 0 | Q42: =P42*E42 -> 0 | R42: 0 | S42: =R42*E42 -> 0 | T42: 0 | U42: =T42*E42 -> 0 | V42: 1 | W42: =V42*E42 -> 3500 | X42: 0 | Y42: =X42*E42 -> 0 | Z42: 1 | AA42: =Z42*E42 -> 3500 | AB42: 0 | AC42: =AB42*E42 -> 0 | AD42: 0 | AE42: =AD42*E42 -> 0 | AF42: 0 | AG42: =AF42*E42 -> 0 | AH42: 0 | AI42: =AH42*E42 -> 0 | AJ42: 0 | AK42: =AJ42*E42 -> 0 | AL42: 0 | AM42: =AL42*E42 -> 0 | AN42: 0 | AO42: =AN42*E42 -> 0 | AP42: 0 | AQ42: =AP42*E42 -> 0 | AR42: 0 | AS42: =AR42*E42 -> 0 | AT42: 0 | AU42: =AT42*E42 -> 0 | AV42: 0 | AW42: =AV42*E42 -> 0 | AX42: 0 | AY42: =AX42*E42 -> 0
A43: UND. LUCKY | B43: 6500 | C43: 650 | D43: 1000 | E43: =D43-C43 -> 350 | F43: 4 | G43: =F43*E43 -> 1400 | H43: 3 | I43: =H43*E43 -> 1050 | J43: 1 | K43: =J43*E43 -> 350 | L43: 16 | M43: =L43*E43 -> 5600 | N43: 8 | O43: =N43*E43 -> 2800 | P43: 7 | Q43: =P43*E43 -> 2450 | R43: 10 | S43: =R43*E43 -> 3500 | T43: 12 | U43: =T43*E43 -> 4200 | V43: 7 | W43: =V43*E43 -> 2450 | X43: 8 | Y43: =X43*E43 -> 2800 | Z43: 13 | AA43: =Z43*E43 -> 4550 | AB43: 1 | AC43: =AB43*E43 -> 350 | AD43: 12 | AE43: =AD43*E43 -> 4200 | AF43: 10 | AG43: =AF43*E43 -> 3500 | AH43: 9 | AI43: =AH43*E43 -> 3150 | AJ43: 11 | AK43: =AJ43*E43 -> 3850 | AL43: 13 | AM43: =AL43*E43 -> 4550 | AN43: 2 | AO43: =AN43*E43 -> 700 | AP43: 11 | AQ43: =AP43*E43 -> 3850 | AR43: 5 | AS43: =AR43*E43 -> 1750 | AT43: 4 | AU43: =AT43*E43 -> 1400 | AV43: 0 | AW43: =AV43*E43 -> 0 | AX43: 4 | AY43: =AX43*E43 -> 1400
A44: 1/2 MALBORO ROJO | B44: 5500 | C44: 5500 | D44: 10000 | E44: =D44-C44 -> 4500 | F44: 0 | G44: =F44*E44 -> 0 | H44: 0 | I44: =H44*E44 -> 0 | J44: 0 | K44: =J44*E44 -> 0 | L44: 0 | M44: =L44*E44 -> 0 | N44: 0 | O44: =N44*E44 -> 0 | P44: 0 | Q44: =P44*E44 -> 0 | R44: 0 | S44: =R44*E44 -> 0 | T44: 0 | U44: =T44*E44 -> 0 | V44: 0 | W44: =V44*E44 -> 0 | X44: 0 | Y44: =X44*E44 -> 0 | Z44: 0 | AA44: =Z44*E44 -> 0 | AB44: 0 | AC44: =AB44*E44 -> 0 | AD44: 0 | AE44: =AD44*E44 -> 0 | AF44: 0 | AG44: =AF44*E44 -> 0 | AH44: 0 | AI44: =AH44*E44 -> 0 | AJ44: 0 | AK44: =AJ44*E44 -> 0 | AL44: 0 | AM44: =AL44*E44 -> 0 | AN44: 0 | AO44: =AN44*E44 -> 0 | AP44: 0 | AQ44: =AP44*E44 -> 0 | AR44: 0 | AS44: =AR44*E44 -> 0 | AT44: 0 | AU44: =AT44*E44 -> 0 | AV44: 0 | AW44: =AV44*E44 -> 0 | AX44: 0 | AY44: =AX44*E44 -> 0
A45: UND. MALBORO ROJO | B45: 550 | C45: 550 | D45: 1000 | E45: =D45-C45 -> 450 | F45: 1 | G45: =F45*E45 -> 450 | H45: 0 | I45: =H45*E45 -> 0 | J45: 0 | K45: =J45*E45 -> 0 | L45: 8 | M45: =L45*E45 -> 3600 | N45: 0 | O45: =N45*E45 -> 0 | P45: 1 | Q45: =P45*E45 -> 450 | R45: 0 | S45: =R45*E45 -> 0 | T45: 0 | U45: =T45*E45 -> 0 | V45: 0 | W45: =V45*E45 -> 0 | X45: 2 | Y45: =X45*E45 -> 900 | Z45: 2 | AA45: =Z45*E45 -> 900 | AB45: 0 | AC45: =AB45*E45 -> 0 | AD45: 0 | AE45: =AD45*E45 -> 0 | AF45: 0 | AG45: =AF45*E45 -> 0 | AH45: 0 | AI45: =AH45*E45 -> 0 | AJ45: 0 | AK45: =AJ45*E45 -> 0 | AL45: 0 | AM45: =AL45*E45 -> 0 | AN45: 1 | AO45: =AN45*E45 -> 450 | AP45: 0 | AQ45: =AP45*E45 -> 0 | AR45: 0 | AS45: =AR45*E45 -> 0 | AT45: 0 | AU45: =AT45*E45 -> 0 | AV45: 4 | AW45: =AV45*E45 -> 1800 | AX45: 1 | AY45: =AX45*E45 -> 450
A46: 1/2 MALBORO FUSION | B46: 5900 | C46: 5900 | D46: 10000 | E46: =D46-C46 -> 4100 | F46: 0 | G46: =F46*E46 -> 0 | H46: 0 | I46: =H46*E46 -> 0 | J46: 0 | K46: =J46*E46 -> 0 | L46: 0 | M46: =L46*E46 -> 0 | N46: 0 | O46: =N46*E46 -> 0 | P46: 0 | Q46: =P46*E46 -> 0 | R46: 0 | S46: =R46*E46 -> 0 | T46: 0 | U46: =T46*E46 -> 0 | V46: 0 | W46: =V46*E46 -> 0 | X46: 0 | Y46: =X46*E46 -> 0 | Z46: 0 | AA46: =Z46*E46 -> 0 | AB46: 0 | AC46: =AB46*E46 -> 0 | AD46: 0 | AE46: =AD46*E46 -> 0 | AF46: 0 | AG46: =AF46*E46 -> 0 | AH46: 0 | AI46: =AH46*E46 -> 0 | AJ46: 2 | AK46: =AJ46*E46 -> 8200 | AL46: 0 | AM46: =AL46*E46 -> 0 | AN46: 0 | AO46: =AN46*E46 -> 0 | AP46: 0 | AQ46: =AP46*E46 -> 0 | AR46: 0 | AS46: =AR46*E46 -> 0 | AT46: 0 | AU46: =AT46*E46 -> 0 | AV46: 0 | AW46: =AV46*E46 -> 0 | AX46: 0 | AY46: =AX46*E46 -> 0
A47: UND. MALBORO FUSION | B47: 590 | C47: 590 | D47: 1000 | E47: =D47-C47 -> 410 | F47: 2 | G47: =F47*E47 -> 820 | H47: 3 | I47: =H47*E47 -> 1230 | J47: 0 | K47: =J47*E47 -> 0 | L47: 0 | M47: =L47*E47 -> 0 | N47: 0 | O47: =N47*E47 -> 0 | P47: 0 | Q47: =P47*E47 -> 0 | R47: 0 | S47: =R47*E47 -> 0 | T47: 13 | U47: =T47*E47 -> 5330 | V47: 0 | W47: =V47*E47 -> 0 | X47: 9 | Y47: =X47*E47 -> 3690 | Z47: 0 | AA47: =Z47*E47 -> 0 | AB47: 2 | AC47: =AB47*E47 -> 820 | AD47: 0 | AE47: =AD47*E47 -> 0 | AF47: 0 | AG47: =AF47*E47 -> 0 | AH47: 0 | AI47: =AH47*E47 -> 0 | AJ47: 10 | AK47: =AJ47*E47 -> 4100 | AL47: 3 | AM47: =AL47*E47 -> 1230 | AN47: 7 | AO47: =AN47*E47 -> 2870 | AP47: 0 | AQ47: =AP47*E47 -> 0 | AR47: 0 | AS47: =AR47*E47 -> 0 | AT47: 0 | AU47: =AT47*E47 -> 0 | AV47: 0 | AW47: =AV47*E47 -> 0 | AX47: 0 | AY47: =AX47*E47 -> 0
A48: D.P LIMON | B48: 1956 | C48: 1956 | D48: 4000 | E48: =D48-C48 -> 2044 | F48: 0 | G48: =F48*E48 -> 0 | H48: 0 | I48: =H48*E48 -> 0 | J48: 0 | K48: =J48*E48 -> 0 | L48: 0 | M48: =L48*E48 -> 0 | N48: 0 | O48: =N48*E48 -> 0 | P48: 0 | Q48: =P48*E48 -> 0 | R48: 0 | S48: =R48*E48 -> 0 | T48: 0 | U48: =T48*E48 -> 0 | V48: 0 | W48: =V48*E48 -> 0 | X48: 0 | Y48: =X48*E48 -> 0 | Z48: 0 | AA48: =Z48*E48 -> 0 | AB48: 0 | AC48: =AB48*E48 -> 0 | AD48: 0 | AE48: =AD48*E48 -> 0 | AF48: 0 | AG48: =AF48*E48 -> 0 | AH48: 0 | AI48: =AH48*E48 -> 0 | AJ48: 0 | AK48: =AJ48*E48 -> 0 | AL48: 0 | AM48: =AL48*E48 -> 0 | AN48: 0 | AO48: =AN48*E48 -> 0 | AP48: 0 | AQ48: =AP48*E48 -> 0 | AR48: 0 | AS48: =AR48*E48 -> 0 | AT48: 0 | AU48: =AT48*E48 -> 0 | AV48: 0 | AW48: =AV48*E48 -> 0 | AX48: 0 | AY48: =AX48*E48 -> 0
A49: D.P BBQ | B49: 1956 | C49: 1956 | D49: 4000 | E49: =D49-C49 -> 2044 | F49: 0 | G49: =F49*E49 -> 0 | H49: 0 | I49: =H49*E49 -> 0 | J49: 0 | K49: =J49*E49 -> 0 | L49: 0 | M49: =L49*E49 -> 0 | N49: 0 | O49: =N49*E49 -> 0 | P49: 0 | Q49: =P49*E49 -> 0 | R49: 0 | S49: =R49*E49 -> 0 | T49: 3 | U49: =T49*E49 -> 6132 | V49: 0 | W49: =V49*E49 -> 0 | X49: 2 | Y49: =X49*E49 -> 4088 | Z49: 0 | AA49: =Z49*E49 -> 0 | AB49: 1 | AC49: =AB49*E49 -> 2044 | AD49: 0 | AE49: =AD49*E49 -> 0 | AF49: 1 | AG49: =AF49*E49 -> 2044 | AH49: 2 | AI49: =AH49*E49 -> 4088 | AJ49: 0 | AK49: =AJ49*E49 -> 0 | AL49: 1 | AM49: =AL49*E49 -> 2044 | AN49: 4 | AO49: =AN49*E49 -> 8176 | AP49: 0 | AQ49: =AP49*E49 -> 0 | AR49: 0 | AS49: =AR49*E49 -> 0 | AT49: 0 | AU49: =AT49*E49 -> 0 | AV49: 0 | AW49: =AV49*E49 -> 0 | AX49: 0 | AY49: =AX49*E49 -> 0
A50: D.P NATURAL | B50: 1956 | C50: 1956 | D50: 4000 | E50: =D50-C50 -> 2044 | F50: 0 | G50: =F50*E50 -> 0 | H50: 1 | I50: =H50*E50 -> 2044 | J50: 0 | K50: =J50*E50 -> 0 | L50: 0 | M50: =L50*E50 -> 0 | N50: 1 | O50: =N50*E50 -> 2044 | P50: 0 | Q50: =P50*E50 -> 0 | R50: 0 | S50: =R50*E50 -> 0 | T50: 0 | U50: =T50*E50 -> 0 | V50: 0 | W50: =V50*E50 -> 0 | X50: 2 | Y50: =X50*E50 -> 4088 | Z50: 3 | AA50: =Z50*E50 -> 6132 | AB50: 0 | AC50: =AB50*E50 -> 0 | AD50: 0 | AE50: =AD50*E50 -> 0 | AF50: 0 | AG50: =AF50*E50 -> 0 | AH50: 2 | AI50: =AH50*E50 -> 4088 | AJ50: 0 | AK50: =AJ50*E50 -> 0 | AL50: 0 | AM50: =AL50*E50 -> 0 | AN50: 0 | AO50: =AN50*E50 -> 0 | AP50: 0 | AQ50: =AP50*E50 -> 0 | AR50: 0 | AS50: =AR50*E50 -> 0 | AT50: 0 | AU50: =AT50*E50 -> 0 | AV50: 0 | AW50: =AV50*E50 -> 0 | AX50: 0 | AY50: =AX50*E50 -> 0
A51: D.P MIX | B51: 1956 | C51: 1956 | D51: 4000 | E51: =D51-C51 -> 2044 | F51: 1 | G51: =F51*E51 -> 2044 | H51: 0 | I51: =H51*E51 -> 0 | J51: 0 | K51: =J51*E51 -> 0 | L51: 0 | M51: =L51*E51 -> 0 | N51: 0 | O51: =N51*E51 -> 0 | P51: 0 | Q51: =P51*E51 -> 0 | R51: 0 | S51: =R51*E51 -> 0 | T51: 0 | U51: =T51*E51 -> 0 | V51: 0 | W51: =V51*E51 -> 0 | X51: 6 | Y51: =X51*E51 -> 12264 | Z51: 0 | AA51: =Z51*E51 -> 0 | AB51: 0 | AC51: =AB51*E51 -> 0 | AD51: 0 | AE51: =AD51*E51 -> 0 | AF51: 0 | AG51: =AF51*E51 -> 0 | AH51: 4 | AI51: =AH51*E51 -> 8176 | AJ51: 0 | AK51: =AJ51*E51 -> 0 | AL51: 1 | AM51: =AL51*E51 -> 2044 | AN51: 0 | AO51: =AN51*E51 -> 0 | AP51: 1 | AQ51: =AP51*E51 -> 2044 | AR51: 1 | AS51: =AR51*E51 -> 2044 | AT51: 0 | AU51: =AT51*E51 -> 0 | AV51: 0 | AW51: =AV51*E51 -> 0 | AX51: 3 | AY51: =AX51*E51 -> 6132
A52: TRIDENT | B52: 825 | C52: 825 | D52: 2500 | E52: =D52-C52 -> 1675 | F52: 0 | G52: 0 | H52: 1 | I52: =H52*E52 -> 1675 | J52: 0 | K52: =J52*E52 -> 0 | L52: 1 | M52: =L52*E52 -> 1675 | N52: 0 | O52: =N52*E52 -> 0 | P52: 0 | Q52: =P52*E52 -> 0 | R52: 0 | S52: =R52*E52 -> 0 | T52: 0 | U52: =T52*E52 -> 0 | V52: 0 | W52: =V52*E52 -> 0 | X52: 0 | Y52: =X52*E52 -> 0 | Z52: 0 | AA52: =Z52*E52 -> 0 | AB52: 0 | AC52: =AB52*E52 -> 0 | AD52: 0 | AE52: =AD52*E52 -> 0 | AF52: 0 | AG52: =AF52*E52 -> 0 | AH52: 0 | AI52: =AH52*E52 -> 0 | AJ52: 0 | AK52: =AJ52*E52 -> 0 | AL52: 0 | AM52: =AL52*E52 -> 0 | AN52: 0 | AO52: =AN52*E52 -> 0 | AP52: 0 | AQ52: =AP52*E52 -> 0 | AR52: 0 | AS52: =AR52*E52 -> 0 | AT52: 0 | AU52: =AT52*E52 -> 0 | AV52: 0 | AW52: =AV52*E52 -> 0 | AX52: 0 | AY52: =AX52*E52 -> 0
A53: CHICLETS XTIME | B53: 103 | C53: 103 | D53: 200 | E53: =D53-C53 -> 97 | F53: 0 | G53: 0 | H53: 0 | I53: =H53*E53 -> 0 | J53: 0 | K53: =J53*E53 -> 0 | L53: 23 | M53: =L53*E53 -> 2231 | N53: 1 | O53: =N53*E53 -> 97 | P53: 1 | Q53: =P53*E53 -> 97 | R53: 0 | S53: =R53*E53 -> 0 | T53: 0 | U53: =T53*E53 -> 0 | V53: 0 | W53: =V53*E53 -> 0 | X53: 0 | Y53: =X53*E53 -> 0 | Z53: 0 | AA53: =Z53*E53 -> 0 | AB53: 0 | AC53: =AB53*E53 -> 0 | AD53: 0 | AE53: =AD53*E53 -> 0 | AF53: 0 | AG53: =AF53*E53 -> 0 | AH53: 0 | AI53: =AH53*E53 -> 0 | AJ53: 0 | AK53: =AJ53*E53 -> 0 | AL53: 0 | AM53: =AL53*E53 -> 0 | AN53: 0 | AO53: =AN53*E53 -> 0 | AP53: 0 | AQ53: =AP53*E53 -> 0 | AR53: 0 | AS53: =AR53*E53 -> 0 | AT53: 0 | AU53: =AT53*E53 -> 0 | AV53: 0 | AW53: =AV53*E53 -> 0 | AX53: 0 | AY53: =AX53*E53 -> 0
A54: BOMBOMBUM | B54: 352 | C54: 352 | D54: 700 | E54: =D54-C54 -> 348 | F54: 0 | G54: 0 | H54: 0 | I54: =H54*E54 -> 0 | J54: 1 | K54: =J54*E54 -> 348 | L54: 10 | M54: =L54*E54 -> 3480 | N54: 0 | O54: =N54*E54 -> 0 | P54: 0 | Q54: =P54*E54 -> 0 | R54: 0 | S54: =R54*E54 -> 0 | T54: 0 | U54: =T54*E54 -> 0 | V54: 0 | W54: =V54*E54 -> 0 | X54: 0 | Y54: =X54*E54 -> 0 | Z54: 0 | AA54: =Z54*E54 -> 0 | AB54: 0 | AC54: =AB54*E54 -> 0 | AD54: 0 | AE54: =AD54*E54 -> 0 | AF54: 0 | AG54: =AF54*E54 -> 0 | AH54: 0 | AI54: =AH54*E54 -> 0 | AJ54: 0 | AK54: =AJ54*E54 -> 0 | AL54: 0 | AM54: =AL54*E54 -> 0 | AN54: 0 | AO54: =AN54*E54 -> 0 | AP54: 0 | AQ54: =AP54*E54 -> 0 | AR54: 0 | AS54: =AR54*E54 -> 0 | AT54: 0 | AU54: =AT54*E54 -> 0 | AV54: 0 | AW54: =AV54*E54 -> 0 | AX54: 0 | AY54: =AX54*E54 -> 0
A55: BOTELLA AGT. AMARILLO | B55: 60000 | C55: 60000 | D55: 100000 | E55: =D55-C55 -> 40000 | F55: 0 | G55: 0 | H55: 0 | I55: =H55*E55 -> 0 | J55: 0 | K55: =J55*E55 -> 0 | L55: 1 | M55: =L55*E55 -> 40000 | N55: 0 | O55: =N55*E55 -> 0 | P55: 1 | Q55: =P55*E55 -> 40000 | R55: 0 | S55: =R55*E55 -> 0 | T55: 0 | U55: =T55*E55 -> 0 | V55: 1 | W55: =V55*E55 -> 40000 | X55: 0 | Y55: =X55*E55 -> 0 | Z55: 0 | AA55: =Z55*E55 -> 0 | AB55: 0 | AC55: =AB55*E55 -> 0 | AD55: 0 | AE55: =AD55*E55 -> 0 | AF55: 0 | AG55: =AF55*E55 -> 0 | AH55: 0 | AI55: =AH55*E55 -> 0 | AJ55: 0 | AK55: =AJ55*E55 -> 0 | AL55: 0 | AM55: =AL55*E55 -> 0 | AN55: 0 | AO55: =AN55*E55 -> 0 | AP55: 0 | AQ55: =AP55*E55 -> 0 | AR55: 0 | AS55: =AR55*E55 -> 0 | AT55: 0 | AU55: =AT55*E55 -> 0 | AV55: 0 | AW55: =AV55*E55 -> 0 | AX55: 0 | AY55: =AX55*E55 -> 0
G56: =SUM(G2:G51) -> 79366 | I56: =SUM(I3:I55) -> 203342 | K56: =SUM(K3:K55) -> 187281 | M56: =SUM(M2:M55) -> 573502 | O56: =SUM(O2:O55) -> 839727 | Q56: =SUM(Q2:Q55) -> 188215 | S56: =SUM(S2:S55) -> 70055 | U56: =SUM(U2:U55) -> 152070 | W56: =SUM(W2:W55) -> 237305 | Y56: =SUM(Y2:Y55) -> 351378 | AA56: =SUM(AA2:AA55) -> 334515 | AC56: =SUM(AC2:AC55) -> 110725 | AE56: =SUM(AE2:AE55) -> 293166 | AG56: =SUM(AG2:AG55) -> 73596 | AI56: =SUM(AI2:AI55) -> 241279 | AK56: =SUM(AK2:AK55) -> 183262 | AM56: =SUM(AM2:AM55) -> 478587 | AO56: =SUM(AO2:AO55) -> 285965 | AQ56: =SUM(AQ2:AQ55) -> 178453 | AS56: =SUM(AS2:AS55) -> 94018 | AU56: =SUM(AU2:AU55) -> 110569 | AW56: =SUM(AW2:AW55) -> 15479 | AY56: =SUM(AY2:AY55) -> 172730

Sheet PRECIOS
A1: PRODUCTO | B1: VR VENTA
A2: AGUA X24 | B2: 3000
A3: COCA COLA | B3: 3500
A4: GATORADE | B4: 5000
A5: SMIRNOFF | B5: 12000
A6: GASEOSA CUATRO | B6: 3000
A7: GASEOSA CANADA DRY | B7: 3000
A8: GASEOSA SHWEPPES | B8: 3000
A9: BRETAÑA | B9: 4000
A10: SPEED MAX | B10: 3500
A11: REDBULL | B11: 10000
A12: ELECTROLIT | B12: 10000
A13: POKER LATA | B13: 5000
... A36: RON MEDELLIN DORADO PEQUEÑA | B36: 85000
A37: SOMETHING SPECIAL PEQUEÑA
A38: BLACK LABEL
A39: RED LABEL
A40: 1/2 MUSTANG | B40: 10000
A41: UND. MUSTANG | B41: 1000
A42: 1/2 LUCKY | B42: 10000
A43: UND. LUCKY | B43: 1000
A44: 1/2 MALBORO ROJO | B44: 10000
A45: UND. MALBORO ROJO | B45: 1000
A46: 1/2 MALBORO FUSION | B46: 10000
A47: UND. MALBORO FUSION | B47: 1000
A48: D.P LIMON | B48: 4000
A49: D.P BBQ | B49: 4000
A50: D.P NATURAL | B50: 4000
A51: D.P MIX | B51: 4000
... A55: BOTELLA AGT. AMARILLO | B55: 100000

Sheet GANAN. FEB
A1: PRODUCTO | B1: PRECIO | C1: VR UNIDAD | D1: VR VENTA | E1: VR GANANCIA | F1: 01/02/25 VENTA | G1: 01/02/25 GANANCIA | H1: 02/02/25 VENTA | I1: 02/02/25 GANANCIA | J1: 03/02/25 VENTA | K1: 03/02/25 GANANCIA | L1: 04/02/25 VENTA | M1: 04/02/25 GANANCIA | N1: 06/02/25 VENTA | O1: 06/02/25 GANANCIA | P1: 07/02/25 VENTA | Q1: 07/02/25 GANANCIA | R1: 08/02/25 VENTA | S1: 08/02/25 GANANCIA | T1: 09/02/25 VENTA | U1: 09/02/25 GANANCIA | V1: 10/02/25 VENTA | W1: 10/02/25 GANANCIA | X1: 11/02/25 VENTA | Y1: 11/02/25 GANANCIA | Z1: 12/02/25 VENTA | AA1: 12/02/25 GANANCIA | AB1: 13/02/25 VENTA | AC1: 13/02/25 GANANCIA | AD1: 14/02/25 VENTA | AE1: 14/02/25 GANANCIA | AF1: 15/02/25 VENTA | AG1: 15/02/25 GANANCIA | AH1: 16/02/25 VENTA | AI1: 16/02/25 GANANCIA | AJ1: 18/02/25 VENTA | AK1: 18/02/25 GANANCIA | AL1: 19/02/25 VENTA | AM1: 19/02/25 GANANCIA | AN1: 20/02/25 VENTA | AO1: 20/02/25 GANANCIA | AP1: 21/02/25 VENTA | AQ1: 21/02/25 GANANCIA | AR1: 22/02/25 VENTA | AS1: 22/02/25 GANANCIA | AT1: 23/02/25 VENTA | AU1: 23/02/25 GANANCIA | AV1: 24/02/25 VENTA | AW1: 24/02/25 GANANCIA | AX1: 25/02/25 VENTA | AY1: 25/02/25 GANANCIA | AZ1: 26/02/25 VENTA | BA1: 26/02/25 GANANCIA | BB1: 27/02/25 VENTA | BC1: 27/02/25 GANANCIA | BD1: 28/02/25 VENTA | BE1: 28/02/25 GANANCIA
A2: AGUA X24 | B2: 24000 | C2: 1000 | D2: 3000 | E2: =D2-C2 -> 2000 | F2: 3 | G2: =F2*E2 -> 6000 | H2: 1 | I2: =H2*E2 -> 2000 | J2: 0 | K2: =J2*E2 -> 0 | L2: 1 | M2: =L2*E2 -> 2000 | N2: 5 | O2: =N2*E2 -> 10000 | P2: 0 | Q2: =P2*E2 -> 0 | R2: 5 | S2: =R2*E2 -> 10000 | T2: 0 | U2: =T2*E2 -> 0 | V2: 0 | W2: =V2*E2 -> 0 | X2: 0 | Y2: =X2*E2 -> 0 | Z2: 0 | AA2: =Z2*E2 -> 0 | AB2: 0 | AC2: =AB2*E2 -> 0 | AD2: 1 | AE2: =AD2*E2 -> 2000 | AF2: 5 | AG2: =AF2*E2 -> 10000 | AH2: 0 | AI2: =AH2*E2 -> 0 | AJ2: 0 | AK2: =AJ2*E2 -> 0 | AL2: 1 | AM2: =AL2*E2 -> 2000 | AN2: 2 | AO2: =AN2*E2 -> 4000 | AP2: 1 | AQ2: =AP2*E2 -> 2000 | AR2: 0 | AS2: =AR2*E2 -> 0 | AT2: 0 | AU2: =AT2*E2 -> 0 | AV2: 0 | AW2: =AV2*E2 -> 0 | AX2: 1 | AY2: =AX2*E2 -> 2000 | AZ2: 0 | BA2: =AZ2*E2 -> 0 | BB2: 6 | BC2: =BB2*E2 -> 12000 | BD2: 1 | BE2: =BD2*E2 -> 2000
A3: COCA COLA | B3: 30000 | C3: 2500 | D3: 3500 | E3: =D3-C3 -> 1000 | F3: 0 | G3: =F3*E3 -> 0 | H3: 2 | I3: =H3*E3 -> 2000 | J3: 1 | K3: =J3*E3 -> 1000 | L3: 0 | M3: =L3*E3 -> 0 | N3: 1 | O3: =N3*E3 -> 1000 | P3: 1 | Q3: =P3*E3 -> 1000 | R3: 1 | S3: =R3*E3 -> 1000 | T3: 0 | U3: =T3*E3 -> 0 | V3: 0 | W3: =V3*E3 -> 0 | X3: 0 | Y3: =X3*E3 -> 0 | Z3: 0 | AA3: =Z3*E3 -> 0 | AB3: 0 | AC3: =AB3*E3 -> 0 | AD3: 2 | AE3: =AD3*E3 -> 2000 | AF3: 0 | AG3: =AF3*E3 -> 0 | AH3: 2 | AI3: =AH3*E3 -> 2000 | AJ3: 0 | AK3: =AJ3*E3 -> 0 | AL3: 2 | AM3: =AL3*E3 -> 2000 | AN3: 2 | AO3: =AN3*E3 -> 2000 | AP3: 1 | AQ3: =AP3*E3 -> 1000 | AR3: 0 | AS3: =AR3*E3 -> 0 | AT3: 2 | AU3: =AT3*E3 -> 2000 | AV3: 0 | AW3: =AV3*E3 -> 0 | AX3: 0 | AY3: =AX3*E3 -> 0 | AZ3: 1 | BA3: =AZ3*E3 -> 1000 | BB3: 1 | BC3: =BB3*E3 -> 1000 | BD3: 1 | BE3: =BD3*E3 -> 1000
A4: GATORADE | B4: 37000 | C4: 3083 | D4: 5000 | E4: =D4-C4 -> 1917 | F4: 0 | G4: =F4*E4 -> 0 | H4: 2 | I4: =H4*E4 -> 3834 | J4: 0 | K4: =J4*E4 -> 0 | L4: 2 | M4: =L4*E4 -> 3834 | N4: 6 | O4: =N4*E4 -> 11502 | P4: 0 | Q4: =P4*E4 -> 0 | R4: 0 | S4: =R4*E4 -> 0 | T4: 0 | U4: =T4*E4 -> 0 | V4: 0 | W4: =V4*E4 -> 0 | X4: 1 | Y4: =X4*E4 -> 1917 | Z4: 0 | AA4: =Z4*E4 -> 0 | AB4: 0 | AC4: =AB4*E4 -> 0 | AD4: 1 | AE4: =AD4*E4 -> 1917 | AF4: 1 | AG4: =AF4*E4 -> 1917 | AH4: 2 | AI4: =AH4*E4 -> 3834 | AJ4: 0 | AK4: =AJ4*E4 -> 0 | AL4: 0 | AM4: =AL4*E4 -> 0 | AN4: 0 | AO4: =AN4*E4 -> 0 | AP4: 1 | AQ4: =AP4*E4 -> 1917 | AR4: 1 | AS4: =AR4*E4 -> 1917 | AT4: 0 | AU4: =AT4*E4 -> 0 | AV4: 0 | AW4: =AV4*E4 -> 0 | AX4: 0 | AY4: =AX4*E4 -> 0 | AZ4: 0 | BA4: =AZ4*E4 -> 0 | BB4: 2 | BC4: =BB4*E4 -> 3834 | BD4: 1 | BE4: =BD4*E4 -> 1917
A5: SMIRNOFF | B5: 8000 | C5: 8000 | D5: 12000 | E5: =D5-C5 -> 4000 | F5: 3 | G5: =F5*E5 -> 12000 | H5: 0 | I5: =H5*E5 -> 0 | J5: 0 | K5: =J5*E5 -> 0 | L5: 0 | M5: =L5*E5 -> 0 | N5: 0 | O5: =N5*E5 -> 0 | P5: 0 | Q5: =P5*E5 -> 0 | R5: 0 | S5: =R5*E5 -> 0 | T5: 0 | U5: =T5*E5 -> 0 | V5: 0 | W5: =V5*E5 -> 0 | X5: 0 | Y5: =X5*E5 -> 0 | Z5: 0 | AA5: =Z5*E5 -> 0 | AB5: 0 | AC5: =AB5*E5 -> 0 | AD5: 0 | AE5: =AD5*E5 -> 0 | AF5: 1 | AG5: =AF5*E5 -> 4000 | AH5: 0 | AI5: =AH5*E5 -> 0 | AJ5: 0 | AK5: =AJ5*E5 -> 0 | AL5: 0 | AM5: =AL5*E5 -> 0 | AN5: 0 | AO5: =AN5*E5 -> 0 | AP5: 0 | AQ5: =AP5*E5 -> 0 | AR5: 0 | AS5: =AR5*E5 -> 0 | AT5: 0 | AU5: =AT5*E5 -> 0 | AV5: 0 | AW5: =AV5*E5 -> 0 | AX5: 0 | AY5: =AX5*E5 -> 0 | AZ5: 0 | BA5: =AZ5*E5 -> 0 | BB5: 0 | BC5: =BB5*E5 -> 0 | BD5: 0 | BE5: =BD5*E5 -> 0
A6: GASEOSA CUATRO | B6: 2000 | C6: 2000 | D6: 3000 | E6: =D6-C6 -> 1000 | F6: 0 | G6: =F6*E6 -> 0 | H6: 1 | I6: =H6*E6 -> 1000 | J6: 0 | K6: =J6*E6 -> 0 | L6: 0 | M6: =L6*E6 -> 0 | N6: 0 | O6: =N6*E6 -> 0 | P6: 0 | Q6: =P6*E6 -> 0 | R6: 0 | S6: =R6*E6 -> 0 | T6: 0 | U6: =T6*E6 -> 0 | V6: 0 | W6: =V6*E6 -> 0 | X6: 0 | Y6: =X6*E6 -> 0 | Z6: 0 | AA6: =Z6*E6 -> 0 | AB6: 0 | AC6: =AB6*E6 -> 0 | AD6: 0 | AE6: =AD6*E6 -> 0 | AF6: 0 | AG6: =AF6*E6 -> 0 | AH6: 0 | AI6: =AH6*E6 -> 0 | AJ6: 0 | AK6: =AJ6*E6 -> 0 | AL6: 0 | AM6: =AL6*E6 -> 0 | AN6: 0 | AO6: =AN6*E6 -> 0 | AP6: 0 | AQ6: =AP6*E6 -> 0 | AR6: 0 | AS6: =AR6*E6 -> 0 | AT6: 0 | AU6: =AT6*E6 -> 0 | AV6: 0 | AW6: =AV6*E6 -> 0 | AX6: 0 | AY6: =AX6*E6 -> 0 | AZ6: 0 | BA6: =AZ6*E6 -> 0 | BB6: 0 | BC6: =BB6*E6 -> 0 | BD6: 3 | BE6: =BD6*E6 -> 3000
A7: GASEOSA CANADA DRY | B7: 2000 | C7: 2000 | D7: 3000 | E7: =D7-C7 -> 1000 | F7: 0 | G7: =F7*E7 -> 0 | H7: 0 | I7: =H7*E7 -> 0 | J7: 0 | K7: =J7*E7 -> 0 | L7: 0 | M7: =L7*E7 -> 0 | N7: 0 | O7: =N7*E7 -> 0 | P7: 0 | Q7: =P7*E7 -> 0 | R7: 0 | S7: =R7*E7 -> 0 | T7: 0 | U7: =T7*E7 -> 0 | V7: 0 | W7: =V7*E7 -> 0 | X7: 0 | Y7: =X7*E7 -> 0 | Z7: 0 | AA7: =Z7*E7 -> 0 | AB7: 0 | AC7: =AB7*E7 -> 0 | AD7: 0 | AE7: =AD7*E7 -> 0 | AF7: 0 | AG7: =AF7*E7 -> 0 | AH7: 0 | AI7: =AH7*E7 -> 0 | AJ7: 0 | AK7: =AJ7*E7 -> 0 | AL7: 0 | AM7: =AL7*E7 -> 0 | AN7: 0 | AO7: =AN7*E7 -> 0 | AP7: 0 | AQ7: =AP7*E7 -> 0 | AR7: 0 | AS7: =AR7*E7 -> 0 | AT7: 0 | AU7: =AT7*E7 -> 0 | AV7: 0 | AW7: =AV7*E7 -> 0 | AX7: 0 | AY7: =AX7*E7 -> 0 | AZ7: 0 | BA7: =AZ7*E7 -> 0 | BB7: 1 | BC7: =BB7*E7 -> 1000 | BD7: 0 | BE7: =BD7*E7 -> 0
A8: GASEOSA SHWEPPES | B8: 2000 | C8: 2000 | D8: 3000 | E8: =D8-C8 -> 1000 | F8: 0 | G8: =F8*E8 -> 0 | H8: 0 | I8: =H8*E8 -> 0 | J8: 0 | K8: =J8*E8 -> 0 | L8: 0 | M8: =L8*E8 -> 0 | N8: 0 | O8: =N8*E8 -> 0 | P8: 0 | Q8: =P8*E8 -> 0 | R8: 0 | S8: =R8*E8 -> 0 | T8: 0 | U8: =T8*E8 -> 0 | V8: 0 | W8: =V8*E8 -> 0 | X8: 0 | Y8: =X8*E8 -> 0 | Z8: 0 | AA8: =Z8*E8 -> 0 | AB8: 0 | AC8: =AB8*E8 -> 0 | AD8: 0 | AE8: =AD8*E8 -> 0 | AF8: 0 | AG8: =AF8*E8 -> 0 | AH8: 0 | AI8: =AH8*E8 -> 0 | AJ8: 0 | AK8: =AJ8*E8 -> 0 | AL8: 0 | AM8: =AL8*E8 -> 0 | AN8: 0 | AO8: =AN8*E8 -> 0 | AP8: 0 | AQ8: =AP8*E8 -> 0 | AR8: 0 | AS8: =AR8*E8 -> 0 | AT8: 0 | AU8: =AT8*E8 -> 0 | AV8: 0 | AW8: =AV8*E8 -> 0 | AX8: 0 | AY8: =AX8*E8 -> 0 | AZ8: 0 | BA8: =AZ8*E8 -> 0 | BB8: 0 | BC8: =BB8*E8 -> 0 | BD8: 0 | BE8: =BD8*E8 -> 0
A9: BRETAÑA | B9: 46800 | C9: 1950 | D9: 4000 | E9: =D9-C9 -> 2050 | F9: 0 | G9: =F9*E9 -> 0 | H9: 0 | I9: =H9*E9 -> 0 | J9: 0 | K9: =J9*E9 -> 0 | L9: 0 | M9: =L9*E9 -> 0 | N9: 0 | O9: =N9*E9 -> 0 | P9: 0 | Q9: =P9*E9 -> 0 | R9: 0 | S9: =R9*E9 -> 0 | T9: 0 | U9: =T9*E9 -> 0 | V9: 0 | W9: =V9*E9 -> 0 | X9: 0 | Y9: =X9*E9 -> 0 | Z9: 0 | AA9: =Z9*E9 -> 0 | AB9: 0 | AC9: =AB9*E9 -> 0 | AD9: 0 | AE9: =AD9*E9 -> 0 | AF9: 0 | AG9: =AF9*E9 -> 0 | AH9: 0 | AI9: =AH9*E9 -> 0 | AJ9: 0 | AK9: =AJ9*E9 -> 0 | AL9: 0 | AM9: =AL9*E9 -> 0 | AN9: 0 | AO9: =AN9*E9 -> 0 | AP9: 1 | AQ9: =AP9*E9 -> 2050 | AR9: 0 | AS9: =AR9*E9 -> 0 | AT9: 0 | AU9: =AT9*E9 -> 0 | AV9: 0 | AW9: =AV9*E9 -> 0 | AX9: 0 | AY9: =AX9*E9 -> 0 | AZ9: 0 | BA9: =AZ9*E9 -> 0 | BB9: 0 | BC9: =BB9*E9 -> 0 | BD9: 0 | BE9: =BD9*E9 -> 0
A10: SPEED MAX | B10: 2500 | C10: 2500 | D10: 3500 | E10: =D10-C10 -> 1000 | F10: 0 | G10: =F10*E10 -> 0 | H10: 0 | I10: =H10*E10 -> 0 | J10: 0 | K10: =J10*E10 -> 0 | L10: 0 | M10: =L10*E10 -> 0 | N10: 0 | O10: =N10*E10 -> 0 | P10: 0 | Q10: =P10*E10 -> 0 | R10: 0 | S10: =R10*E10 -> 0 | T10: 0 | U10: =T10*E10 -> 0 | V10: 0 | W10: =V10*E10 -> 0 | X10: 0 | Y10: =X10*E10 -> 0 | Z10: 0 | AA10: =Z10*E10 -> 0 | AB10: 0 | AC10: =AB10*E10 -> 0 | AD10: 0 | AE10: =AD10*E10 -> 0 | AF10: 0 | AG10: =AF10*E10 -> 0 | AH10: 2 | AI10: =AH10*E10 -> 2000 | AJ10: 0 | AK10: =AJ10*E10 -> 0 | AL10: 0 | AM10: =AL10*E10 -> 0 | AN10: 0 | AO10: =AN10*E10 -> 0 | AP10: 0 | AQ10: =AP10*E10 -> 0 | AR10: 0 | AS10: =AR10*E10 -> 0 | AT10: 0 | AU10: =AT10*E10 -> 0 | AV10: 0 | AW10: =AV10*E10 -> 0 | AX10: 0 | AY10: =AX10*E10 -> 0 | AZ10: 0 | BA10: =AZ10*E10 -> 0 | BB10: 0 | BC10: =BB10*E10 -> 0 | BD10: 0 | BE10: =BD10*E10 -> 0
A11: REDBULL | B11: 5000 | C11: 6150 | D11: 10000 | E11: =D11-C11 -> 3850 | F11: 0 | G11: =F11*E11 -> 0 | H11: 0 | I11: =H11*E11 -> 0 | J11: 0 | K11: =J11*E11 -> 0 | L11: 0 | M11: =L11*E11 -> 0 | N11: 0 | O11: =N11*E11 -> 0 | P11: 0 | Q11: =P11*E11 -> 0 | R11: 0 | S11: =R11*E11 -> 0 | T11: 0 | U11: =T11*E11 -> 0 | V11: 0 | W11: =V11*E11 -> 0 | X11: 0 | Y11: =X11*E11 -> 0 | Z11: 0 | AA11: =Z11*E11 -> 0 | AB11: 0 | AC11: =AB11*E11 -> 0 | AD11: 0 | AE11: =AD11*E11 -> 0 | AF11: 0 | AG11: =AF11*E11 -> 0 | AH11: 0 | AI11: =AH11*E11 -> 0 | AJ11: 0 | AK11: =AJ11*E11 -> 0 | AL11: 0 | AM11: =AL11*E11 -> 0 | AN11: 0 | AO11: =AN11*E11 -> 0 | AP11: 0 | AQ11: =AP11*E11 -> 0 | AR11: 0 | AS11: =AR11*E11 -> 0 | AT11: 0 | AU11: =AT11*E11 -> 0 | AV11: 0 | AW11: =AV11*E11 -> 0 | AX11: 0 | AY11: =AX11*E11 -> 0 | AZ11: 0 | BA11: =AZ11*E11 -> 0 | BB11: 0 | BC11: =BB11*E11 -> 0 | BD11: 0 | BE11: =BD11*E11 -> 0
A12: ELECTROLIT | B12: 6800 | C12: 6800 | D12: 10000 | E12: =D12-C12 -> 3200 | F12: 0 | G12: =F12*E12 -> 0 | H12: 0 | I12: =H12*E12 -> 0 | J12: 0 | K12: =J12*E12 -> 0 | L12: 0 | M12: =L12*E12 -> 0 | N12: 0 | O12: =N12*E12 -> 0 | P12: 0 | Q12: =P12*E12 -> 0 | R12: 0 | S12: =R12*E12 -> 0 | T12: 0 | U12: =T12*E12 -> 0 | V12: 0 | W12: =V12*E12 -> 0 | X12: 0 | Y12: =X12*E12 -> 0 | Z12: 0 | AA12: =Z12*E12 -> 0 | AB12: 0 | AC12: =AB12*E12 -> 0 | AD12: 0 | AE12: =AD12*E12 -> 0 | AF12: 1 | AG12: =AF12*E12 -> 3200 | AH12: 1 | AI12: =AH12*E12 -> 3200 | AJ12: 0 | AK12: =AJ12*E12 -> 0 | AL12: 0 | AM12: =AL12*E12 -> 0 | AN12: 0 | AO12: =AN12*E12 -> 0 | AP12: 0 | AQ12: =AP12*E12 -> 0 | AR12: 1 | AS12: =AR12*E12 -> 3200 | AT12: 0 | AU12: =AT12*E12 -> 0 | AV12: 0 | AW12: =AV12*E12 -> 0 | AX12: 0 | AY12: =AX12*E12 -> 0 | AZ12: 0 | BA12: =AZ12*E12 -> 0 | BB12: 0 | BC12: =BB12*E12 -> 0 | BD12: 0 | BE12: =BD12*E12 -> 0
A13: POKER LATA | B13: 60000 | C13: 2500 | D13: 5000 | E13: =D13-C13 -> 2500 | F13: 0 | G13: =F13*E13 -> 0 | H13: 0 | I13: =H13*E13 -> 0 | J13: 0 | K13: =J13*E13 -> 0 | L13: 0 | M13: =L13*E13 -> 0 | N13: 0 | O13: =N13*E13 -> 0 | P13: 0 | Q13: =P13*E13 -> 0 | R13: 1 | S13: =R13*E13 -> 2500 | T13: 0 | U13: =T13*E13 -> 0 | V13: 0 | W13: =V13*E13 -> 0 | X13: 0 | Y13: =X13*E13 -> 0 | Z13: 0 | AA13: =Z13*E13 -> 0 | AB13: 0 | AC13: =AB13*E13 -> 0 | AD13: 0 | AE13: =AD13*E13 -> 0 | AF13: 0 | AG13: =AF13*E13 -> 0 | AH13: 0 | AI13: =AH13*E13 -> 0 | AJ13: 0 | AK13: =AJ13*E13 -> 0 | AL13: 0 | AM13: =AL13*E13 -> 0 | AN13: 0 | AO13: =AN13*E13 -> 0 | AP13: 0 | AQ13: =AP13*E13 -> 0 | AR13: 0 | AS13: =AR13*E13 -> 0 | AT13: 0 | AU13: =AT13*E13 -> 0 | AV13: 0 | AW13: =AV13*E13 -> 0 | AX13: 0 | AY13: =AX13*E13 -> 0 | AZ13: 0 | BA13: =AZ13*E13 -> 0 | BB13: 0 | BC13: =BB13*E13 -> 0 | BD13: 0 | BE13: =BD13*E13 -> 0
... A15: CORONITA LATA | B15: 56000 | C15: 2333 | D15: 5000 | E15: =D15-C15 -> 2667 | F15: 0 | G15: =F15*E15 -> 0 | H15: 0 | I15: =H15*E15 -> 0 | J15: 0 | K15: =J15*E15 -> 0 | L15: 0 | M15: =L15*E15 -> 0 | N15: 0 | O15: =N15*E15 -> 0 | P15: 0 | Q15: =P15*E15 -> 0 | R15: 0 | S15: =R15*E15 -> 0 | T15: 0 | U15: =T15*E15 -> 0 | V15: 0 | W15: =V15*E15 -> 0 | X15: 0 | Y15: =X15*E15 -> 0 | Z15: 0 | AA15: =Z15*E15 -> 0 | AB15: 0 | AC15: =AB15*E15 -> 0 | AD15: 0 | AE15: =AD15*E15 -> 0 | AF15: 0 | AG15: =AF15*E15 -> 0 | AH15: 0 | AI15: =AH15*E15 -> 0 | AJ15: 0 | AK15: =AJ15*E15 -> 0 | AL15: 0 | AM15: =AL15*E15 -> 0 | AN15: 0 | AO15: =AN15*E15 -> 0 | AP15: 0 | AQ15: =AP15*E15 -> 0 | AR15: 0 | AS15: =AR15*E15 -> 0 | AT15: 0 | AU15: =AT15*E15 -> 0 | AV15: 0 | AW15: =AV15*E15 -> 0 | AX15: 0 | AY15: =AX15*E15 -> 0 | AZ15: 0 | BA15: =AZ15*E15 -> 0 | BB15: 0 | BC15: =BB15*E15 -> 0 | BD15: 0 | BE15: =BD15*E15 -> 0
A16: CORONA LATA | D16: 7000 | E16: =D16-C16 -> 7000 | F16: 0 | G16: =F16*E16 -> 0 | H16: 0 | I16: =H16*E16 -> 0 | J16: 0 | K16: =J16*E16 -> 0 | L16: 0 | M16: =L16*E16 -> 0 | N16: 0 | O16: =N16*E16 -> 0 | P16: 0 | Q16: =P16*E16 -> 0 | R16: 0 | S16: =R16*E16 -> 0 | T16: 0 | U16: =T16*E16 -> 0 | V16: 0 | W16: =V16*E16 -> 0 | X16: 0 | Y16: =X16*E16 -> 0 | Z16: 0 | AA16: =Z16*E16 -> 0 | AB16: 0 | AC16: =AB16*E16 -> 0 | AD16: 0 | AE16: =AD16*E16 -> 0 | AF16: 0 | AG16: =AF16*E16 -> 0 | AH16: 0 | AI16: =AH16*E16 -> 0 | AJ16: 0 | AK16: =AJ16*E16 -> 0 | AL16: 0 | AM16: =AL16*E16 -> 0 | AN16: 0 | AO16: =AN16*E16 -> 0 | AP16: 0 | AQ16: =AP16*E16 -> 0 | AR16: 0 | AS16: =AR16*E16 -> 0 | AT16: 0 | AU16: =AT16*E16 -> 0 | AV16: 0 | AW16: =AV16*E16 -> 0 | AX16: 0 | AY16: =AX16*E16 -> 0 | AZ16: 0 | BA16: =AZ16*E16 -> 0 | BB16: 0 | BC16: =BB16*E16 -> 0 | BD16: 0 | BE16: =BD16*E16 -> 0
A17: HEINEKEN LATA X24 | B17: 46000 | C17: 1916 | D17: 6000 | E17: =D17-C17 -> 4084 | F17: 0 | G17: =F17*E17 -> 0 | H17: 0 | I17: =H17*E17 -> 0 | J17: 0 | K17: =J17*E17 -> 0 | L17: 0 | M17: =L17*E17 -> 0 | N17: 0 | O17: =N17*E17 -> 0 | P17: 0 | Q17: =P17*E17 -> 0 | R17: 0 | S17: =R17*E17 -> 0 | T17: 0 | U17: =T17*E17 -> 0 | V17: 0 | W17: =V17*E17 -> 0 | X17: 0 | Y17: =X17*E17 -> 0 | Z17: 0 | AA17: =Z17*E17 -> 0 | AB17: 0 | AC17: =AB17*E17 -> 0 | AD17: 0 | AE17: =AD17*E17 -> 0 | AF17: 0 | AG17: =AF17*E17 -> 0 | AH17: 0 | AI17: =AH17*E17 -> 0 | AJ17: 0 | AK17: =AJ17*E17 -> 0 | AL17: 0 | AM17: =AL17*E17 -> 0 | AN17: 0 | AO17: =AN17*E17 -> 0 | AP17: 0 | AQ17: =AP17*E17 -> 0 | AR17: 0 | AS17: =AR17*E17 -> 0 | AT17: 0 | AU17: =AT17*E17 -> 0 | AV17: 0 | AW17: =AV17*E17 -> 0 | AX17: 0 | AY17: =AX17*E17 -> 0 | AZ17: 0 | BA17: =AZ17*E17 -> 0 | BB17: 0 | BC17: =BB17*E17 -> 0 | BD17: 0 | BE17: =BD17*E17 -> 0
A18: SOL PEQUEÑA X24 | B18: 55000 | C18: 2291 | D18: 4000 | E18: =D18-C18 -> 1709 | F18: 0 | G18: =F18*E18 -> 0 | H18: 0 | I18: =H18*E18 -> 0 | J18: 0 | K18: =J18*E18 -> 0 | L18: 0 | M18: =L18*E18 -> 0 | N18: 0 | O18: =N18*E18 -> 0 | P18: 0 | Q18: =P18*E18 -> 0 | R18: 0 | S18: =R18*E18 -> 0 | T18: 0 | U18: =T18*E18 -> 0 | V18: 0 | W18: =V18*E18 -> 0 | X18: 0 | Y18: =X18*E18 -> 0 | Z18: 0 | AA18: =Z18*E18 -> 0 | AB18: 0 | AC18: =AB18*E18 -> 0 | AD18: 0 | AE18: =AD18*E18 -> 0 | AF18: 0 | AG18: =AF18*E18 -> 0 | AH18: 0 | AI18: =AH18*E18 -> 0 | AJ18: 0 | AK18: =AJ18*E18 -> 0 | AL18: 0 | AM18: =AL18*E18 -> 0 | AN18: 0 | AO18: =AN18*E18 -> 0 | AP18: 0 | AQ18: =AP18*E18 -> 0 | AR18: 0 | AS18: =AR18*E18 -> 0 | AT18: 0 | AU18: =AT18*E18 -> 0 | AV18: 0 | AW18: =AV18*E18 -> 0 | AX18: 0 | AY18: =AX18*E18 -> 0 | AZ18: 0 | BA18: =AZ18*E18 -> 0 | BB18: 0 | BC18: =BB18*E18 -> 0 | BD18: 0 | BE18: =BD18*E18 -> 0
A19: SOL GRANDE X24 | B19: 72000 | C19: 3000 | D19: 6000 | E19: =D19-C19 -> 3000 | F19: 6 | G19: =F19*E19 -> 18000 | H19: 0 | I19: =H19*E19 -> 0 | J19: 0 | K19: =J19*E19 -> 0 | L19: 0 | M19: =L19*E19 -> 0 | N19: 0 | O19: =N19*E19 -> 0 | P19: 0 | Q19: =P19*E19 -> 0 | R19: 0 | S19: =R19*E19 -> 0 | T19: 0 | U19: =T19*E19 -> 0 | V19: 0 | W19: =V19*E19 -> 0 | X19: 0 | Y19: =X19*E19 -> 0 | Z19: 0 | AA19: =Z19*E19 -> 0 | AB19: 0 | AC19: =AB19*E19 -> 0 | AD19: 0 | AE19: =AD19*E19 -> 0 | AF19: 0 | AG19: =AF19*E19 -> 0 | AH19: 0 | AI19: =AH19*E19 -> 0 | AJ19: 0 | AK19: =AJ19*E19 -> 0 | AL19: 0 | AM19: =AL19*E19 -> 0 | AN19: 0 | AO19: =AN19*E19 -> 0 | AP19: 0 | AQ19: =AP19*E19 -> 0 | AR19: 0 | AS19: =AR19*E19 -> 0 | AT19: 0 | AU19: =AT19*E19 -> 0 | AV19: 0 | AW19: =AV19*E19 -> 0 | AX19: 0 | AY19: =AX19*E19 -> 0 | AZ19: 0 | BA19: =AZ19*E19 -> 0 | BB19: 0 | BC19: =BB19*E19 -> 0 | BD19: 0 | BE19: =BD19*E19 -> 0
A20: ANDINA PEQUEÑA X6 | B20: 7560 | C20: 1260 | D20: 3000 | E20: =D20-C20 -> 1740 | F20: 0 | G20: =F20*E20 -> 0 | H20: 0 | I20: =H20*E20 -> 0 | J20: 0 | K20: =J20*E20 -> 0 | L20: 0 | M20: =L20*E20 -> 0 | N20: 0 | O20: =N20*E20 -> 0 | P20: 0 | Q20: =P20*E20 -> 0 | R20: 0 | S20: =R20*E20 -> 0 | T20: 0 | U20: =T20*E20 -> 0 | V20: 0 | W20: =V20*E20 -> 0 | X20: 0 | Y20: =X20*E20 -> 0 | Z20: 0 | AA20: =Z20*E20 -> 0 | AB20: 0 | AC20: =AB20*E20 -> 0 | AD20: 0 | AE20: =AD20*E20 -> 0 | AF20: 0 | AG20: =AF20*E20 -> 0 | AH20: 0 | AI20: =AH20*E20 -> 0 | AJ20: 0 | AK20: =AJ20*E20 -> 0 | AL20: 0 | AM20: =AL20*E20 -> 0 | AN20: 0 | AO20: =AN20*E20 -> 0 | AP20: 0 | AQ20: =AP20*E20 -> 0 | AR20: 0 | AS20: =AR20*E20 -> 0 | AT20: 0 | AU20: =AT20*E20 -> 0 | AV20: 0 | AW20: =AV20*E20 -> 0 | AX20: 0 | AY20: =AX20*E20 -> 0 | AZ20: 0 | BA20: =AZ20*E20 -> 0 | BB20: 0 | BC20: =BB20*E20 -> 0 | BD20: 0 | BE20: =BD20*E20 -> 0
A21: ANDINA GRANDE X30 | B21: 54700 | C21: 1823 | D21: 4000 | E21: =D21-C21 -> 2177 | F21: 0 | G21: =F21*E21 -> 0 | H21: 0 | I21: =H21*E21 -> 0 | J21: 0 | K21: =J21*E21 -> 0 | L21: 0 | M21: =L21*E21 -> 0 | N21: 0 | O21: =N21*E21 -> 0 | P21: 0 | Q21: =P21*E21 -> 0 | R21: 0 | S21: =R21*E21 -> 0 | T21: 0 | U21: =T21*E21 -> 0 | V21: 0 | W21: =V21*E21 -> 0 | X21: 0 | Y21: =X21*E21 -> 0 | Z21: 0 | AA21: =Z21*E21 -> 0 | AB21: 0 | AC21: =AB21*E21 -> 0 | AD21: 0 | AE21: =AD21*E21 -> 0 | AF21: 0 | AG21: =AF21*E21 -> 0 | AH21: 0 | AI21: =AH21*E21 -> 0 | AJ21: 0 | AK21: =AJ21*E21 -> 0 | AL21: 0 | AM21: =AL21*E21 -> 0 | AN21: 0 | AO21: =AN21*E21 -> 0 | AP21: 0 | AQ21: =AP21*E21 -> 0 | AR21: 0 | AS21: =AR21*E21 -> 0 | AT21: 8 | AU21: =AT21*E21 -> 17416 | AV21: 0 | AW21: =AV21*E21 -> 0 | AX21: 0 | AY21: =AX21*E21 -> 0 | AZ21: 0 | BA21: =AZ21*E21 -> 0 | BB21: 0 | BC21: =BB21*E21 -> 0 | BD21: 0 | BE21: =BD21*E21 -> 0
A22: ANDINA DORADA X30 | B22: 56000 | C22: 1866 | D22: 4000 | E22: =D22-C22 -> 2134 | F22: 0 | G22: =F22*E22 -> 0 | H22: 0 | I22: =H22*E22 -> 0 | J22: 0 | K22: =J22*E22 -> 0 | L22: 0 | M22: =L22*E22 -> 0 | N22: 0 | O22: =N22*E22 -> 0 | P22: 0 | Q22: =P22*E22 -> 0 | R22: 0 | S22: =R22*E22 -> 0 | T22: 0 | U22: =T22*E22 -> 0 | V22: 0 | W22: =V22*E22 -> 0 | X22: 0 | Y22: =X22*E22 -> 0 | Z22: 0 | AA22: =Z22*E22 -> 0 | AB22: 0 | AC22: =AB22*E22 -> 0 | AD22: 0 | AE22: =AD22*E22 -> 0 | AF22: 0 | AG22: =AF22*E22 -> 0 | AH22: 0 | AI22: =AH22*E22 -> 0 | AJ22: 0 | AK22: =AJ22*E22 -> 0 | AL22: 0 | AM22: =AL22*E22 -> 0 | AN22: 0 | AO22: =AN22*E22 -> 0 | AP22: 0 | AQ22: =AP22*E22 -> 0 | AR22: 0 | AS22: =AR22*E22 -> 0 | AT22: 0 | AU22: =AT22*E22 -> 0 | AV22: 0 | AW22: =AV22*E22 -> 0 | AX22: 0 | AY22: =AX22*E22 -> 0 | AZ22: 0 | BA22: =AZ22*E22 -> 0 | BB22: 0 | BC22: =BB22*E22 -> 0 | BD22: 0 | BE22: =BD22*E22 -> 0
A23: HEINEKEN BOTELLA X24 | B23: 55000 | C23: 2291 | D23: 5000 | E23: =D23-C23 -> 2709 | F23: 1 | G23: =F23*E23 -> 2709 | H23: 0 | I23: =H23*E23 -> 0 | J23: 0 | K23: =J23*E23 -> 0 | L23: 0 | M23: =L23*E23 -> 0 | N23: 0 | O23: =N23*E23 -> 0 | P23: 0 | Q23: =P23*E23 -> 0 | R23: 0 | S23: =R23*E23 -> 0 | T23: 0 | U23: =T23*E23 -> 0 | V23: 0 | W23: =V23*E23 -> 0 | X23: 0 | Y23: =X23*E23 -> 0 | Z23: 0 | AA23: =Z23*E23 -> 0 | AB23: 0 | AC23: =AB23*E23 -> 0 | AD23: 0 | AE23: =AD23*E23 -> 0 | AF23: 0 | AG23: =AF23*E23 -> 0 | AH23: 0 | AI23: =AH23*E23 -> 0 | AJ23: 0 | AK23: =AJ23*E23 -> 0 | AL23: 0 | AM23: =AL23*E23 -> 0 | AN23: 0 | AO23: =AN23*E23 -> 0 | AP23: 0 | AQ23: =AP23*E23 -> 0 | AR23: 0 | AS23: =AR23*E23 -> 0 | AT23: 0 | AU23: =AT23*E23 -> 0 | AV23: 0 | AW23: =AV23*E23 -> 0 | AX23: 0 | AY23: =AX23*E23 -> 0 | AZ23: 0 | BA23: =AZ23*E23 -> 0 | BB23: 0 | BC23: =BB23*E23 -> 0 | BD23: 0 | BE23: =BD23*E23 -> 0
A24: CORONITA | B24: 6000 | C24: 2500 | D24: 5000 | E24: =D24-C24 -> 2500 | F24: 6 | G24: =F24*E24 -> 15000 | H24: 49 | I24: =H24*E24 -> 122500 | J24: 0 | K24: =J24*E24 -> 0 | L24: 2 | M24: =L24*E24 -> 5000 | N24: 16 | O24: =N24*E24 -> 40000 | P24: 0 | Q24: =P24*E24 -> 0 | R24: 0 | S24: =R24*E24 -> 0 | T24: 1 | U24: =T24*E24 -> 2500 | V24: 0 | W24: =V24*E24 -> 0 | X24: 0 | Y24: =X24*E24 -> 0 | Z24: 0 | AA24: =Z24*E24 -> 0 | AB24: 0 | AC24: =AB24*E24 -> 0 | AD24: 3 | AE24: =AD24*E24 -> 7500 | AF24: 12 | AG24: =AF24*E24 -> 30000 | AH24: 0 | AI24: =AH24*E24 -> 0 | AJ24: 0 | AK24: =AJ24*E24 -> 0 | AL24: 0 | AM24: =AL24*E24 -> 0 | AN24: 14 | AO24: =AN24*E24 -> 35000 | AP24: 0 | AQ24: =AP24*E24 -> 0 | AR24: 17 | AS24: =AR24*E24 -> 42500 | AT24: 1 | AU24: =AT24*E24 -> 2500 | AV24: 0 | AW24: =AV24*E24 -> 0 | AX24: 0 | AY24: =AX24*E24 -> 0 | AZ24: 8 | BA24: =AZ24*E24 -> 20000 | BB24: 0 | BC24: =BB24*E24 -> 0 | BD24: 2 | BE24: =BD24*E24 -> 5000
A25: AGUILA | B25: 64000 | C25: 2133 | D25: 3400 | E25: =D25-C25 -> 1267 | F25: 70 | G25: =F25*E25 -> 88690 | H25: 80 | I25: =H25*E25 -> 101360 | J25: 4 | K25: =J25*E25 -> 5068 | L25: 70 | M25: =L25*E25 -> 88690 | N25: 58 | O25: =N25*E25 -> 73486 | P25: 23 | Q25: =P25*E25 -> 29141 | R25: 50 | S25: =R25*E25 -> 63350 | T25: 42 | U25: =T25*E25 -> 53214 | V25: 5 | W25: =V25*E25 -> 6335 | X25: 63 | Y25: =X25*E25 -> 79821 | Z25: 12 | AA25: =Z25*E25 -> 15204 | AB25: 0 | AC25: =AB25*E25 -> 0 | AD25: 68 | AE25: =AD25*E25 -> 86156 | AF25: 92 | AG25: =AF25*E25 -> 116564 | AH25: 25 | AI25: =AH25*E25 -> 31675 | AJ25: 7 | AK25: =AJ25*E25 -> 8869 | AL25: 17 | AM25: =AL25*E25 -> 21539 | AN25: 23 | AO25: =AN25*E25 -> 29141 | AP25: 40 | AQ25: =AP25*E25 -> 50680 | AR25: 27 | AS25: =AR25*E25 -> 34209 | AT25: 11 | AU25: =AT25*E25 -> 13937 | AV25: 12 | AW25: =AV25*E25 -> 15204 | AX25: 26 | AY25: =AX25*E25 -> 32942 | AZ25: 25 | BA25: =AZ25*E25 -> 31675 | BB25: 30 | BC25: =BB25*E25 -> 38010 | BD25: 15 | BE25: =BD25*E25 -> 19005
A26: LIGTH | B26: 63500 | C26: 2116 | D26: 3400 | E26: =D26-C26 -> 1284 | F26: 72 | G26: =F26*E26 -> 92448 | H26: 9 | I26: =H26*E26 -> 11556 | J26: 0 | K26: =J26*E26 -> 0 | L26: 57 | M26: =L26*E26 -> 73188 | N26: 5 | O26: =N26*E26 -> 6420 | P26: 8 | Q26: =P26*E26 -> 10272 | R26: 27 | S26: =R26*E26 -> 34668 | T26: 4 | U26: =T26*E26 -> 5136 | V26: 6 | W26: =V26*E26 -> 7704 | X26: 6 | Y26: =X26*E26 -> 7704 | Z26: 0 | AA26: =Z26*E26 -> 0 | AB26: 4 | AC26: =AB26*E26 -> 5136 | AD26: 12 | AE26: =AD26*E26 -> 15408 | AF26: 34 | AG26: =AF26*E26 -> 43656 | AH26: 19 | AI26: =AH26*E26 -> 24396 | AJ26: 18 | AK26: =AJ26*E26 -> 23112 | AL26: 0 | AM26: =AL26*E26 -> 0 | AN26: 49 | AO26: =AN26*E26 -> 62916 | AP26: 32 | AQ26: =AP26*E26 -> 41088 | AR26: 30 | AS26: =AR26*E26 -> 38520 | AT26: 31 | AU26: =AT26*E26 -> 39804 | AV26: 36 | AW26: =AV26*E26 -> 46224 | AX26: 0 | AY26: =AX26*E26 -> 0 | AZ26: 96 | BA26: =AZ26*E26 -> 123264 | BB26: 90 | BC26: =BB26*E26 -> 115560 | BD26: 39 | BE26: =BD26*E26 -> 50076
A27: POKER | B27: 63500 | C27: 2116 | D27: 3400 | E27: =D27-C27 -> 1284 | F27: 13 | G27: =F27*E27 -> 16692 | H27: 20 | I27: =H27*E27 -> 25680 | J27: 0 | K27: =J27*E27 -> 0 | L27: 7 | M27: =L27*E27 -> 8988 | N27: 5 | O27: =N27*E27 -> 6420 | P27: 0 | Q27: =P27*E27 -> 0 | R27: 5 | S27: =R27*E27 -> 6420 | T27: 4 | U27: =T27*E27 -> 5136 | V27: 0 | W27: =V27*E27 -> 0 | X27: 0 | Y27: =X27*E27 -> 0 | Z27: 0 | AA27: =Z27*E27 -> 0 | AB27: 0 | AC27: =AB27*E27 -> 0 | AD27: 0 | AE27: =AD27*E27 -> 0 | AF27: 21 | AG27: =AF27*E27 -> 26964 | AH27: 5 | AI27: =AH27*E27 -> 6420 | AJ27: 0 | AK27: =AJ27*E27 -> 0 | AL27: 4 | AM27: =AL27*E27 -> 5136 | AN27: 1 | AO27: =AN27*E27 -> 1284 | AP27: 2 | AQ27: =AP27*E27 -> 2568 | AR27: 8 | AS27: =AR27*E27 -> 10272 | AT27: 4 | AU27: =AT27*E27 -> 5136 | AV27: 4 | AW27: =AV27*E27 -> 5136 | AX27: 0 | AY27: =AX27*E27 -> 0 | AZ27: 0 | BA27: =AZ27*E27 -> 0 | BB27: 18 | BC27: =BB27*E27 -> 23112 | BD27: 2 | BE27: =BD27*E27 -> 2568
A28: COSTEÑA | B28: 52500 | C28: 1733 | D28: 3400 | E28: =D28-C28 -> 1667 | F28: 3 | G28: =F28*E28 -> 5001 | H28: 8 | I28: =H28*E28 -> 13336 | J28: 20 | K28: =J28*E28 -> 33340 | L28: 23 | M28: =L28*E28 -> 38341 | N28: 6 | O28: =N28*E28 -> 10002 | P28: 0 | Q28: =P28*E28 -> 0 | R28: 10 | S28: =R28*E28 -> 16670 | T28: 6 | U28: =T28*E28 -> 10002 | V28: 0 | W28: =V28*E28 -> 0 | X28: 0 | Y28: =X28*E28 -> 0 | Z28: 2 | AA28: =Z28*E28 -> 3334 | AB28: 12 | AC28: =AB28*E28 -> 20004 | AD28: 18 | AE28: =AD28*E28 -> 30006 | AF28: 0 | AG28: =AF28*E28 -> 0 | AH28: 5 | AI28: =AH28*E28 -> 8335 | AJ28: 0 | AK28: =AJ28*E28 -> 0 | AL28: 5 | AM28: =AL28*E28 -> 8335 | AN28: 0 | AO28: =AN28*E28 -> 0 | AP28: 26 | AQ28: =AP28*E28 -> 43342 | AR28: 26 | AS28: =AR28*E28 -> 43342 | AT28: 5 | AU28: =AT28*E28 -> 8335 | AV28: 0 | AW28: =AV28*E28 -> 0 | AX28: 0 | AY28: =AX28*E28 -> 0 | AZ28: 9 | BA28: =AZ28*E28 -> 15003 | BB28: 20 | BC28: =BB28*E28 -> 33340 | BD28: 7 | BE28: =BD28*E28 -> 11669
... A33: 1 BOTELLA AG. ANTIOQUEÑO AZUL | B33: 43150 | C33: 43150 | D33: 85000 | E33: =D33-C33 -> 41850 | F33: 0 | G33: =F33*E33 -> 0 | H33: 0 | I33: =H33*E33 -> 0 | J33: 0 | K33: =J33*E33 -> 0 | L33: 0 | M33: =L33*E33 -> 0 | N33: 0 | O33: =N33*E33 -> 0 | P33: 0 | Q33: =P33*E33 -> 0 | R33: 0 | S33: =R33*E33 -> 0 | T33: 0 | U33: =T33*E33 -> 0 | V33: 0 | W33: =V33*E33 -> 0 | X33: 0 | Y33: =X33*E33 -> 0 | Z33: 0 | AA33: =Z33*E33 -> 0 | AB33: 0 | AC33: =AB33*E33 -> 0 | AD33: 0 | AE33: =AD33*E33 -> 0 | AF33: 0 | AG33: =AF33*E33 -> 0 | AH33: 0 | AI33: =AH33*E33 -> 0 | AJ33: 0 | AK33: =AJ33*E33 -> 0 | AL33: 0 | AM33: =AL33*E33 -> 0 | AN33: 0 | AO33: =AN33*E33 -> 0 | AP33: 0 | AQ33: =AP33*E33 -> 0 | AR33: 0 | AS33: =AR33*E33 -> 0 | AT33: 0 | AU33: =AT33*E33 -> 0 | AV33: 0 | AW33: =AV33*E33 -> 0 | AX33: 0 | AY33: =AX33*E33 -> 0 | AZ33: 0 | BA33: =AZ33*E33 -> 0 | BB33: 0 | BC33: =BB33*E33 -> 0 | BD33: 0 | BE33: =BD33*E33 -> 0
A34: SMIRNOFF LULO PEQUEÑA | D34: 50000 | E34: =D34-C34 -> 50000 | F34: 0 | G34: =F34*E34 -> 0 | H34: 0 | I34: =H34*E34 -> 0 | J34: 0 | K34: =J34*E34 -> 0 | L34: 0 | M34: =L34*E34 -> 0 | N34: 0 | O34: =N34*E34 -> 0 | P34: 0 | Q34: =P34*E34 -> 0 | R34: 0 | S34: =R34*E34 -> 0 | T34: 0 | U34: =T34*E34 -> 0 | V34: 0 | W34: =V34*E34 -> 0 | X34: 0 | Y34: =X34*E34 -> 0 | Z34: 0 | AA34: =Z34*E34 -> 0 | AB34: 0 | AC34: =AB34*E34 -> 0 | AD34: 0 | AE34: =AD34*E34 -> 0 | AF34: 0 | AG34: =AF34*E34 -> 0 | AH34: 0 | AI34: =AH34*E34 -> 0 | AJ34: 0 | AK34: =AJ34*E34 -> 0 | AL34: 0 | AM34: =AL34*E34 -> 0 | AN34: 0 | AO34: =AN34*E34 -> 0 | AP34: 0 | AQ34: =AP34*E34 -> 0 | AR34: 0 | AS34: =AR34*E34 -> 0 | AT34: 0 | AU34: =AT34*E34 -> 0 | AV34: 0 | AW34: =AV34*E34 -> 0 | AX34: 0 | AY34: =AX34*E34 -> 0 | AZ34: 0 | BA34: =AZ34*E34 -> 0 | BB34: 0 | BC34: =BB34*E34 -> 0 | BD34: 0 | BE34: =BD34*E34 -> 0
A35: RON MEDELLIN DORADO GRANDE | D35: 45000 | E35: =D35-C35 -> 45000 | F35: 0 | G35: =F35*E35 -> 0 | H35: 0 | I35: =H35*E35 -> 0 | J35: 0 | K35: =J35*E35 -> 0 | L35: 0 | M35: =L35*E35 -> 0 | N35: 0 | O35: =N35*E35 -> 0 | P35: 0 | Q35: =P35*E35 -> 0 | R35: 0 | S35: =R35*E35 -> 0 | T35: 0 | U35: =T35*E35 -> 0 | V35: 0 | W35: =V35*E35 -> 0 | X35: 0 | Y35: =X35*E35 -> 0 | Z35: 0 | AA35: =Z35*E35 -> 0 | AB35: 0 | AC35: =AB35*E35 -> 0 | AD35: 0 | AE35: =AD35*E35 -> 0 | AF35: 0 | AG35: =AF35*E35 -> 0 | AH35: 0 | AI35: =AH35*E35 -> 0 | AJ35: 0 | AK35: =AJ35*E35 -> 0 | AL35: 0 | AM35: =AL35*E35 -> 0 | AN35: 0 | AO35: =AN35*E35 -> 0 | AP35: 0 | AQ35: =AP35*E35 -> 0 | AR35: 0 | AS35: =AR35*E35 -> 0 | AT35: 0 | AU35: =AT35*E35 -> 0 | AV35: 0 | AW35: =AV35*E35 -> 0 | AX35: 0 | AY35: =AX35*E35 -> 0 | AZ35: 0 | BA35: =AZ35*E35 -> 0 | BB35: 0 | BC35: =BB35*E35 -> 0 | BD35: 0 | BE35: =BD35*E35 -> 0
A36: RON MEDELLIN DORADO PEQUEÑA | D36: 85000 | E36: =D36-C36 -> 85000 | F36: 0 | G36: =F36*E36 -> 0 | H36: 0 | I36: =H36*E36 -> 0 | J36: 0 | K36: =J36*E36 -> 0 | L36: 0 | M36: =L36*E36 -> 0 | N36: 0 | O36: =N36*E36 -> 0 | P36: 0 | Q36: =P36*E36 -> 0 | R36: 0 | S36: =R36*E36 -> 0 | T36: 0 | U36: =T36*E36 -> 0 | V36: 0 | W36: =V36*E36 -> 0 | X36: 0 | Y36: =X36*E36 -> 0 | Z36: 0 | AA36: =Z36*E36 -> 0 | AB36: 0 | AC36: =AB36*E36 -> 0 | AD36: 0 | AE36: =AD36*E36 -> 0 | AF36: 0 | AG36: =AF36*E36 -> 0 | AH36: 0 | AI36: =AH36*E36 -> 0 | AJ36: 0 | AK36: =AJ36*E36 -> 0 | AL36: 0 | AM36: =AL36*E36 -> 0 | AN36: 0 | AO36: =AN36*E36 -> 0 | AP36: 0 | AQ36: =AP36*E36 -> 0 | AR36: 0 | AS36: =AR36*E36 -> 0 | AT36: 0 | AU36: =AT36*E36 -> 0 | AV36: 0 | AW36: =AV36*E36 -> 0 | AX36: 0 | AY36: =AX36*E36 -> 0 | AZ36: 0 | BA36: =AZ36*E36 -> 0 | BB36: 0 | BC36: =BB36*E36 -> 0 | BD36: 0 | BE36: =BD36*E36 -> 0
A37: SOMETHING SPECIAL PEQUEÑA | E37: =D37-C37 -> 0 | F37: 0 | G37: =F37*E37 -> 0 | H37: 0 | I37: =H37*E37 -> 0 | J37: 0 | K37: =J37*E37 -> 0 | L37: 0 | M37: =L37*E37 -> 0 | N37: 0 | O37: =N37*E37 -> 0 | P37: 0 | Q37: =P37*E37 -> 0 | R37: 0 | S37: =R37*E37 -> 0 | T37: 0 | U37: =T37*E37 -> 0 | V37: 0 | W37: =V37*E37 -> 0 | X37: 0 | Y37: =X37*E37 -> 0 | Z37: 0 | AA37: =Z37*E37 -> 0 | AB37: 0 | AC37: =AB37*E37 -> 0 | AD37: 0 | AE37: =AD37*E37 -> 0 | AF37: 0 | AG37: =AF37*E37 -> 0 | AH37: 0 | AI37: =AH37*E37 -> 0 | AJ37: 0 | AK37: =AJ37*E37 -> 0 | AL37: 0 | AM37: =AL37*E37 -> 0 | AN37: 0 | AO37: =AN37*E37 -> 0 | AP37: 1 | AQ37: =AP37*E37 -> 0 | AR37: 0 | AS37: =AR37*E37 -> 0 | AT37: 0 | AU37: =AT37*E37 -> 0 | AV37: 0 | AW37: =AV37*E37 -> 0 | AX37: 0 | AY37: =AX37*E37 -> 0 | AZ37: 0 | BA37: =AZ37*E37 -> 0 | BB37: 0 | BC37: =BB37*E37 -> 0 | BD37: 0 | BE37: =BD37*E37 -> 0
A38: BLACK LABEL | E38: =D38-C38 -> 0 | F38: 0 | G38: =F38*E38 -> 0 | H38: 0 | I38: =H38*E38 -> 0 | J38: 0 | K38: =J38*E38 -> 0 | L38: 0 | M38: =L38*E38 -> 0 | N38: 0 | O38: =N38*E38 -> 0 | P38: 0 | Q38: =P38*E38 -> 0 | R38: 0 | S38: =R38*E38 -> 0 | T38: 0 | U38: =T38*E38 -> 0 | V38: 0 | W38: =V38*E38 -> 0 | X38: 0 | Y38: =X38*E38 -> 0 | Z38: 0 | AA38: =Z38*E38 -> 0 | AB38: 0 | AC38: =AB38*E38 -> 0 | AD38: 0 | AE38: =AD38*E38 -> 0 | AF38: 0 | AG38: =AF38*E38 -> 0 | AH38: 0 | AI38: =AH38*E38 -> 0 | AJ38: 0 | AK38: =AJ38*E38 -> 0 | AL38: 0 | AM38: =AL38*E38 -> 0 | AN38: 0 | AO38: =AN38*E38 -> 0 | AP38: 0 | AQ38: =AP38*E38 -> 0 | AR38: 0 | AS38: =AR38*E38 -> 0 | AT38: 0 | AU38: =AT38*E38 -> 0 | AV38: 0 | AW38: =AV38*E38 -> 0 | AX38: 0 | AY38: =AX38*E38 -> 0 | AZ38: 0 | BA38: =AZ38*E38 -> 0 | BB38: 0 | BC38: =BB38*E38 -> 0 | BD38: 0 | BE38: =BD38*E38 -> 0
A39: RED LABEL | E39: =D39-C39 -> 0 | F39: 0 | G39: =F39*E39 -> 0 | H39: 0 | I39: =H39*E39 -> 0 | J39: 0 | K39: =J39*E39 -> 0 | L39: 0 | M39: =L39*E39 -> 0 | N39: 0 | O39: =N39*E39 -> 0 | P39: 0 | Q39: =P39*E39 -> 0 | R39: 0 | S39: =R39*E39 -> 0 | T39: 0 | U39: =T39*E39 -> 0 | V39: 0 | W39: =V39*E39 -> 0 | X39: 0 | Y39: =X39*E39 -> 0 | Z39: 0 | AA39: =Z39*E39 -> 0 | AB39: 0 | AC39: =AB39*E39 -> 0 | AD39: 0 | AE39: =AD39*E39 -> 0 | AF39: 0 | AG39: =AF39*E39 -> 0 | AH39: 0 | AI39: =AH39*E39 -> 0 | AJ39: 0 | AK39: =AJ39*E39 -> 0 | AL39: 0 | AM39: =AL39*E39 -> 0 | AN39: 0 | AO39: =AN39*E39 -> 0 | AP39: 0 | AQ39: =AP39*E39 -> 0 | AR39: 0 | AS39: =AR39*E39 -> 0 | AT39: 0 | AU39: =AT39*E39 -> 0 | AV39: 0 | AW39: =AV39*E39 -> 0 | AX39: 0 | AY39: =AX39*E39 -> 0 | AZ39: 0 | BA39: =AZ39*E39 -> 0 | BB39: 0 | BC39: =BB39*E39 -> 0 | BD39: 0 | BE39: =BD39*E39 -> 0
A40: 1/2 MUSTANG | B40: 5500 | C40: 5500 | D40: 10000 | E40: =D40-C40 -> 4500 | F40: 0 | G40: =F40*E40 -> 0 | H40: 0 | I40: =H40*E40 -> 0 | J40: 0 | K40: =J40*E40 -> 0 | L40: 0 | M40: =L40*E40 -> 0 | N40: 0 | O40: =N40*E40 -> 0 | P40: 0 | Q40: =P40*E40 -> 0 | R40: 0 | S40: =R40*E40 -> 0 | T40: 0 | U40: =T40*E40 -> 0 | V40: 0 | W40: =V40*E40 -> 0 | X40: 1 | Y40: =X40*E40 -> 4500 | Z40: 0 | AA40: =Z40*E40 -> 0 | AB40: 0 | AC40: =AB40*E40 -> 0 | AD40: 0 | AE40: =AD40*E40 -> 0 | AF40: 0 | AG40: =AF40*E40 -> 0 | AH40: 0 | AI40: =AH40*E40 -> 0 | AJ40: 0 | AK40: =AJ40*E40 -> 0 | AL40: 0 | AM40: =AL40*E40 -> 0 | AN40: 0 | AO40: =AN40*E40 -> 0 | AP40: 0 | AQ40: =AP40*E40 -> 0 | AR40: 0 | AS40: =AR40*E40 -> 0 | AT40: 0 | AU40: =AT40*E40 -> 0 | AV40: 0 | AW40: =AV40*E40 -> 0 | AX40: 0 | AY40: =AX40*E40 -> 0 | AZ40: 2 | BA40: =AZ40*E40 -> 9000 | BB40: 1 | BC40: =BB40*E40 -> 4500 | BD40: 0 | BE40: =BD40*E40 -> 0
A41: UND. MUSTANG | B41: 5500 | C41: 550 | D41: 1000 | E41: =D41-C41 -> 450 | F41: 3 | G41: =F41*E41 -> 1350 | H41: 3 | I41: =H41*E41 -> 1350 | J41: 0 | K41: =J41*E41 -> 0 | L41: 9 | M41: =L41*E41 -> 4050 | N41: 15 | O41: =N41*E41 -> 6750 | P41: 4 | Q41: =P41*E41 -> 1800 | R41: 2 | S41: =R41*E41 -> 900 | T41: 16 | U41: =T41*E41 -> 7200 | V41: 0 | W41: =V41*E41 -> 0 | X41: 3 | Y41: =X41*E41 -> 1350 | Z41: 2 | AA41: =Z41*E41 -> 900 | AB41: 0 | AC41: =AB41*E41 -> 0 | AD41: 3 | AE41: =AD41*E41 -> 1350 | AF41: 3 | AG41: =AF41*E41 -> 1350 | AH41: 0 | AI41: =AH41*E41 -> 0 | AJ41: 0 | AK41: =AJ41*E41 -> 0 | AL41: 14 | AM41: =AL41*E41 -> 6300 | AN41: 7 | AO41: =AN41*E41 -> 3150 | AP41: 6 | AQ41: =AP41*E41 -> 2700 | AR41: 1 | AS41: =AR41*E41 -> 450 | AT41: 0 | AU41: =AT41*E41 -> 0 | AV41: 0 | AW41: =AV41*E41 -> 0 | AX41: 2 | AY41: =AX41*E41 -> 900 | AZ41: 9 | BA41: =AZ41*E41 -> 4050 | BB41: 0 | BC41: =BB41*E41 -> 0 | BD41: 0 | BE41: =BD41*E41 -> 0
A42: 1/2 LUCKY | B42: 6500 | C42: 6500 | D42: 10000 | E42: =D42-C42 -> 3500 | F42: 0 | G42: =F42*E42 -> 0 | H42: 0 | I42: =H42*E42 -> 0 | J42: 0 | K42: =J42*E42 -> 0 | L42: 0 | M42: =L42*E42 -> 0 | N42: 0 | O42: =N42*E42 -> 0 | P42: 0 | Q42: =P42*E42 -> 0 | R42: 0 | S42: =R42*E42 -> 0 | T42: 0 | U42: =T42*E42 -> 0 | V42: 0 | W42: =V42*E42 -> 0 | X42: 0 | Y42: =X42*E42 -> 0 | Z42: 0 | AA42: =Z42*E42 -> 0 | AB42: 0 | AC42: =AB42*E42 -> 0 | AD42: 1 | AE42: =AD42*E42 -> 3500 | AF42: 0 | AG42: =AF42*E42 -> 0 | AH42: 1 | AI42: =AH42*E42 -> 3500 | AJ42: 0 | AK42: =AJ42*E42 -> 0 | AL42: 0 | AM42: =AL42*E42 -> 0 | AN42: 0 | AO42: =AN42*E42 -> 0 | AP42: 0 | AQ42: =AP42*E42 -> 0 | AR42: 0 | AS42: =AR42*E42 -> 0 | AT42: 0 | AU42: =AT42*E42 -> 0 | AV42: 0 | AW42: =AV42*E42 -> 0 | AX42: 0 | AY42: =AX42*E42 -> 0 | AZ42: 0 | BA42: =AZ42*E42 -> 0 | BB42: 0 | BC42: =BB42*E42 -> 0 | BD42: 0 | BE42: =BD42*E42 -> 0
A43: UND. LUCKY | B43: 6500 | C43: 650 | D43: 1000 | E43: =D43-C43 -> 350 | F43: 4 | G43: =F43*E43 -> 1400 | H43: 7 | I43: =H43*E43 -> 2450 | J43: 0 | K43: =J43*E43 -> 0 | L43: 8 | M43: =L43*E43 -> 2800 | N43: 0 | O43: =N43*E43 -> 0 | P43: 0 | Q43: =P43*E43 -> 0 | R43: 6 | S43: =R43*E43 -> 2100 | T43: 6 | U43: =T43*E43 -> 2100 | V43: 1 | W43: =V43*E43 -> 350 | X43: 3 | Y43: =X43*E43 -> 1050 | Z43: 6 | AA43: =Z43*E43 -> 2100 | AB43: 0 | AC43: =AB43*E43 -> 0 | AD43: 13 | AE43: =AD43*E43 -> 4550 | AF43: 12 | AG43: =AF43*E43 -> 4200 | AH43: 4 | AI43: =AH43*E43 -> 1400 | AJ43: 2 | AK43: =AJ43*E43 -> 700 | AL43: 1 | AM43: =AL43*E43 -> 350 | AN43: 26 | AO43: =AN43*E43 -> 9100 | AP43: 21 | AQ43: =AP43*E43 -> 7350 | AR43: 8 | AS43: =AR43*E43 -> 2800 | AT43: 8 | AU43: =AT43*E43 -> 2800 | AV43: 1 | AW43: =AV43*E43 -> 350 | AX43: 1 | AY43: =AX43*E43 -> 350 | AZ43: 4 | BA43: =AZ43*E43 -> 1400 | BB43: 15 | BC43: =BB43*E43 -> 5250 | BD43: 2 | BE43: =BD43*E43 -> 700
A44: 1/2 MALBORO ROJO | B44: 5500 | C44: 5500 | D44: 10000 | E44: =D44-C44 -> 4500 | F44: 1 | G44: =F44*E44 -> 4500 | H44: 0 | I44: =H44*E44 -> 0 | J44: 0 | K44: =J44*E44 -> 0 | L44: 0 | M44: =L44*E44 -> 0 | N44: 0 | O44: =N44*E44 -> 0 | P44: 0 | Q44: =P44*E44 -> 0 | R44: 0 | S44: =R44*E44 -> 0 | T44: 0 | U44: =T44*E44 -> 0 | V44: 0 | W44: =V44*E44 -> 0 | X44: 0 | Y44: =X44*E44 -> 0 | Z44: 0 | AA44: =Z44*E44 -> 0 | AB44: 0 | AC44: =AB44*E44 -> 0 | AD44: 0 | AE44: =AD44*E44 -> 0 | AF44: 0 | AG44: =AF44*E44 -> 0 | AH44: 0 | AI44: =AH44*E44 -> 0 | AJ44: 0 | AK44: =AJ44*E44 -> 0 | AL44: 0 | AM44: =AL44*E44 -> 0 | AN44: 0 | AO44: =AN44*E44 -> 0 | AP44: 0 | AQ44: =AP44*E44 -> 0 | AR44: 0 | AS44: =AR44*E44 -> 0 | AT44: 0 | AU44: =AT44*E44 -> 0 | AV44: 0 | AW44: =AV44*E44 -> 0 | AX44: 0 | AY44: =AX44*E44 -> 0 | AZ44: 1 | BA44: =AZ44*E44 -> 4500 | BB44: 0 | BC44: =BB44*E44 -> 0 | BD44: 0 | BE44: =BD44*E44 -> 0
A45: UND. MALBORO ROJO | B45: 550 | C45: 550 | D45: 1000 | E45: =D45-C45 -> 450 | F45: 5 | G45: =F45*E45 -> 2250 | H45: 2 | I45: =H45*E45 -> 900 | J45: 0 | K45: =J45*E45 -> 0 | L45: 6 | M45: =L45*E45 -> 2700 | N45: 0 | O45: =N45*E45 -> 0 | P45: 0 | Q45: =P45*E45 -> 0 | R45: 1 | S45: =R45*E45 -> 450 | T45: 0 | U45: =T45*E45 -> 0 | V45: 0 | W45: =V45*E45 -> 0 | X45: 0 | Y45: =X45*E45 -> 0 | Z45: 0 | AA45: =Z45*E45 -> 0 | AB45: 0 | AC45: =AB45*E45 -> 0 | AD45: 2 | AE45: =AD45*E45 -> 900 | AF45: 0 | AG45: =AF45*E45 -> 0 | AH45: 0 | AI45: =AH45*E45 -> 0 | AJ45: 4 | AK45: =AJ45*E45 -> 1800 | AL45: 1 | AM45: =AL45*E45 -> 450 | AN45: 0 | AO45: =AN45*E45 -> 0 | AP45: 0 | AQ45: =AP45*E45 -> 0 | AR45: 5 | AS45: =AR45*E45 -> 2250 | AT45: 0 | AU45: =AT45*E45 -> 0 | AV45: 0 | AW45: =AV45*E45 -> 0 | AX45: 5 | AY45: =AX45*E45 -> 2250 | AZ45: 0 | BA45: =AZ45*E45 -> 0 | BB45: 10 | BC45: =BB45*E45 -> 4500 | BD45: 0 | BE45: =BD45*E45 -> 0
A46: 1/2 MALBORO FUSION | B46: 5900 | C46: 5900 | D46: 10000 | E46: =D46-C46 -> 4100 | F46: 0 | G46: =F46*E46 -> 0 | H46: 0 | I46: =H46*E46 -> 0 | J46: 0 | K46: =J46*E46 -> 0 | L46: 1 | M46: =L46*E46 -> 4100 | N46: 0 | O46: =N46*E46 -> 0 | P46: 0 | Q46: =P46*E46 -> 0 | R46: 0 | S46: =R46*E46 -> 0 | T46: 0 | U46: =T46*E46 -> 0 | V46: 0 | W46: =V46*E46 -> 0 | X46: 0 | Y46: =X46*E46 -> 0 | Z46: 0 | AA46: =Z46*E46 -> 0 | AB46: 0 | AC46: =AB46*E46 -> 0 | AD46: 0 | AE46: =AD46*E46 -> 0 | AF46: 0 | AG46: =AF46*E46 -> 0 | AH46: 1 | AI46: =AH46*E46 -> 4100 | AJ46: 0 | AK46: =AJ46*E46 -> 0 | AL46: 0 | AM46: =AL46*E46 -> 0 | AN46: 0 | AO46: =AN46*E46 -> 0 | AP46: 0 | AQ46: =AP46*E46 -> 0 | AR46: 0 | AS46: =AR46*E46 -> 0 | AT46: 0 | AU46: =AT46*E46 -> 0 | AV46: 0 | AW46: =AV46*E46 -> 0 | AX46: 0 | AY46: =AX46*E46 -> 0 | AZ46: 0 | BA46: =AZ46*E46 -> 0 | BB46: 0 | BC46: =BB46*E46 -> 0 | BD46: 0 | BE46: =BD46*E46 -> 0
A47: UND. MALBORO FUSION | B47: 590 | C47: 590 | D47: 1000 | E47: =D47-C47 -> 410 | F47: 0 | G47: =F47*E47 -> 0 | H47: 0 | I47: =H47*E47 -> 0 | J47: 0 | K47: =J47*E47 -> 0 | L47: 1 | M47: =L47*E47 -> 410 | N47: 0 | O47: =N47*E47 -> 0 | P47: 0 | Q47: =P47*E47 -> 0 | R47: 3 | S47: =R47*E47 -> 1230 | T47: 0 | U47: =T47*E47 -> 0 | V47: 0 | W47: =V47*E47 -> 0 | X47: 0 | Y47: =X47*E47 -> 0 | Z47: 0 | AA47: =Z47*E47 -> 0 | AB47: 0 | AC47: =AB47*E47 -> 0 | AD47: 0 | AE47: =AD47*E47 -> 0 | AF47: 3 | AG47: =AF47*E47 -> 1230 | AH47: 0 | AI47: =AH47*E47 -> 0 | AJ47: 0 | AK47: =AJ47*E47 -> 0 | AL47: 0 | AM47: =AL47*E47 -> 0 | AN47: 0 | AO47: =AN47*E47 -> 0 | AP47: 0 | AQ47: =AP47*E47 -> 0 | AR47: 2 | AS47: =AR47*E47 -> 820 | AT47: 0 | AU47: =AT47*E47 -> 0 | AV47: 0 | AW47: =AV47*E47 -> 0 | AX47: 1 | AY47: =AX47*E47 -> 410 | AZ47: 14 | BA47: =AZ47*E47 -> 5740 | BB47: 0 | BC47: =BB47*E47 -> 0 | BD47: 0 | BE47: =BD47*E47 -> 0
A48: D.P LIMON | B48: 1956 | C48: 1956 | D48: 4000 | E48: =D48-C48 -> 2044 | F48: 0 | G48: =F48*E48 -> 0 | H48: 0 | I48: =H48*E48 -> 0 | J48: 0 | K48: =J48*E48 -> 0 | L48: 3 | M48: =L48*E48 -> 6132 | N48: 1 | O48: =N48*E48 -> 2044 | P48: 0 | Q48: =P48*E48 -> 0 | R48: 0 | S48: =R48*E48 -> 0 | T48: 0 | U48: =T48*E48 -> 0 | V48: 0 | W48: =V48*E48 -> 0 | X48: 0 | Y48: =X48*E48 -> 0 | Z48: 0 | AA48: =Z48*E48 -> 0 | AB48: 2 | AC48: =AB48*E48 -> 4088 | AD48: 1 | AE48: =AD48*E48 -> 2044 | AF48: 1 | AG48: =AF48*E48 -> 2044 | AH48: 0 | AI48: =AH48*E48 -> 0 | AJ48: 0 | AK48: =AJ48*E48 -> 0 | AL48: 0 | AM48: =AL48*E48 -> 0 | AN48: 0 | AO48: =AN48*E48 -> 0 | AP48: 1 | AQ48: =AP48*E48 -> 2044 | AR48: 2 | AS48: =AR48*E48 -> 4088 | AT48: 0 | AU48: =AT48*E48 -> 0 | AV48: 0 | AW48: =AV48*E48 -> 0 | AX48: 0 | AY48: =AX48*E48 -> 0 | AZ48: 3 | BA48: =AZ48*E48 -> 6132 | BB48: 0 | BC48: =BB48*E48 -> 0 | BD48: 3 | BE48: =BD48*E48 -> 6132
A49: D.P BBQ | B49: 1956 | C49: 1956 | D49: 4000 | E49: =D49-C49 -> 2044 | F49: 6 | G49: =F49*E49 -> 12264 | H49: 0 | I49: =H49*E49 -> 0 | J49: 0 | K49: =J49*E49 -> 0 | L49: 0 | M49: =L49*E49 -> 0 | N49: 0 | O49: =N49*E49 -> 0 | P49: 0 | Q49: =P49*E49 -> 0 | R49: 0 | S49: =R49*E49 -> 0 | T49: 0 | U49: =T49*E49 -> 0 | V49: 0 | W49: =V49*E49 -> 0 | X49: 0 | Y49: =X49*E49 -> 0 | Z49: 0 | AA49: =Z49*E49 -> 0 | AB49: 0 | AC49: =AB49*E49 -> 0 | AD49: 2 | AE49: =AD49*E49 -> 4088 | AF49: 0 | AG49: =AF49*E49 -> 0 | AH49: 0 | AI49: =AH49*E49 -> 0 | AJ49: 0 | AK49: =AJ49*E49 -> 0 | AL49: 0 | AM49: =AL49*E49 -> 0 | AN49: 0 | AO49: =AN49*E49 -> 0 | AP49: 1 | AQ49: =AP49*E49 -> 2044 | AR49: 0 | AS49: =AR49*E49 -> 0 | AT49: 2 | AU49: =AT49*E49 -> 4088 | AV49: 0 | AW49: =AV49*E49 -> 0 | AX49: 0 | AY49: =AX49*E49 -> 0 | AZ49: 0 | BA49: =AZ49*E49 -> 0 | BB49: 3 | BC49: =BB49*E49 -> 6132 | BD49: 0 | BE49: =BD49*E49 -> 0
A50: D.P NATURAL | B50: 1956 | C50: 1956 | D50: 4000 | E50: =D50-C50 -> 2044 | F50: 5 | G50: =F50*E50 -> 10220 | H50: 0 | I50: =H50*E50 -> 0 | J50: 1 | K50: =J50*E50 -> 2044 | L50: 2 | M50: =L50*E50 -> 4088 | N50: 2 | O50: =N50*E50 -> 4088 | P50: 0 | Q50: =P50*E50 -> 0 | R50: 0 | S50: =R50*E50 -> 0 | T50: 0 | U50: =T50*E50 -> 0 | V50: 0 | W50: =V50*E50 -> 0 | X50: 1 | Y50: =X50*E50 -> 2044 | Z50: 0 | AA50: =Z50*E50 -> 0 | AB50: 0 | AC50: =AB50*E50 -> 0 | AD50: 1 | AE50: =AD50*E50 -> 2044 | AF50: 0 | AG50: =AF50*E50 -> 0 | AH50: 2 | AI50: =AH50*E50 -> 4088 | AJ50: 0 | AK50: =AJ50*E50 -> 0 | AL50: 0 | AM50: =AL50*E50 -> 0 | AN50: 1 | AO50: =AN50*E50 -> 2044 | AP50: 0 | AQ50: =AP50*E50 -> 0 | AR50: 1 | AS50: =AR50*E50 -> 2044 | AT50: 2 | AU50: =AT50*E50 -> 4088 | AV50: 0 | AW50: =AV50*E50 -> 0 | AX50: 0 | AY50: =AX50*E50 -> 0 | AZ50: 2 | BA50: =AZ50*E50 -> 4088 | BB50: 0 | BC50: =BB50*E50 -> 0 | BD50: 0 | BE50: =BD50*E50 -> 0
A51: D.P MIX | B51: 1956 | C51: 1956 | D51: 4000 | E51: =D51-C51 -> 2044 | F51: 0 | G51: =F51*E51 -> 0 | H51: 0 | I51: =H51*E51 -> 0 | J51: 2 | K51: =J51*E51 -> 4088 | L51: 0 | M51: =L51*E51 -> 0 | N51: 0 | O51: =N51*E51 -> 0 | P51: 0 | Q51: =P51*E51 -> 0 | R51: 0 | S51: =R51*E51 -> 0 | T51: 0 | U51: =T51*E51 -> 0 | V51: 0 | W51: =V51*E51 -> 0 | X51: 0 | Y51: =X51*E51 -> 0 | Z51: 0 | AA51: =Z51*E51 -> 0 | AB51: 0 | AC51: =AB51*E51 -> 0 | AD51: 0 | AE51: =AD51*E51 -> 0 | AF51: 0 | AG51: =AF51*E51 -> 0 | AH51: 0 | AI51: =AH51*E51 -> 0 | AJ51: 0 | AK51: =AJ51*E51 -> 0 | AL51: 0 | AM51: =AL51*E51 -> 0 | AN51: 0 | AO51: =AN51*E51 -> 0 | AP51: 0 | AQ51: =AP51*E51 -> 0 | AR51: 0 | AS51: =AR51*E51 -> 0 | AT51: 0 | AU51: =AT51*E51 -> 0 | AV51: 0 | AW51: =AV51*E51 -> 0 | AX51: 0 | AY51: =AX51*E51 -> 0 | AZ51: 0 | BA51: =AZ51*E51 -> 0 | BB51: 0 | BC51: =BB51*E51 -> 0 | BD51: 0 | BE51: =BD51*E51 -> 0
... A54: BOMBOMBUM | B54: 352 | C54: 352 | D54: 700 | E54: =D54-C54 -> 348 | F54: 0 | G54: =F54*E54 -> 0 | H54: 0 | I54: =H54*E54 -> 0 | J54: 0 | K54: =J54*E54 -> 0 | L54: 0 | M54: =L54*E54 -> 0 | N54: 0 | O54: =N54*E54 -> 0 | P54: 0 | Q54: =P54*E54 -> 0 | R54: 0 | S54: =R54*E54 -> 0 | T54: 0 | U54: =T54*E54 -> 0 | V54: 0 | W54: =V54*E54 -> 0 | X54: 0 | Y54: =X54*E54 -> 0 | Z54: 0 | AA54: =Z54*E54 -> 0 | AB54: 0 | AC54: =AB54*E54 -> 0 | AD54: 0 | AE54: =AD54*E54 -> 0 | AF54: 0 | AG54: =AF54*E54 -> 0 | AH54: 0 | AI54: =AH54*E54 -> 0 | AJ54: 0 | AK54: =AJ54*E54 -> 0 | AL54: 0 | AM54: =AL54*E54 -> 0 | AN54: 0 | AO54: =AN54*E54 -> 0 | AP54: 0 | AQ54: =AP54*E54 -> 0 | AR54: 0 | AS54: =AR54*E54 -> 0 | AT54: 0 | AU54: =AT54*E54 -> 0 | AV54: 0 | AW54: =AV54*E54 -> 0 | AX54: 0 | AY54: =AX54*E54 -> 0 | AZ54: 0 | BA54: =AZ54*E54 -> 0 | BB54: 0 | BC54: =BB54*E54 -> 0 | BD54: 0 | BE54: =BD54*E54 -> 0
A55: BOTELLA AGT. AMARILLO | B55: 60000 | C55: 60000 | D55: 100000 | E55: =D55-C55 -> 40000 | F55: 0 | G55: =F55*E55 -> 0 | H55: 0 | I55: =H55*E55 -> 0 | J55: 0 | K55: =J55*E55 -> 0 | L55: 0 | M55: =L55*E55 -> 0 | N55: 0 | O55: =N55*E55 -> 0 | P55: 0 | Q55: =P55*E55 -> 0 | R55: 0 | S55: =R55*E55 -> 0 | T55: 0 | U55: =T55*E55 -> 0 | V55: 0 | W55: =V55*E55 -> 0 | X55: 0 | Y55: =X55*E55 -> 0 | Z55: 0 | AA55: =Z55*E55 -> 0 | AB55: 0 | AC55: =AB55*E55 -> 0 | AE55: =AD55*E55 -> 0 | AF55: 0 | AG55: =AF55*E55 -> 0 | AH55: 0 | AI55: =AH55*E55 -> 0 | AJ55: 0 | AK55: =AJ55*E55 -> 0 | AL55: 0 | AM55: =AL55*E55 -> 0 | AN55: 0 | AO55: =AN55*E55 -> 0 | AP55: 0 | AQ55: =AP55*E55 -> 0 | AR55: 0 | AS55: =AR55*E55 -> 0 | AT55: 0 | AU55: =AT55*E55 -> 0 | AV55: 0 | AW55: =AV55*E55 -> 0 | AX55: 0 | AY55: =AX55*E55 -> 0 | AZ55: 0 | BA55: =AZ55*E55 -> 0 | BB55: 0 | BC55: =BB55*E55 -> 0 | BD55: 0 | BE55: =BD55*E55 -> 0
G56: =SUM(G2:G55) -> 288524 | I56: =SUM(I2:I55) -> 287966 | K56: =SUM(K2:K55) -> 45540 | M56: =SUM(M2:M55) -> 318121 | O56: =SUM(O2:O55) -> 232450 | Q56: =SUM(Q2:Q55) -> 42213 | S56: =SUM(S2:S55) -> 176188 | U56: =SUM(U2:U55) -> 86655 | W56: =SUM(W2:W55) -> 14389 | Y56: =SUM(Y2:Y55) -> 98386 | AA56: =SUM(AA2:AA55) -> 21538 | AC56: =SUM(AC2:AC55) -> 31962 | AE56: =SUM(AE2:AE55) -> 163463 | AG56: =SUM(AG2:AG55) -> 401526 | AI56: =SUM(AI2:AI55) -> 196598 | AK56: =SUM(AK2:AK55) -> 34481 | AM56: =SUM(AM2:AM55) -> 46110 | AO56: =SUM(AO2:AO55) -> 186902 | AQ56: =SUM(AQ2:AQ55) -> 177233 | AS56: =SUM(AS2:AS55) -> 217165 | AU56: =SUM(AU2:AU55) -> 105572 | AW56: =SUM(AW2:AW55) -> 66914 | AY56: =SUM(AY2:AY55) -> 38852 | BA56: =SUM(BA2:BA55) -> 225852 | BC56: =SUM(BC2:BC55) -> 303588 | BE56: =SUM(BE2:BE55) -> 103067
L57: GANANCIA STELLA | M57: 13666 | Q57: =P57*E57 -> 0 | AG57: 15 pero se cobro el 16 | AH57: smirnoff grande | AI57: 46300 | AK57: =AJ57*G57 -> 0 | AM57: =AL57*I57 -> 0 | AO57: =AN57*K57 -> 0 | AP57: somtig media | AQ57: 3550 | AS57: =AR57*O57 -> 0 | AU57: =AT57*Q57 -> 0 | AW57: =AV57*S57 -> 0 | AY57: =AX57*U57 -> 0 | BA57: =AZ57*W57 -> 0 | BC57: =BB57*Y57 -> 0 | BE57: =BD57*AA57 -> 0
M58: =M56+M57 -> 331787 | Q58: =P58*E58 -> 0 | AI58: =AI56+AI57 -> 242898 | AK58: =AJ58*G58 -> 0 | AM58: =AL58*I58 -> 0 | AO58: =AN58*K58 -> 0 | AQ58: =AQ56+AQ57 -> 180783 | AS58: =AR58*O58 -> 0 | AU58: =AT58*Q58 -> 0 | AW58: =AV58*S58 -> 0 | AY58: =AX58*U58 -> 0 | BA58: =AZ58*W58 -> 0 | BC58: =BB58*Y58 -> 0 | BE58: =BD58*AA58 -> 0

Sheet TABLA DIARIA
A1: FECHA | B1: T. VENTA DIARIA | C1: GANANCIA | D1: TURNO | E1: ARRIENDO | F1: LUZ | G1: AGUA | H1: TOTAL GANANCIA | J1: MIGUEL
A2: 01 ENE 2025
A3: 2 ENE 2025
A4: 3 ENE 2025
A5: 4 ENE 2025
A6: 5 ENE 2025
A7: 6 ENE 2025
A8: 7 ENE 2025
A9: 8 ENE 2025
A10: 9 ENE 2025 | B10: 206800 | C10: 79366 | D10: 55000 | E10: 53225 | F10: 8096 | H10: =C10-D10-E10-F10-G10 -> -36955 | J10: 1 CANADA DRY
A11: 10 ENE 2025 | B11: 489000 | C11: 203342 | D11: 55000 | E11: 53225 | F11: 8096 | H11: =C11-D11-E11-F11-G11 -> 87021 | J11: GASEOSA CUATRO
A12: 11 ENE 2025 | B12: 458000 | C12: 187281 | D12: 55000 | E12: 53225 | F12: 8096 | H12: =C12-D12-E12-F12-G12 -> 70960
A13: 12 ENE 2025 | B13: 1249900 | C13: 573502 | D13: 55000 | E13: 53225 | F13: 8096 | H13: =C13-D13-E13-F13-G13 -> 457181
A14: 13 ENE 2025 | B14: 1814000 | C14: 839727 | D14: 55000 | E14: 53225 | F14: 8096 | H14: =C14-D14-E14-F14-G14 -> 723406
A15: 14 ENE 2025 | B15: 485400 | C15: 188215 | D15: 55000 | E15: 53225 | F15: 8096 | H15: =C15-D15-E15-F15-G15 -> 71894
A16: 15 ENE 2025 | C16: 70055 | E16: 53225 | F16: 8096 | H16: =C16-D16-E16-F16-G16 -> 8734 | J16: 1 CANADA + DT. BBQ
A17: 16 ENE 2025 | B17: 375600 | C17: 152070 | D17: 55000 | E17: 53225 | F17: 8096 | H17: =C17-D17-E17-F17-G17 -> 35749 | J17: 4 LIGTH + 1 COSTEÑA + 1 CORONITA + 1 AGUILA
A18: 17 ENE 2025 | B18: 566000 | C18: 237305 | D18: 55000 | E18: 53225 | F18: 8096 | H18: =C18-D18-E18-F18-G18 -> 120984 | J18: 1 CANADA
A19: 18 ENE 2025 | B19: 883000 | C19: 351378 | D19: 55000 | E19: 53225 | F19: 8096 | H19: =C19-D19-E19-F19-G19 -> 235057
A20: 19 ENE 2025 | B20: 788000 | C20: 334515 | D20: 55000 | E20: 53225 | F20: 8096 | H20: =C20-D20-E20-F20-G20 -> 218194
A21: 20 ENE 2025 | B21: 255000 | C21: 110725 | D21: 55000 | E21: 53225 | F21: 8096 | H21: =C21-D21-E21-F21-G21 -> -5596
A22: 21 ENE 2025 | B22: 610200 | C22: 293166 | D22: 55000 | E22: 53225 | F22: 8096 | H22: =C22-D22-E22-F22-G22 -> 176845 | J22: 2 DT. BBQ
A23: 22 ENE 2025 | B23: 194200 | C23: 73596 | D23: 55000 | E23: 53225 | F23: 8096 | H23: =C23-D23-E23-F23-G23 -> -42725 | J23: 1 CANADA + 2 LUKY + AGUILA
A24: 23 ENE 2025 | B24: 544800 | C24: 241279 | D24: 55000 | E24: 53225 | F24: 8096 | H24: =C24-D24-E24-F24-G24 -> 124958
A25: 24 ENE 2025 | B25: 470600 | C25: 183262 | D25: 55000 | E25: 53225 | F25: 8096 | H25: =C25-D25-E25-F25-G25 -> 66941
A26: 25 ENE 2025 | B26: 1028900 | C26: 478587 | D26: 55000 | E26: 53225 | F26: 8096 | H26: =C26-D26-E26-F26-G26 -> 362266
A27: 26 ENE 2025 | B27: 699100 | C27: 282965 | D27: 50000 | E27: 53225 | F27: 8096 | H27: =C27-D27-E27-F27-G27 -> 171644 | J27: 1 detodito jimena el 31
A28: 27 ENE 2025 | B28: 416400 | C28: 178456 | D28: 55000 | E28: 53225 | F28: 8096 | H28: =C28-D28-E28-F28-G28 -> 62135
A29: 28 ENE 2025 | B29: 245400 | C29: 94018 | D29: 55000 | E29: 53225 | F29: 8096 | H29: =C29-D29-E29-F29-G29 -> -22303 | J29: 1 DT.MIX
A30: 29 ENE 2025 | B30: 275600 | C30: 110569 | D30: 55000 | E30: 53225 | F30: 8096 | H30: =C30-D30-E30-F30-G30 -> -5752 | J30: 1 ELECTROLIT
A31: 30 ENE 2025 | B31: 37200 | C31: 15479 | D31: 55000 | E31: 53225 | F31: 8096 | H31: =C31-D31-E31-F31-G31 -> -100842
A32: 31 ENE 2025 | B32: 406700 | C32: 172730 | D32: 50000 | E32: 53225 | F32: 8096 | H32: =C32-D32-E32-F32-G32 -> 61409
B34: =SUM(B10:B30) -> 12055900 | C34: =SUM(C10:C30) -> 5263379 | D34: =SUM(D10:D30) -> 1095000 | E34: =SUM(E10:E30) -> 1117725 | F34: =SUM(F10:F30) -> 170016 | H34: =SUM(H10:H30) -> 2880638
A37: FECHA | B37: ESTANCO | C37: AGUARDIENTE | D37: PAPAS | E37: CIGARRILOS | F37: OTROS
A38: 45901 | B38: 744000
A39: 45992 | B39: 384000
A40: 13/01/25 | C40: 419400 | E40: 89400
A41: 14/01/25 | B41: 827800 | C41: 482700
A42: 15/01/25 | D42: 41900 | E42: 5800
A43: 16/01/25 | B43: 256000 | E43: 75000 | F43: 7000
A44: 17/01/25 | B44: 244000
A45: 18/01/25 | B45: 286000 | E45: 44400
A46: 19/01/25 | B46: 538000
A47: 20/01/25 | B47: 316000 | C47: 21550 | D47: 41900 | E47: 6800 | F47: 70.000 NEVERA
A48: 22/01/25 | B48: 120000 | C48: 214050 | E48: 13500 | F48: 160.000 LAVAMANOS
A49: 23/01/25 | B49: 254000 | F49: 6500
A50: 24/01/25 | B50: 232000 | E50: 26100
A51: 25/01/25 | B51: 384000 | D51: 25600 | E51: 25600 | F51: 24800 ASEO
A52: 26/01/25 | B52: 496000
A53: 27/01/25 | C53: 43100 | E53: 28700
A54: 28/01/25 | B54: 624000
A55: 29/01/25 | E55: 24800 | F55: 6550
A56: 30/01/25 | B56: 128000 | D56: 16300

Sheet TABLA FEBRERO
A1: FECHA | B1: T. VENTA DIARIA | C1: GANANCIA | D1: TURNO | E1: ARRIENDO | F1: LUZ | G1: INTERNET | H1: YOUTUBE | I1: AGUA | J1: TOTAL GANANCIA | K1: G ADMIN | L1: MIGUEL
A2: 45689 | B2: 709000 | C2: 288524 | D2: 50000 | E2: 58282 | G2: 2857 | H2: 373 | J2: =C2-D2-E2-F2-G2-H2-I2 -> 177012 | K2: =J2*30/100 -> 53103.6
A3: 45690 | B3: 677300 | C3: 287966 | D3: 50000 | E3: 58282 | G3: 2857 | H3: 373 | J3: =C3-D3-E3-F3-G3-H3-I3 -> 176454 | K3: =J3*30/100 -> 52936.2
A4: 45691 | B4: 97100 | C4: 45540 | D4: 50000 | E4: 58282 | G4: 2857 | H4: 373 | J4: =C4-D4-E4-F4-G4-H4-I4 -> -65972 | K4: =J4*30/100 -> -19791.6
A5: 45692 | B5: 798800 | C5: 331787 | D5: 50000 | E5: 58282 | G5: 2857 | H5: 373 | J5: =C5-D5-E5-F5-G5-H5-I5 -> 220275 | K5: =J5*30/100 -> 66082.5
A6: 45693 | E6: 58282 | G6: 2857 | H6: 373 | J6: =C6-D6-E6-F6-G6-H6-I6 -> -61512 | K6: =J6*30/100 -> -18453.6
A7: 45694 | B7: 544600 | C7: 232450 | D7: 50000 | E7: 58282 | G7: 2857 | H7: 373 | J7: =C7-D7-E7-F7-G7-H7-I7 -> 120938 | K7: =J7*30/100 -> 36281.4
A8: 45695 | B8: 114300 | C8: 42213 | D8: 50000 | E8: 58282 | G8: 2857 | H8: 373 | J8: =C8-D8-E8-F8-G8-H8-I8 -> -69299 | K8: =J8*30/100 -> -20789.7
A9: 45696 | B9: 418200 | C9: 178188 | D9: 50000 | E9: 58282 | G9: 2857 | H9: 373 | J9: =C9-D9-E9-F9-G9-H9-I9 -> 66676 | K9: =J9*30/100 -> 20002.8
A10: 45697 | B10: 190200 | C10: 86655 | D10: 50000 | E10: 58282 | G10: 2857 | H10: 373 | J10: =C10-D10-E10-F10-G10-H10-I10 -> -24857 | K10: =J10*30/100 -> -7457.1 | L10: 1 corinta , 1 stella
A11: 45698 | B11: 45200 | C11: 14389 | D11: 50000 | E11: 58282 | G11: 2857 | H11: 373 | J11: =C11-D11-E11-F11-G11-H11-I11 -> -97123 | K11: =J11*30/100 -> -29136.9
A12: 45699 | B12: 254800 | C12: 98386 | D12: 50000 | E12: 58282 | G12: 2857 | H12: 373 | J12: =C12-D12-E12-F12-G12-H12-I12 -> -13126 | K12: =J12*30/100 -> -3937.8
A13: 45700 | B13: 53600 | C13: 21538 | D13: 50000 | E13: 58282 | G13: 2857 | H13: 373 | J13: =C13-D13-E13-F13-G13-H13-I13 -> -89974 | K13: =J13*30/100 -> -26992.2
A14: 45701 | B14: 70400 | C14: 31962 | D14: 50000 | E14: 58282 | G14: 2857 | H14: 373 | J14: =C14-D14-E14-F14-G14-H14-I14 -> -79550 | K14: =J14*30/100 -> -23865
A15: 45702 | B15: 389600 | C15: 163463 | D15: 50000 | E15: 58282 | G15: 2857 | H15: 373 | J15: =C15-D15-E15-F15-G15-H15-I15 -> 51951 | K15: =J15*30/100 -> 15585.3
A16: 45703 | B16: 1044000 | C16: 401526 | D16: 50000 | E16: 58282 | G16: 2857 | H16: 373 | J16: =C16-D16-E16-F16-G16-H16-I16 -> 290014 | K16: =J16*30/100 -> 87004.2
J17: =SUM(J2:J16) -> 601907 | K17: =J17*30/100 -> 180572.1
A19: FECHA | B19: T. VENTA DIARIA | C19: GANANCIA | D19: TURNO | E19: ARRIENDO | F19: LUZ | G19: INTERNET | H19: YOUTUBE | I19: AGUA | J19: TOTAL GANANCIA | K19: G ADMIN
A20: 45704 | B20: 410700 | C20: 242898 | D20: 50000 | E20: 58282 | F20: 17061 | G20: 2857 | H20: 373 | J20: =C20-D20-E20-F20-G20-H20-I20 -> 114325 | K20: =J20*30/100 -> 34297.5
A21: 45705 | D21: 50000 | E21: 58282 | F21: 17061 | G21: 2857 | H21: 373 | J21: =C21-D21-E21-F21-G21-H21-I21 -> -128573 | K21: =J21*30/100 -> -38571.9
A22: 45706 | B22: 91000 | C22: 34481 | D22: 50000 | E22: 58282 | F22: 17061 | G22: 2857 | H22: 373 | J22: =C22-D22-E22-F22-G22-H22-I22 -> -94092 | K22: =J22*30/100 -> -28227.6
A23: 45707 | B23: 117400 | C23: 46110 | D23: 50000 | E23: 58282 | F23: 17061 | G23: 2857 | H23: 373 | J23: =C23-D23-E23-F23-G23-H23-I23 -> -82463 | K23: =J23*30/100 -> -24738.9
A24: 45708 | B24: 451300 | C24: 186902 | D24: 50000 | E24: 58282 | F24: 17061 | G24: 2857 | H24: 373 | J24: =C24-D24-E24-F24-G24-H24-I24 -> 58329 | K24: =J24*30/100 -> 17498.7
A25: 45709 | B25: 471500 | C25: 180783 | D25: 50000 | E25: 58282 | F25: 17061 | G25: 2857 | H25: 373 | J25: =C25-D25-E25-F25-G25-H25-I25 -> 52210 | K25: =J25*30/100 -> 15663
A26: 45710 | B26: 514400 | C26: 217165 | D26: 50000 | E26: 58282 | F26: 17061 | G26: 2857 | H26: 373 | J26: =C26-D26-E26-F26-G26-H26-I26 -> 88592 | K26: =J26*30/100 -> 26577.6
A27: 45711 | B27: 265400 | C27: 105572 | D27: 50000 | E27: 58282 | F27: 17061 | G27: 2857 | H27: 373 | J27: =C27-D27-E27-F27-G27-H27-I27 -> -23001 | K27: =J27*30/100 -> -6900.3
A28: 45712 | B28: 178800 | C28: 66914 | D28: 50000 | E28: 58282 | F28: 17061 | G28: 2857 | H28: 373 | J28: =C28-D28-E28-F28-G28-H28-I28 -> -61659 | K28: =J28*30/100 -> -18497.7
A29: 45713 | B29: 99400 | C29: 38852 | D29: 50000 | E29: 58282 | F29: 17061 | G29: 2857 | H29: 373 | J29: =C29-D29-E29-F29-G29-H29-I29 -> -89721 | K29: =J29*30/100 -> -26916.3
A30: 45714 | B30: 560000 | C30: 225852 | D30: 50000 | E30: 58282 | F30: 17061 | G30: 2857 | H30: 373 | J30: =C30-D30-E30-F30-G30-H30-I30 -> 97279 | K30: =J30*30/100 -> 29183.7
A31: 45715 | B31: 738700 | C31: 303588 | D31: 50000 | E31: 58282 | F31: 17061 | G31: 2857 | H31: 373 | J31: =C31-D31-E31-F31-G31-H31-I31 -> 175015 | K31: =J31*30/100 -> 52504.5
A32: 45716 | B32: 258700 | C32: 103067 | D32: 50000 | E32: 58282 | F32: 17061 | G32: 2857 | H32: 373 | J32: =C32-D32-E32-F32-G32-H32-I32 -> -25506 | K32: =J32*30/100 -> -7651.8
J33: =SUM(J20:J32) -> 80735 | K33: =SUM(K20:K32) -> 24220.5

Sheet Hoja1

Sheet INVENTARIO MAR
A1: INVENTARIO
A2: PRODUCTO | B2: 01/03/25 INICIA | C2: 01/03/25 ENTRA | D2: 01/03/25 SALE | E2: 02/03/25 UNICIA | F2: 02/03/25 ENTRA | G2: 02/03/25 SALE | H2: 03/03/25 UNICIA | I2: 03/03/25 ENTRA | J2: 03/03/25 SALE | K2: 04/03/25 UNICIA | L2: 04/03/25 ENTRA | M2: 04/03/25 SALE | N2: 05/03/25 UNICIA | O2: 05/03/25 ENTRA | P2: 05/03/25 SALE | Q2: 06/03/25 UNICIA | R2: 06/03/25 ENTRA | S2: 06/03/25 SALE | T2: 07/03/25 UNICIA | U2: 07/03/25 ENTRA | V2: 07/03/25 SALE | W2: 08/03/25 UNICIA | X2: 08/03/25 ENTRA | Y2: 08/03/25 SALE | Z2: 09/03/25 UNICIA | AA2: 09/03/25 ENTRA | AB2: 09/03/25 SALE | AC2: 10/03/25 UNICIA | AD2: 10/03/25 ENTRA | AE2: 10/03/25 SALE | AF2: 11/03/25 UNICIA | AG2: 11/03/25 ENTRA | AH2: 11/03/25 SALE | AI2: 12/03/25 UNICIA | AJ2: 12/03/25 ENTRA | AK2: 12/03/25 SALE | AL2: 13/03/25 UNICIA | AM2: 13/03/25 ENTRA | AN2: 13/03/25 SALE | AO2: 14/03/25 UNICIA | AP2: 14/03/25 ENTRA | AQ2: 14/03/25 SALE | AR2: 15/03/25 UNICIA | AS2: 15/03/25 ENTRO | AT2: 15/03/25 SALIO | AU2: 16/03/25 INICIA | AV2: 16/03/25 ENTRO | AW2: 16/03/25 SALIO | AX2: 17/03/25 INICIA | AY2: 17/03/25 ENTRO | AZ2: 17/03/25 SALIO | BA2: 18/03/25 INICIA | BB2: 18/03/25 ENTRO | BC2: 18/03/25 SALIO | BD2: 19/03/25 INICIA | BE2: 19/03/25 ENTRO | BF2: 19/03/25 SALIO | BG2: 20/03/25 INICIA | BH2: 20/03/25 ENTRO | BI2: 20/03/25 SALIO | BJ2: 21/03/25 INICIA | BK2: 21/03/25 ENTRO | BL2: 21/03/25 SALIO | BM2: 22/03/25 INICIA | BN2: 22/03/25 ENTRO | BO2: 22/03/25 SALIO | BP2: 23/03/25 INICIA | BQ2: 23/03/25 ENTRO | BR2: 23/03/25 SALIO | BS2: 24/03/25 INICIA | BT2: 24/03/25 ENTRO | BU2: 24/03/25 SALIO | BV2: 25/03/25 INICIA | BW2: 25/03/25 ENTRO | BX2: 25/03/25 SALIO | BY2: 26/03/25 INICIA | BZ2: 26/03/25 ENTRO | CA2: 26/03/25 SALIO | CB2: 27/03/25 INICIA | CC2: 27/03/25 ENTRO | CD2: 27/03/25 SALIO | CE2: 28/03/25 INICIA | CF2: 28/03/25 INICIA | CG2: 28/03/25 INICIA | CH2: 29/03/25 INICIA | CI2: 29/03/25 ENTRO | CJ2: 29/03/25 SALIO | CK2: 30/03/25 INICIA | CL2: 30/03/25 ENTRO | CM2: 30/03/25 SALIO | CN2: 31/03/25 INICIA | CO2: 31/03/25 ENTRO | CP2: 31/03/25 SALIO | CQ2: 01/04/25 INICIA | CR2: 01/04/25ENTRO | CS2: 01/04/25 SALIO | CT2: 02-04-25INICIA | CU2: ENTRA 02/04/25 | CV2: SALIO 02/04/ | CW2: 03/04/25INICIA | CX2: 03/04 ENTRO | CY2: 03/04/SALIO | CZ2: 04/04/INICIA | DA2: 4/ 4ENTRA | DB2: 04/04/25SALIO | DC2: 05/04/25INICIA | DD2: 05/04/25 ENTRA | DE2: 05/04/25SALIO | DF2: 06/05/25INICIA | DG2: 06/04/2025ENTRA | DH2: 06/04/202SALIO | DI2: 07/04/2025 INICIA | DJ2: 07/04/2025 ENTRA | DK2: 07/04SALE | DL2: 08/04/202INICIO | DM2: 08/04/25ENTRA | DN2: 08/04/25SALIO | DO2: 09/04/25INICIA | DP2: 09/04/25 ENTRA | DQ2: 09/04/25 SALIO | DR2: 10/04/25 INICIA | DS2: 10/04/ENTRADA | DT2: 10/04/SALIO | DU2: 1104/INICIA | DV2: 11/04 ENTRA | DW2: 11/04 SALIO | DX2: 12/04 INICIA | DY2: 12/04ENTRA | DZ2: 12/04SALE | EA2: 13/04INICIA | EB2: 13/04ENTRA | EC2: 13/04SALE | ED2: 14/04INICIA | EE2: 14/04 ENTRA | EF2: 14/04SALIO | EG2: 15/04INICIA | EH2: 15/04IENTRA | EI2: 15/04I SALE | EJ2: 16/04IINICIA | EK2: 16/04ENTRA | EL2: 16/04SALE | EM2: 17/04 INICIO | EN2: 17/04 ENTRA | EO2: 17/04SALE | EP2: 19/04 INICIA | EQ2: 19/04 ENTRA | ER2: 19/04 SALE | ES2: 20/04 INICIA | ET2: 20/04/2025 ENTRA | EU2: 20/04/2025SALE | EV2: 21/04/25 INICIA | EW2: 21/04/25 ENTRA | EX2: 21/04 SALIO | EY2: 22/ INICIA | EZ2: 22/ ENTRA | FA2: 22/ SALIO | FB2: 23/INICIA | FC2: 23/ ENTRA | FD2: 23/ SALIO | FE2: 24/INICA | FF2: 24/ENTRA | FG2: 24/ SALIO | FH2: 25/INICIA | FI2: 25/ ENTRA | FJ2: 25 SALE | FK2: 27 INICIO | FL2: 27/ ENTRA | FM2: 27/ SALIO | FN2: 28/ INICIA | FO2: 28/ ENTRA | FP2: 28/ SALIO | FQ2: 29/ INICIA | FR2: 29/ ENTRA | FS2: 29/ SALIO | FT2: 30/ INICIA | FU2: 30/ ENTRA | FV2: 30/ SALIO | FW2: INICIA 01/05
A3: AGUA X24 | B3: ='INV. FEB'!BX3 -> 14 | C3: 0 | D3: 1 | E3: =B3+C3-D3 -> 13 | F3: 0 | G3: 0 | H3: =E3+F3-G3 -> 13 | I3: 0 | J3: 0 | K3: =H3+I3-J3 -> 13 | L3: 0 | M3: 0 | N3: =K3+L3-M3 -> 13 | O3: 0 | P3: 0 | Q3: =N3+O3-P3 -> 13 | R3: 0 | S3: 2 | T3: =Q3+R3-S3 -> 11 | U3: 0 | V3: 1 | W3: =T3+U3-V3 -> 10 | X3: 0 | Y3: 6 | Z3: =W3+X3-Y3 -> 4 | AA3: 0 | AB3: 0 | AC3: =Z3+AA3-AB3 -> 4 | AD3: 24 | AE3: 0 | AF3: =AC3+AD3-AE3 -> 28 | AG3: 0 | AH3: 1 | AI3: =AF3+AG3-AH3 -> 27 | AJ3: 0 | AK3: 0 | AL3: =AI3+AJ3-AK3 -> 27 | AM3: 0 | AN3: 2 | AO3: =AL3+AM3-AN3 -> 25 | AP3: 0 | AQ3: 0 | AR3: =AO3+AP3-AQ3 -> 25 | AS3: 0 | AT3: 0 | AU3: =AR3+AS3-AT3 -> 25 | AV3: 0 | AW3: 0 | AX3: =AU3+AV3-AW3 -> 25 | AY3: 0 | AZ3: 0 | BA3: =AX3+AY3-AZ3 -> 25 | BB3: 0 | BC3: 0 | BD3: =BA3+BB3-BC3 -> 25 | BE3: 0 | BF3: 0 | BG3: =BD3+BE3-BF3 -> 25 | BH3: 0 | BI3: 3 | BJ3: =BG3+BH3-BI3 -> 22 | BK3: 0 | BL3: 0 | BM3: =BJ3+BK3-BL3 -> 22 | BN3: 0 | BO3: 0 | BP3: =BM3+BN3-BO3 -> 22 | BQ3: 0 | BR3: 2 | BS3: =BP3+BQ3-BR3 -> 20 | BT3: 0 | BU3: 4 | BV3: =BS3+BT3-BU3 -> 16 | BW3: 0 | BX3: 3 | BY3: =BV3+BW3-BX3 -> 13 | BZ3: 0 | CA3: 0 | CB3: =BY3+BZ3-CA3 -> 13 | CC3: 0 | CD3: 0 | CE3: =CB3+CC3-CD3 -> 13 | CF3: 0 | CG3: 0 | CH3: =CE3+CF3-CG3 -> 13 | CI3: 0 | CJ3: 0 | CK3: =CH3+CI3-CJ3 -> 13 | CL3: 0 | CM3: 1 | CN3: =CK3+CL3-CM3 -> 12 | CO3: 0 | CP3: 0 | CQ3: =CN3+CO3-CP3 -> 12 | CR3: 0 | CS3: 0 | CT3: =CQ3+CR3-CS3 -> 12 | CU3: 0 | CV3: 0 | CW3: =CT3+CU3-CU3 -> 12 | CX3: 0 | CY3: 0 | CZ3: 12 | DC3: =CZ3+DA3-DB3 -> 12 | DF3: =DC3+DD3-DE3 -> 12 | DI3: =DF3+DG3-DH3 -> 12 | DL3: =DI3+DJ3-DK3 -> 12 | DO3: =DL3+DM3-DN3 -> 12 | DR3: =DO3+DP3-DQ3 -> 12 | DU3: =DR3+DS3-DT3 -> 12 | DX3: =DU3+DV3-DW3 -> 12 | EA3: =DX3+DY3-DZ3 -> 12 | EC3: 4 | ED3: =EA3+EB3-EC3 -> 8 | EG3: =ED3+EE3-EF3 -> 8 | EI3: 5 | EJ3: =EG3+EH3-EI3 -> 3 | EK3: 12 | EM3: =EJ3+EK3-EL3 -> 15 | EO3: 2 | EP3: =EM3+EN3-EO3 -> 13 | ER3: 3 | ES3: =EP3+EQ3-ER3 -> 10 | EU3: 4 | EV3: =ES3+ET3-EU3 -> 6 | EY3: =EV3+EW3-EX3 -> 6 | FA3: 1 | FB3: =EY3+EZ3-FA3 -> 5 | FE3: =FB3+FC3-FD3 -> 5 | FH3: =FE3+FF3-FG3 -> 5 | FK3: =FH3+FI3-FJ3 -> 5 | FN3: =FK3+FL3-FM3 -> 5 | FQ3: =FN3+FO3-FP3 -> 5 | FT3: =FQ3+FR3-FS3 -> 5 | FW3: =FT3+FU3-FV3 -> 5
A4: COCA COLA | B4: ='INV. FEB'!BX4 -> 12 | C4: 0 | D4: 0 | E4: =B4+C4-D4 -> 12 | F4: 0 | G4: 1 | H4: =E4+F4-G4 -> 11 | I4: 0 | J4: 0 | K4: =H4+I4-J4 -> 11 | L4: 0 | M4: 1 | N4: =K4+L4-M4 -> 10 | O4: 0 | P4: 0 | Q4: =N4+O4-P4 -> 10 | R4: 0 | S4: 0 | T4: =Q4+R4-S4 -> 10 | U4: 0 | V4: 1 | W4: =T4+U4-V4 -> 9 | X4: 0 | Y4: 0 | Z4: =W4+X4-Y4 -> 9 | AA4: 0 | AB4: 1 | AC4: =Z4+AA4-AB4 -> 8 | AD4: 0 | AE4: 0 | AF4: =AC4+AD4-AE4 -> 8 | AG4: 0 | AH4: 1 | AI4: =AF4+AG4-AH4 -> 7 | AJ4: 0 | AK4: 1 | AL4: =AI4+AJ4-AK4 -> 6 | AM4: 0 | AN4: 0 | AO4: =AL4+AM4-AN4 -> 6 | AP4: 0 | AQ4: 0 | AR4: =AO4+AP4-AQ4 -> 6 | AS4: 0 | AT4: 0 | AU4: =AR4+AS4-AT4 -> 6 | AV4: 0 | AW4: 0 | AX4: =AU4+AV4-AW4 -> 6 | AY4: 0 | AZ4: 2 | BA4: =AX4+AY4-AZ4 -> 4 | BB4: 0 | BC4: 1 | BD4: =BA4+BB4-BC4 -> 3 | BE4: 0 | BF4: 1 | BG4: =BD4+BE4-BF4 -> 2 | BH4: 0 | BI4: 0 | BJ4: =BG4+BH4-BI4 -> 2 | BK4: 0 | BL4: 1 | BM4: =BJ4+BK4-BL4 -> 1 | BN4: 0 | BO4: 0 | BP4: =BM4+BN4-BO4 -> 1 | BQ4: 0 | BR4: 0 | BS4: =BP4+BQ4-BR4 -> 1 | BT4: 0 | BU4: 1 | BV4: =BS4+BT4-BU4 -> 0 | BW4: 12 | BX4: 1 | BY4: =BV4+BW4-BX4 -> 11 | BZ4: 0 | CA4: 1 | CB4: =BY4+BZ4-CA4 -> 10 | CC4: 0 | CD4: 0 | CE4: =CB4+CC4-CD4 -> 10 | CF4: 0 | CG4: 0 | CH4: =CE4+CF4-CG4 -> 10 | CI4: 0 | CJ4: 0 | CK4: =CH4+CI4-CJ4 -> 10 | CL4: 0 | CM4: 0 | CN4: =CK4+CL4-CM4 -> 10 | CO4: 0 | CP4: 0 | CQ4: 7 | CR4: 0 | CS4: 0 | CT4: 9 | CU4: 0 | CV4: 1 | CW4: =CT4+CU4-CV4 -> 8 | CZ4: =CW4+CX4-CY4 -> 8 | DC4: =CZ4+DA4-DB4 -> 8 | DF4: =DC4+DD4-DE4 -> 8 | DH4: 1 | DI4: =DF4+DG4-DH4 -> 7 | DL4: =DI4+DJ4-DK4 -> 7 | DN4: 2 | DO4: =DL4+DM4-DN4 -> 5 | DR4: =DO4+DP4-DQ4 -> 5 | DU4: =DR4+DS4-DT4 -> 5 | DX4: =DU4+DV4-DW4 -> 5 | DY4: 12 | DZ4: 4 | EA4: =DX4+DY4-DZ4 -> 13 | EB4: 12 | EC4: 4 | ED4: =EA4+EB4-EC4 -> 21 | EG4: =ED4+EE4-EF4 -> 21 | EJ4: =EG4+EH4-EI4 -> 21 | EM4: =EJ4+EK4-EL4 -> 21 | EO4: 2 | EP4: =EM4+EN4-EO4 -> 19 | ER4: 2 | ES4: =EP4+EQ4-ER4 -> 17 | EV4: =ES4+ET4-EU4 -> 17 | EY4: =EV4+EW4-EX4 -> 17 | FA4: 1 | FB4: =EY4+EZ4-FA4 -> 16 | FE4: =FB4+FC4-FD4 -> 16 | FH4: =FE4+FF4-FG4 -> 16 | FK4: =FH4+FI4-FJ4 -> 16 | FN4: =FK4+FL4-FM4 -> 16 | FQ4: =FN4+FO4-FP4 -> 16 | FT4: =FQ4+FR4-FS4 -> 16 | FW4: =FT4+FU4-FV4 -> 16
A5: GATORADE | B5: ='INV. FEB'!BX5 -> 14 | C5: 0 | D5: 1 | E5: =B5+C5-D5 -> 13 | F5: 0 | G5: 0 | H5: =E5+F5-G5 -> 13 | I5: 0 | J5: 0 | K5: =H5+I5-J5 -> 13 | L5: 0 | M5: 0 | N5: =K5+L5-M5 -> 13 | O5: 0 | P5: 0 | Q5: =N5+O5-P5 -> 13 | R5: 0 | S5: 0 | T5: =Q5+R5-S5 -> 13 | U5: 0 | V5: 0 | W5: =T5+U5-V5 -> 13 | X5: 0 | Y5: 0 | Z5: =W5+X5-Y5 -> 13 | AA5: 0 | AB5: 0 | AC5: =Z5+AA5-AB5 -> 13 | AD5: 0 | AE5: 0 | AF5: =AC5+AD5-AE5 -> 13 | AG5: 0 | AH5: 0 | AI5: =AF5+AG5-AH5 -> 13 | AJ5: 0 | AK5: 0 | AL5: =AI5+AJ5-AK5 -> 13 | AM5: 0 | AN5: 0 | AO5: =AL5+AM5-AN5 -> 13 | AP5: 0 | AQ5: 0 | AR5: =AO5+AP5-AQ5 -> 13 | AS5: 0 | AT5: 1 | AU5: =AR5+AS5-AT5 -> 12 | AV5: 0 | AW5: 0 | AX5: =AU5+AV5-AW5 -> 12 | AY5: 0 | AZ5: 6 | BA5: =AX5+AY5-AZ5 -> 6 | BB5: 0 | BC5: 1 | BD5: =BA5+BB5-BC5 -> 5 | BE5: 0 | BF5: 1 | BG5: =BD5+BE5-BF5 -> 4 | BH5: 0 | BI5: 1 | BJ5: =BG5+BH5-BI5 -> 3 | BK5: 0 | BL5: 0 | BM5: =BJ5+BK5-BL5 -> 3 | BN5: 0 | BO5: 0 | BP5: =BM5+BN5-BO5 -> 3 | BQ5: 0 | BR5: 2 | BS5: =BP5+BQ5-BR5 -> 1 | BT5: 0 | BU5: 3 | BV5: =BS5+BT5-BU5 -> -2 | BW5: 12 | BX5: 1 | BY5: =BV5+BW5-BX5 -> 9 | BZ5: 0 | CA5: 0 | CB5: =BY5+BZ5-CA5 -> 9 | CC5: 0 | CD5: 0 | CE5: =CB5+CC5-CD5 -> 9 | CF5: 0 | CG5: 0 | CH5: =CE5+CF5-CG5 -> 9 | CI5: 0 | CJ5: 0 | CK5: =CH5+CI5-CJ5 -> 9 | CL5: 0 | CM5: 2 | CN5: =CK5+CL5-CM5 -> 7 | CO5: 0 | CP5: 0 | CQ5: =CN5+CO5-CP5 -> 7 | CR5: 0 | CS5: 0 | CT5: 6 | CU5: 0 | CV5: 0 | CW5: =CT5+CU5-CV5 -> 6 | CZ5: =CW5+CX5-CY5 -> 6 | DC5: =CZ5+DA5-DB5 -> 6 | DF5: =DC5+DD5-DE5 -> 6 | DH5: 1 | DI5: =DF5+DG5-DH5 -> 5 | DJ5: 12 | DK5: 2 | DL5: =DI5+DJ5-DK5 -> 15 | DN5: 1 | DO5: =DL5+DM5-DN5 -> 14 | DQ5: 2 | DR5: =DO5+DP5-DQ5 -> 12 | DT5: 1 | DU5: =DR5+DS5-DT5 -> 11 | DX5: =DU5+DV5-DW5 -> 11 | EA5: =DX5+DY5-DZ5 -> 11 | ED5: =EA5+EB5-EC5 -> 11 | EG5: =ED5+EE5-EF5 -> 11 | EJ5: =EG5+EH5-EI5 -> 11 | EM5: =EJ5+EK5-EL5 -> 11 | EP5: =EM5+EN5-EO5 -> 11 | ER5: 2 | ES5: =EP5+EQ5-ER5 -> 9 | EV5: =ES5+ET5-EU5 -> 9 | EX5: 1 | EY5: =EV5+EW5-EX5 -> 8 | FB5: =EY5+EZ5-FA5 -> 8 | FE5: =FB5+FC5-FD5 -> 8 | FH5: =FE5+FF5-FG5 -> 8 | FK5: =FH5+FI5-FJ5 -> 8 | FN5: =FK5+FL5-FM5 -> 8 | FQ5: =FN5+FO5-FP5 -> 8 | FT5: =FQ5+FR5-FS5 -> 8 | FW5: =FT5+FU5-FV5 -> 8
A6: SMIRNOFF | B6: ='INV. FEB'!BX6 -> 3 | C6: 0 | D6: 2 | E6: =B6+C6-D6 -> 1 | F6: 0 | G6: 0 | H6: =E6+F6-G6 -> 1 | I6: 3 | J6: 0 | K6: =H6+I6-J6 -> 4 | L6: 0 | M6: 0 | N6: =K6+L6-M6 -> 4 | O6: 0 | P6: 0 | Q6: =N6+O6-P6 -> 4 | R6: 0 | S6: 0 | T6: =Q6+R6-S6 -> 4 | U6: 0 | V6: 0 | W6: =T6+U6-V6 -> 4 | X6: 0 | Y6: 0 | Z6: =W6+X6-Y6 -> 4 | AA6: 0 | AB6: 0 | AC6: =Z6+AA6-AB6 -> 4 | AD6: 0 | AE6: 0 | AF6: =AC6+AD6-AE6 -> 4 | AG6: 0 | AH6: 0 | AI6: =AF6+AG6-AH6 -> 4 | AJ6: 0 | AK6: 0 | AL6: =AI6+AJ6-AK6 -> 4 | AM6: 0 | AN6: 0 | AO6: =AL6+AM6-AN6 -> 4 | AP6: 0 | AQ6: 0 | AR6: =AO6+AP6-AQ6 -> 4 | AS6: 0 | AT6: 1 | AU6: =AR6+AS6-AT6 -> 3 | AV6: 0 | AW6: 0 | AX6: =AU6+AV6-AW6 -> 3 | AY6: 0 | AZ6: 0 | BA6: =AX6+AY6-AZ6 -> 3 | BB6: 0 | BC6: 0 | BD6: =BA6+BB6-BC6 -> 3 | BE6: 0 | BF6: 0 | BG6: =BD6+BE6-BF6 -> 3 | BH6: 0 | BI6: 0 | BJ6: =BG6+BH6-BI6 -> 3 | BK6: 0 | BL6: 0 | BM6: =BJ6+BK6-BL6 -> 3 | BN6: 0 | BO6: 0 | BP6: =BM6+BN6-BO6 -> 3 | BQ6: 0 | BR6: 0 | BS6: =BP6+BQ6-BR6 -> 3 | BT6: 0 | BU6: 0 | BV6: =BS6+BT6-BU6 -> 3 | BW6: 0 | BX6: 3 | BY6: =BV6+BW6-BX6 -> 0 | BZ6: 3 | CA6: 0 | CB6: =BY6+BZ6-CA6 -> 3 | CC6: 0 | CD6: 0 | CE6: 3 | CF6: 0 | CG6: 0 | CH6: =CE6+CF6-CG6 -> 3 | CI6: 0 | CJ6: 0 | CK6: =CH6+CI6-CJ6 -> 3 | CL6: 0 | CM6: 0 | CN6: =CK6+CL6-CM6 -> 3 | CO6: 0 | CP6: 0 | CQ6: =CN6+CO6-CP6 -> 3 | CR6: 0 | CS6: 0 | CT6: =CQ6+CR6-CS6 -> 3 | CU6: 0 | CV6: 0 | CW6: =CT6+CU6-CV6 -> 3 | CZ6: =CW6+CX6-CY6 -> 3 | DC6: =CZ6+DA6-DB6 -> 3 | DF6: =DC6+DD6-DE6 -> 3 | DI6: =DF6+DG6-DH6 -> 3 | DL6: =DI6+DJ6-DK6 -> 3 | DO6: =DL6+DM6-DN6 -> 3 | DR6: =DO6+DP6-DQ6 -> 3 | DU6: =DR6+DS6-DT6 -> 3 | DX6: =DU6+DV6-DW6 -> 3 | EA6: =DX6+DY6-DZ6 -> 3 | ED6: =EA6+EB6-EC6 -> 3 | EG6: =ED6+EE6-EF6 -> 3 | EJ6: =EG6+EH6-EI6 -> 3 | EM6: =EJ6+EK6-EL6 -> 3 | EP6: =EM6+EN6-EO6 -> 3 | ES6: =EP6+EQ6-ER6 -> 3 | EV6: =ES6+ET6-EU6 -> 3 | EY6: =EV6+EW6-EX6 -> 3 | FB6: =EY6+EZ6-FA6 -> 3 | FE6: =FB6+FC6-FD6 -> 3 | FH6: =FE6+FF6-FG6 -> 3 | FK6: =FH6+FI6-FJ6 -> 3 | FN6: =FK6+FL6-FM6 -> 3 | FQ6: =FN6+FO6-FP6 -> 3 | FT6: =FQ6+FR6-FS6 -> 3 | FW6: =FT6+FU6-FV6 -> 3
A7: GASEOSA CUATRO | B7: ='INV. FEB'!BX7 -> 1 | C7: 0 | D7: 0 | E7: =B7+C7-D7 -> 1 | F7: 0 | G7: 0 | H7: =E7+F7-G7 -> 1 | I7: 0 | J7: 0 | K7: =H7+I7-J7 -> 1 | L7: 0 | M7: 0 | N7: =K7+L7-M7 -> 1 | O7: 0 | P7: 0 | Q7: =N7+O7-P7 -> 1 | R7: 0 | S7: 0 | T7: =Q7+R7-S7 -> 1 | U7: 0 | V7: 0 | W7: =T7+U7-V7 -> 1 | X7: 0 | Y7: 0 | Z7: =W7+X7-Y7 -> 1 | AA7: 0 | AB7: 0 | AC7: =Z7+AA7-AB7 -> 1 | AD7: 0 | AE7: 0 | AF7: =AC7+AD7-AE7 -> 1 | AG7: 0 | AH7: 0 | AI7: =AF7+AG7-AH7 -> 1 | AJ7: 0 | AK7: 0 | AL7: =AI7+AJ7-AK7 -> 1 | AM7: 0 | AN7: 0 | AO7: =AL7+AM7-AN7 -> 1 | AP7: 0 | AQ7: 0 | AR7: =AO7+AP7-AQ7 -> 1 | AS7: 0 | AT7: 0 | AU7: =AR7+AS7-AT7 -> 1 | AV7: 0 | AW7: 0 | AX7: =AU7+AV7-AW7 -> 1 | AY7: 0 | AZ7: 0 | BA7: =AX7+AY7-AZ7 -> 1 | BB7: 0 | BC7: 0 | BD7: =BA7+BB7-BC7 -> 1 | BE7: 0 | BF7: 0 | BG7: =BD7+BE7-BF7 -> 1 | BH7: 0 | BI7: 0 | BJ7: =BG7+BH7-BI7 -> 1 | BK7: 0 | BL7: 0 | BM7: =BJ7+BK7-BL7 -> 1 | BN7: 0 | BO7: 0 | BP7: =BM7+BN7-BO7 -> 1 | BQ7: 0 | BR7: 0 | BS7: =BP7+BQ7-BR7 -> 1 | BT7: 0 | BU7: 0 | BV7: =BS7+BT7-BU7 -> 1 | BW7: 0 | BX7: 0 | BY7: =BV7+BW7-BX7 -> 1 | BZ7: 0 | CA7: 0 | CB7: =BY7+BZ7-CA7 -> 1 | CC7: 0 | CD7: 0 | CE7: 1 | CF7: 0 | CG7: 0 | CH7: =CE7+CF7-CG7 -> 1 | CI7: 0 | CJ7: 0 | CK7: =CH7+CI7-CJ7 -> 1 | CL7: 0 | CM7: 0 | CN7: =CK7+CL7-CM7 -> 1 | CO7: 0 | CP7: 0 | CQ7: =CN7+CO7-CP7 -> 1 | CR7: 0 | CS7: 0 | CT7: =CQ7+CR7-CS7 -> 1 | CU7: 0 | CV7: 0 | CW7: =CT7+CU7-CV7 -> 1 | CZ7: =CW7+CX7-CY7 -> 1 | DC7: =CZ7+DA7-DB7 -> 1 | DF7: =DC7+DD7-DE7 -> 1 | DI7: =DF7+DG7-DH7 -> 1 | DL7: =DI7+DJ7-DK7 -> 1 | DO7: =DL7+DM7-DN7 -> 1 | DR7: =DO7+DP7-DQ7 -> 1 | DU7: =DR7+DS7-DT7 -> 1 | DX7: =DU7+DV7-DW7 -> 1 | EA7: =DX7+DY7-DZ7 -> 1 | ED7: =EA7+EB7-EC7 -> 1 | EG7: =ED7+EE7-EF7 -> 1 | EJ7: =EG7+EH7-EI7 -> 1 | EM7: =EJ7+EK7-EL7 -> 1 | EP7: =EM7+EN7-EO7 -> 1 | ES7: =EP7+EQ7-ER7 -> 1 | EV7: =ES7+ET7-EU7 -> 1 | EY7: =EV7+EW7-EX7 -> 1 | FB7: =EY7+EZ7-FA7 -> 1 | FE7: =FB7+FC7-FD7 -> 1 | FH7: =FE7+FF7-FG7 -> 1 | FK7: =FH7+FI7-FJ7 -> 1 | FN7: =FK7+FL7-FM7 -> 1 | FQ7: =FN7+FO7-FP7 -> 1 | FT7: =FQ7+FR7-FS7 -> 1 | FW7: =FT7+FU7-FV7 -> 1
A8: GASEOSA CANADA DRY | B8: ='INV. FEB'!BX8 -> 4 | C8: 0 | D8: 0 | E8: =B8+C8-D8 -> 4 | F8: 0 | G8: 0 | H8: =E8+F8-G8 -> 4 | I8: 0 | J8: 0 | K8: =H8+I8-J8 -> 4 | L8: 0 | M8: 0 | N8: =K8+L8-M8 -> 4 | O8: 0 | P8: 0 | Q8: =N8+O8-P8 -> 4 | R8: 0 | S8: 0 | T8: =Q8+R8-S8 -> 4 | U8: 0 | V8: 0 | W8: =T8+U8-V8 -> 4 | X8: 0 | Y8: 0 | Z8: =W8+X8-Y8 -> 4 | AA8: 0 | AB8: 0 | AC8: =Z8+AA8-AB8 -> 4 | AD8: 0 | AE8: 0 | AF8: =AC8+AD8-AE8 -> 4 | AG8: 0 | AH8: 0 | AI8: =AF8+AG8-AH8 -> 4 | AJ8: 0 | AK8: 0 | AL8: =AI8+AJ8-AK8 -> 4 | AM8: 0 | AN8: 0 | AO8: =AL8+AM8-AN8 -> 4 | AP8: 0 | AQ8: 0 | AR8: =AO8+AP8-AQ8 -> 4 | AS8: 0 | AT8: 0 | AU8: =AR8+AS8-AT8 -> 4 | AV8: 0 | AW8: 0 | AX8: =AU8+AV8-AW8 -> 4 | AY8: 0 | AZ8: 0 | BA8: =AX8+AY8-AZ8 -> 4 | BB8: 0 | BC8: 0 | BD8: =BA8+BB8-BC8 -> 4 | BE8: 0 | BF8: 0 | BG8: =BD8+BE8-BF8 -> 4 | BH8: 0 | BI8: 0 | BJ8: =BG8+BH8-BI8 -> 4 | BK8: 0 | BL8: 0 | BM8: =BJ8+BK8-BL8 -> 4 | BN8: 0 | BO8: 0 | BP8: =BM8+BN8-BO8 -> 4 | BQ8: 0 | BR8: 0 | BS8: =BP8+BQ8-BR8 -> 4 | BT8: 0 | BU8: 0 | BV8: =BS8+BT8-BU8 -> 4 | BW8: 0 | BX8: 0 | BY8: =BV8+BW8-BX8 -> 4 | BZ8: 0 | CA8: 0 | CB8: =BY8+BZ8-CA8 -> 4 | CC8: 0 | CD8: 0 | CE8: 4 | CF8: 0 | CG8: 0 | CH8: =CE8+CF8-CG8 -> 4 | CI8: 0 | CJ8: 0 | CK8: =CH8+CI8-CJ8 -> 4 | CL8: 0 | CM8: 0 | CN8: =CK8+CL8-CM8 -> 4 | CO8: 0 | CP8: 0 | CQ8: =CN8+CO8-CP8 -> 4 | CR8: 0 | CS8: 0 | CT8: =CQ8+CR8-CS8 -> 4 | CU8: 0 | CV8: 0 | CW8: =CT8+CU8-CV8 -> 4 | CZ8: =CW8+CX8-CY8 -> 4 | DC8: =CZ8+DA8-DB8 -> 4 | DF8: =DC8+DD8-DE8 -> 4 | DI8: =DF8+DG8-DH8 -> 4 | DL8: =DI8+DJ8-DK8 -> 4 | DO8: =DL8+DM8-DN8 -> 4 | DR8: =DO8+DP8-DQ8 -> 4 | DU8: =DR8+DS8-DT8 -> 4 | DX8: =DU8+DV8-DW8 -> 4 | EA8: =DX8+DY8-DZ8 -> 4 | ED8: =EA8+EB8-EC8 -> 4 | EG8: =ED8+EE8-EF8 -> 4 | EJ8: =EG8+EH8-EI8 -> 4 | EM8: =EJ8+EK8-EL8 -> 4 | EP8: =EM8+EN8-EO8 -> 4 | ES8: =EP8+EQ8-ER8 -> 4 | EV8: =ES8+ET8-EU8 -> 4 | EY8: =EV8+EW8-EX8 -> 4 | FB8: =EY8+EZ8-FA8 -> 4 | FE8: =FB8+FC8-FD8 -> 4 | FH8: =FE8+FF8-FG8 -> 4 | FK8: =FH8+FI8-FJ8 -> 4 | FN8: =FK8+FL8-FM8 -> 4 | FQ8: =FN8+FO8-FP8 -> 4 | FT8: =FQ8+FR8-FS8 -> 4 | FW8: =FT8+FU8-FV8 -> 4
A9: GASEOSA SHWEPPES | B9: ='INV. FEB'!BX9 -> 9 | C9: 0 | D9: 0 | E9: =B9+C9-D9 -> 9 | F9: 0 | G9: 0 | H9: =E9+F9-G9 -> 9 | I9: 0 | J9: 0 | K9: =H9+I9-J9 -> 9 | L9: 0 | M9: 0 | N9: =K9+L9-M9 -> 9 | O9: 0 | P9: 0 | Q9: =N9+O9-P9 -> 9 | R9: 0 | S9: 0 | T9: =Q9+R9-S9 -> 9 | U9: 0 | V9: 0 | W9: =T9+U9-V9 -> 9 | X9: 0 | Y9: 0 | Z9: =W9+X9-Y9 -> 9 | AA9: 0 | AB9: 0 | AC9: =Z9+AA9-AB9 -> 9 | AD9: 0 | AE9: 0 | AF9: =AC9+AD9-AE9 -> 9 | AG9: 0 | AH9: 0 | AI9: =AF9+AG9-AH9 -> 9 | AJ9: 0 | AK9: 0 | AL9: =AI9+AJ9-AK9 -> 9 | AM9: 0 | AN9: 0 | AO9: =AL9+AM9-AN9 -> 9 | AP9: 0 | AQ9: 0 | AR9: =AO9+AP9-AQ9 -> 9 | AS9: 0 | AT9: 0 | AU9: =AR9+AS9-AT9 -> 9 | AV9: 0 | AW9: 0 | AX9: =AU9+AV9-AW9 -> 9 | AY9: 0 | AZ9: 0 | BA9: =AX9+AY9-AZ9 -> 9 | BB9: 0 | BC9: 0 | BD9: =BA9+BB9-BC9 -> 9 | BE9: 0 | BF9: 0 | BG9: =BD9+BE9-BF9 -> 9 | BH9: 0 | BI9: 0 | BJ9: =BG9+BH9-BI9 -> 9 | BK9: 0 | BL9: 0 | BM9: =BJ9+BK9-BL9 -> 9 | BN9: 0 | BO9: 0 | BP9: =BM9+BN9-BO9 -> 9 | BQ9: 0 | BR9: 0 | BS9: =BP9+BQ9-BR9 -> 9 | BT9: 0 | BU9: 0 | BV9: =BS9+BT9-BU9 -> 9 | BW9: 0 | BX9: 0 | BY9: =BV9+BW9-BX9 -> 9 | BZ9: 0 | CA9: 0 | CB9: =BY9+BZ9-CA9 -> 9 | CC9: 0 | CD9: 0 | CE9: 9 | CF9: 0 | CG9: 0 | CH9: =CE9+CF9-CG9 -> 9 | CI9: 0 | CJ9: 0 | CK9: =CH9+CI9-CJ9 -> 9 | CL9: 0 | CM9: 0 | CN9: =CK9+CL9-CM9 -> 9 | CO9: 0 | CP9: 0 | CQ9: =CN9+CO9-CP9 -> 9 | CR9: 0 | CS9: 0 | CT9: =CQ9+CR9-CS9 -> 9 | CU9: 0 | CV9: 0 | CW9: =CT9+CU9-CV9 -> 9 | CZ9: =CW9+CX9-CY9 -> 9 | DC9: =CZ9+DA9-DB9 -> 9 | DF9: =DC9+DD9-DE9 -> 9 | DI9: =DF9+DG9-DH9 -> 9 | DL9: =DI9+DJ9-DK9 -> 9 | DO9: =DL9+DM9-DN9 -> 9 | DR9: =DO9+DP9-DQ9 -> 9 | DU9: =DR9+DS9-DT9 -> 9 | DX9: =DU9+DV9-DW9 -> 9 | EA9: =DX9+DY9-DZ9 -> 9 | ED9: =EA9+EB9-EC9 -> 9 | EG9: =ED9+EE9-EF9 -> 9 | EJ9: =EG9+EH9-EI9 -> 9 | EM9: =EJ9+EK9-EL9 -> 9 | EP9: =EM9+EN9-EO9 -> 9 | ES9: =EP9+EQ9-ER9 -> 9 | EV9: =ES9+ET9-EU9 -> 9 | EY9: =EV9+EW9-EX9 -> 9 | FB9: =EY9+EZ9-FA9 -> 9 | FE9: =FB9+FC9-FD9 -> 9 | FH9: =FE9+FF9-FG9 -> 9 | FK9: =FH9+FI9-FJ9 -> 9 | FN9: =FK9+FL9-FM9 -> 9 | FQ9: =FN9+FO9-FP9 -> 9 | FT9: =FQ9+FR9-FS9 -> 9 | FW9: =FT9+FU9-FV9 -> 9
A10: BRETAÑA | B10: ='INV. FEB'!BX10 -> 11 | C10: 0 | D10: 0 | E10: =B10+C10-D10 -> 11 | F10: 0 | G10: 0 | H10: =E10+F10-G10 -> 11 | I10: 0 | J10: 0 | K10: =H10+I10-J10 -> 11 | L10: 0 | M10: 0 | N10: =K10+L10-M10 -> 11 | O10: 0 | P10: 0 | Q10: =N10+O10-P10 -> 11 | R10: 0 | S10: 0 | T10: =Q10+R10-S10 -> 11 | U10: 0 | V10: 0 | W10: =T10+U10-V10 -> 11 | X10: 0 | Y10: 2 | Z10: =W10+X10-Y10 -> 9 | AA10: 0 | AB10: 1 | AC10: =Z10+AA10-AB10 -> 8 | AD10: 0 | AE10: 0 | AF10: =AC10+AD10-AE10 -> 8 | AG10: 0 | AH10: 1 | AI10: =AF10+AG10-AH10 -> 7 | AJ10: 0 | AK10: 0 | AL10: =AI10+AJ10-AK10 -> 7 | AM10: 0 | AN10: 0 | AO10: =AL10+AM10-AN10 -> 7 | AP10: 0 | AQ10: 0 | AR10: =AO10+AP10-AQ10 -> 7 | AS10: 0 | AT10: 0 | AU10: =AR10+AS10-AT10 -> 7 | AV10: 0 | AW10: 0 | AX10: =AU10+AV10-AW10 -> 7 | AY10: 0 | AZ10: 2 | BA10: =AX10+AY10-AZ10 -> 5 | BB10: 0 | BC10: 0 | BD10: =BA10+BB10-BC10 -> 5 | BE10: 0 | BF10: 0 | BG10: =BD10+BE10-BF10 -> 5 | BH10: 0 | BI10: 0 | BJ10: =BG10+BH10-BI10 -> 5 | BK10: 0 | BL10: 2 | BM10: =BJ10+BK10-BL10 -> 3 | BN10: 0 | BO10: 0 | BP10: =BM10+BN10-BO10 -> 3 | BQ10: 0 | BR10: 0 | BS10: =BP10+BQ10-BR10 -> 3 | BT10: 0 | BU10: 0 | BV10: =BS10+BT10-BU10 -> 3 | BW10: 0 | BX10: 0 | BY10: =BV10+BW10-BX10 -> 3 | BZ10: 0 | CA10: 0 | CB10: =BY10+BZ10-CA10 -> 3 | CC10: 0 | CD10: 0 | CE10: 3 | CF10: 0 | CG10: 0 | CH10: =CE10+CF10-CG10 -> 3 | CI10: 0 | CJ10: 0 | CK10: =CH10+CI10-CJ10 -> 3 | CL10: 0 | CM10: 0 | CN10: =CK10+CL10-CM10 -> 3 | CO10: 5 | CP10: 0 | CQ10: 6 | CR10: 0 | CS10: 0 | CT10: =CQ10+CR10-CS10 -> 6 | CU10: 0 | CV10: 0 | CW10: =CT10+CU10-CV10 -> 6 | CZ10: =CW10+CX10-CY10 -> 6 | DC10: =CZ10+DA10-DB10 -> 6 | DE10: 1 | DF10: =DC10+DD10-DE10 -> 5 | DI10: =DF10+DG10-DH10 -> 5 | DL10: =DI10+DJ10-DK10 -> 5 | DO10: =DL10+DM10-DN10 -> 5 | DR10: =DO10+DP10-DQ10 -> 5 | DU10: =DR10+DS10-DT10 -> 5 | DX10: =DU10+DV10-DW10 -> 5 | EA10: =DX10+DY10-DZ10 -> 5 | ED10: =EA10+EB10-EC10 -> 5 | EG10: =ED10+EE10-EF10 -> 5 | EJ10: =EG10+EH10-EI10 -> 5 | EM10: =EJ10+EK10-EL10 -> 5 | EP10: =EM10+EN10-EO10 -> 5 | ES10: =EP10+EQ10-ER10 -> 5 | EV10: =ES10+ET10-EU10 -> 5 | EY10: =EV10+EW10-EX10 -> 5 | FB10: =EY10+EZ10-FA10 -> 5 | FE10: =FB10+FC10-FD10 -> 5 | FH10: =FE10+FF10-FG10 -> 5 | FK10: =FH10+FI10-FJ10 -> 5 | FN10: =FK10+FL10-FM10 -> 5 | FQ10: =FN10+FO10-FP10 -> 5 | FT10: =FQ10+FR10-FS10 -> 5 | FW10: =FT10+FU10-FV10 -> 5
A11: SPEED MAX | B11: ='INV. FEB'!BX11 -> 14 | C11: 0 | D11: 0 | E11: =B11+C11-D11 -> 14 | F11: 0 | G11: 0 | H11: =E11+F11-G11 -> 14 | I11: 0 | J11: 0 | K11: =H11+I11-J11 -> 14 | L11: 0 | M11: 0 | N11: =K11+L11-M11 -> 14 | O11: 0 | P11: 0 | Q11: =N11+O11-P11 -> 14 | R11: 0 | S11: 0 | T11: =Q11+R11-S11 -> 14 | U11: 0 | V11: 0 | W11: =T11+U11-V11 -> 14 | X11: 0 | Y11: 0 | Z11: =W11+X11-Y11 -> 14 | AA11: 0 | AB11: 1 | AC11: =Z11+AA11-AB11 -> 13 | AD11: 0 | AE11: 0 | AF11: =AC11+AD11-AE11 -> 13 | AG11: 0 | AH11: 0 | AI11: =AF11+AG11-AH11 -> 13 | AJ11: 0 | AK11: 0 | AL11: =AI11+AJ11-AK11 -> 13 | AM11: 0 | AN11: 0 | AO11: =AL11+AM11-AN11 -> 13 | AP11: 0 | AQ11: 1 | AR11: =AO11+AP11-AQ11 -> 12 | AS11: 0 | AT11: 0 | AU11: =AR11+AS11-AT11 -> 12 | AV11: 0 | AW11: 0 | AX11: =AU11+AV11-AW11 -> 12 | AY11: 0 | AZ11: 0 | BA11: =AX11+AY11-AZ11 -> 12 | BB11: 0 | BC11: 0 | BD11: =BA11+BB11-BC11 -> 12 | BE11: 0 | BF11: 0 | BG11: =BD11+BE11-BF11 -> 12 | BH11: 0 | BI11: 1 | BJ11: =BG11+BH11-BI11 -> 11 | BK11: 0 | BL11: 0 | BM11: =BJ11+BK11-BL11 -> 11 | BN11: 0 | BO11: 0 | BP11: =BM11+BN11-BO11 -> 11 | BQ11: 0 | BR11: 0 | BS11: =BP11+BQ11-BR11 -> 11 | BT11: 0 | BU11: 0 | BV11: =BS11+BT11-BU11 -> 11 | BW11: 0 | BX11: 0 | BY11: =BV11+BW11-BX11 -> 11 | BZ11: 0 | CA11: 0 | CB11: =BY11+BZ11-CA11 -> 11 | CC11: 0 | CD11: 0 | CE11: 11 | CF11: 0 | CG11: 0 | CH11: =CE11+CF11-CG11 -> 11 | CI11: 0 | CJ11: 0 | CK11: =CH11+CI11-CJ11 -> 11 | CL11: 0 | CM11: 0 | CN11: =CK11+CL11-CM11 -> 11 | CO11: 0 | CP11: 0 | CQ11: =CN11+CO11-CP11 -> 11 | CR11: 0 | CS11: 0 | CT11: =CQ11+CR11-CS11 -> 11 | CU11: 0 | CV11: 0 | CW11: =CT11+CU11-CV11 -> 11 | CZ11: =CW11+CX11-CY11 -> 11 | DC11: =CZ11+DA11-DB11 -> 11 | DF11: =DC11+DD11-DE11 -> 11 | DI11: =DF11+DG11-DH11 -> 11 | DL11: =DI11+DJ11-DK11 -> 11 | DO11: =DL11+DM11-DN11 -> 11 | DR11: =DO11+DP11-DQ11 -> 11 | DU11: =DR11+DS11-DT11 -> 11 | DX11: =DU11+DV11-DW11 -> 11 | EA11: =DX11+DY11-DZ11 -> 11 | ED11: =EA11+EB11-EC11 -> 11 | EG11: =ED11+EE11-EF11 -> 11 | EJ11: =EG11+EH11-EI11 -> 11 | EM11: =EJ11+EK11-EL11 -> 11 | EP11: =EM11+EN11-EO11 -> 11 | ES11: =EP11+EQ11-ER11 -> 11 | EV11: =ES11+ET11-EU11 -> 11 | EY11: =EV11+EW11-EX11 -> 11 | FB11: =EY11+EZ11-FA11 -> 11 | FE11: =FB11+FC11-FD11 -> 11 | FH11: =FE11+FF11-FG11 -> 11 | FK11: =FH11+FI11-FJ11 -> 11 | FN11: =FK11+FL11-FM11 -> 11 | FQ11: =FN11+FO11-FP11 -> 11 | FT11: =FQ11+FR11-FS11 -> 11 | FW11: =FT11+FU11-FV11 -> 11
A12: REDBULL | B12: ='INV. FEB'!BX12 -> 5 | C12: 0 | D12: 0 | E12: =B12+C12-D12 -> 5 | F12: 0 | G12: 0 | H12: =E12+F12-G12 -> 5 | I12: 0 | J12: 0 | K12: =H12+I12-J12 -> 5 | L12: 0 | M12: 0 | N12: =K12+L12-M12 -> 5 | O12: 0 | P12: 0 | Q12: =N12+O12-P12 -> 5 | R12: 0 | S12: 0 | T12: =Q12+R12-S12 -> 5 | U12: 0 | V12: 0 | W12: =T12+U12-V12 -> 5 | X12: 0 | Y12: 0 | Z12: =W12+X12-Y12 -> 5 | AA12: 0 | AB12: 0 | AC12: =Z12+AA12-AB12 -> 5 | AD12: 0 | AE12: 0 | AF12: =AC12+AD12-AE12 -> 5 | AG12: 0 | AH12: 0 | AI12: =AF12+AG12-AH12 -> 5 | AJ12: 0 | AK12: 0 | AL12: =AI12+AJ12-AK12 -> 5 | AM12: 0 | AN12: 0 | AO12: =AL12+AM12-AN12 -> 5 | AP12: 0 | AQ12: 0 | AR12: =AO12+AP12-AQ12 -> 5 | AS12: 0 | AT12: 0 | AU12: =AR12+AS12-AT12 -> 5 | AV12: 0 | AW12: 0 | AX12: =AU12+AV12-AW12 -> 5 | AY12: 0 | AZ12: 0 | BA12: =AX12+AY12-AZ12 -> 5 | BB12: 0 | BC12: 0 | BD12: =BA12+BB12-BC12 -> 5 | BE12: 0 | BF12: 0 | BG12: =BD12+BE12-BF12 -> 5 | BH12: 0 | BI12: 0 | BJ12: =BG12+BH12-BI12 -> 5 | BK12: 0 | BL12: 0 | BM12: =BJ12+BK12-BL12 -> 5 | BN12: 0 | BO12: 0 | BP12: =BM12+BN12-BO12 -> 5 | BQ12: 0 | BR12: 0 | BS12: =BP12+BQ12-BR12 -> 5 | BT12: 0 | BU12: 0 | BV12: =BS12+BT12-BU12 -> 5 | BW12: 0 | BX12: 0 | BY12: =BV12+BW12-BX12 -> 5 | BZ12: 0 | CA12: 0 | CB12: =BY12+BZ12-CA12 -> 5 | CC12: 0 | CD12: 0 | CE12: 5 | CF12: 0 | CG12: 0 | CH12: =CE12+CF12-CG12 -> 5 | CI12: 0 | CJ12: 0 | CK12: =CH12+CI12-CJ12 -> 5 | CL12: 0 | CM12: 1 | CN12: 5 | CO12: 0 | CP12: 0 | CQ12: 1 | CR12: 0 | CS12: 0 | CT12: =CQ12+CR12-CS12 -> 1 | CU12: 0 | CV12: 0 | CW12: =CT12+CU12-CV12 -> 1 | CZ12: =CW12+CX12-CY12 -> 1 | DC12: =CZ12+DA12-DB12 -> 1 | DF12: =DC12+DD12-DE12 -> 1 | DI12: =DF12+DG12-DH12 -> 1 | DL12: =DI12+DJ12-DK12 -> 1 | DO12: =DL12+DM12-DN12 -> 1 | DR12: =DO12+DP12-DQ12 -> 1 | DU12: =DR12+DS12-DT12 -> 1 | DX12: =DU12+DV12-DW12 -> 1 | EA12: =DX12+DY12-DZ12 -> 1 | ED12: =EA12+EB12-EC12 -> 1 | EG12: =ED12+EE12-EF12 -> 1 | EJ12: =EG12+EH12-EI12 -> 1 | EM12: =EJ12+EK12-EL12 -> 1 | EP12: =EM12+EN12-EO12 -> 1 | ES12: =EP12+EQ12-ER12 -> 1 | EV12: =ES12+ET12-EU12 -> 1 | EY12: =EV12+EW12-EX12 -> 1 | FB12: =EY12+EZ12-FA12 -> 1 | FE12: =FB12+FC12-FD12 -> 1 | FH12: =FE12+FF12-FG12 -> 1 | FK12: =FH12+FI12-FJ12 -> 1 | FN12: =FK12+FL12-FM12 -> 1 | FQ12: =FN12+FO12-FP12 -> 1 | FT12: =FQ12+FR12-FS12 -> 1 | FW12: =FT12+FU12-FV12 -> 1
A13: ELECTROLIT | B13: ='INV. FEB'!BX13 -> 7 | C13: 0 | D13: 1 | E13: =B13+C13-D13 -> 6 | F13: 0 | G13: 0 | H13: =E13+F13-G13 -> 6 | I13: 0 | J13: 0 | K13: =H13+I13-J13 -> 6 | L13: 0 | M13: 0 | N13: =K13+L13-M13 -> 6 | O13: 0 | P13: 0 | Q13: =N13+O13-P13 -> 6 | R13: 0 | S13: 0 | T13: =Q13+R13-S13 -> 6 | U13: 0 | V13: 0 | W13: =T13+U13-V13 -> 6 | X13: 0 | Y13: 0 | Z13: =W13+X13-Y13 -> 6 | AA13: 0 | AB13: 0 | AC13: =Z13+AA13-AB13 -> 6 | AD13: 0 | AE13: 0 | AF13: =AC13+AD13-AE13 -> 6 | AG13: 0 | AH13: 0 | AI13: =AF13+AG13-AH13 -> 6 | AJ13: 0 | AK13: 0 | AL13: =AI13+AJ13-AK13 -> 6 | AM13: 0 | AN13: 0 | AO13: =AL13+AM13-AN13 -> 6 | AP13: 0 | AQ13: 0 | AR13: =AO13+AP13-AQ13 -> 6 | AS13: 0 | AT13: 0 | AU13: =AR13+AS13-AT13 -> 6 | AV13: 0 | AW13: 0 | AX13: =AU13+AV13-AW13 -> 6 | AY13: 0 | AZ13: 0 | BA13: =AX13+AY13-AZ13 -> 6 | BB13: 0 | BC13: 0 | BD13: =BA13+BB13-BC13 -> 6 | BE13: 0 | BF13: 0 | BG13: =BD13+BE13-BF13 -> 6 | BH13: 0 | BI13: 0 | BJ13: =BG13+BH13-BI13 -> 6 | BK13: 0 | BL13: 0 | BM13: =BJ13+BK13-BL13 -> 6 | BN13: 0 | BO13: 0 | BP13: =BM13+BN13-BO13 -> 6 | BQ13: 0 | BR13: 0 | BS13: =BP13+BQ13-BR13 -> 6 | BT13: 0 | BU13: 4 | BV13: =BS13+BT13-BU13 -> 2 | BW13: 0 | BX13: 3 | BY13: =BV13+BW13-BX13 -> -1 | BZ13: 6 | CA13: 0 | CB13: =BY13+BZ13-CA13 -> 5 | CC13: 0 | CD13: 0 | CE13: 5 | CF13: 0 | CG13: 0 | CH13: =CE13+CF13-CG13 -> 5 | CI13: 0 | CJ13: 0 | CK13: =CH13+CI13-CJ13 -> 5 | CL13: 0 | CM13: 4 | CN13: =CK13+CL13-CM13 -> 1 | CO13: 0 | CP13: 0 | CQ13: =CN13+CO13-CP13 -> 1 | CR13: 0 | CS13: 0 | CT13: =CQ13+CR13-CS13 -> 1 | CU13: 0 | CV13: 0 | CW13: =CT13+CU13-CV13 -> 1 | CZ13: =CW13+CX13-CY13 -> 1 | DC13: =CZ13+DA13-DB13 -> 1 | DF13: =DC13+DD13-DE13 -> 1 | DI13: =DF13+DG13-DH13 -> 1 | DJ13: 12 | DL13: =DI13+DJ13-DK13 -> 13 | DO13: =DL13+DM13-DN13 -> 13 | DR13: =DO13+DP13-DQ13 -> 13 | DU13: =DR13+DS13-DT13 -> 13 | DX13: =DU13+DV13-DW13 -> 13 | EA13: =DX13+DY13-DZ13 -> 13 | ED13: =EA13+EB13-EC13 -> 13 | EG13: =ED13+EE13-EF13 -> 13 | EJ13: =EG13+EH13-EI13 -> 13 | EM13: =EJ13+EK13-EL13 -> 13 | EP13: =EM13+EN13-EO13 -> 13 | ES13: =EP13+EQ13-ER13 -> 13 | EV13: =ES13+ET13-EU13 -> 13 | EY13: =EV13+EW13-EX13 -> 13 | FB13: =EY13+EZ13-FA13 -> 13 | FE13: =FB13+FC13-FD13 -> 13 | FH13: =FE13+FF13-FG13 -> 13 | FK13: =FH13+FI13-FJ13 -> 13 | FN13: =FK13+FL13-FM13 -> 13 | FQ13: =FN13+FO13-FP13 -> 13 | FT13: =FQ13+FR13-FS13 -> 13 | FW13: =FT13+FU13-FV13 -> 13
A14: POKER LATA | B14: ='INV. FEB'!BX14 -> 10 | C14: 0 | D14: 0 | E14: =B14+C14-D14 -> 10 | F14: 0 | G14: 0 | H14: =E14+F14-G14 -> 10 | I14: 0 | J14: 0 | K14: =H14+I14-J14 -> 10 | L14: 0 | M14: 0 | N14: =K14+L14-M14 -> 10 | O14: 0 | P14: 0 | Q14: =N14+O14-P14 -> 10 | R14: 0 | S14: 0 | T14: =Q14+R14-S14 -> 10 | U14: 0 | V14: 0 | W14: =T14+U14-V14 -> 10 | X14: 0 | Y14: 0 | Z14: =W14+X14-Y14 -> 10 | AA14: 0 | AB14: 0 | AC14: =Z14+AA14-AB14 -> 10 | AD14: 0 | AE14: 0 | AF14: =AC14+AD14-AE14 -> 10 | AG14: 0 | AH14: 0 | AI14: =AF14+AG14-AH14 -> 10 | AJ14: 0 | AK14: 0 | AL14: =AI14+AJ14-AK14 -> 10 | AM14: 0 | AN14: 0 | AO14: =AL14+AM14-AN14 -> 10 | AP14: 0 | AQ14: 0 | AR14: =AO14+AP14-AQ14 -> 10 | AS14: 0 | AT14: 0 | AU14: =AR14+AS14-AT14 -> 10 | AV14: 0 | AW14: 0 | AX14: =AU14+AV14-AW14 -> 10 | AY14: 0 | AZ14: 0 | BA14: =AX14+AY14-AZ14 -> 10 | BB14: 0 | BC14: 0 | BD14: =BA14+BB14-BC14 -> 10 | BE14: 0 | BF14: 0 | BG14: =BD14+BE14-BF14 -> 10 | BH14: 0 | BI14: 0 | BJ14: =BG14+BH14-BI14 -> 10 | BK14: 0 | BL14: 0 | BM14: =BJ14+BK14-BL14 -> 10 | BN14: 0 | BO14: 0 | BP14: =BM14+BN14-BO14 -> 10 | BQ14: 0 | BR14: 0 | BS14: =BP14+BQ14-BR14 -> 10 | BT14: 0 | BU14: 0 | BV14: =BS14+BT14-BU14 -> 10 | BW14: 0 | BX14: 0 | BY14: =BV14+BW14-BX14 -> 10 | BZ14: 0 | CA14: 0 | CB14: =BY14+BZ14-CA14 -> 10 | CC14: 0 | CD14: 0 | CE14: 10 | CF14: 0 | CG14: 0 | CH14: =CE14+CF14-CG14 -> 10 | CI14: 0 | CJ14: 0 | CK14: =CH14+CI14-CJ14 -> 10 | CL14: 0 | CM14: 0 | CN14: =CK14+CL14-CM14 -> 10 | CO14: 0 | CP14: 0 | CQ14: =CN14+CO14-CP14 -> 10 | CR14: 0 | CS14: 0 | CT14: =CQ14+CR14-CS14 -> 10 | CU14: 0 | CV14: 0 | CW14: =CT14+CU14-CV14 -> 10 | CZ14: =CW14+CX14-CY14 -> 10 | DC14: =CZ14+DA14-DB14 -> 10 | DF14: =DC14+DD14-DE14 -> 10 | DI14: =DF14+DG14-DH14 -> 10 | DL14: =DI14+DJ14-DK14 -> 10 | DO14: =DL14+DM14-DN14 -> 10 | DR14: =DO14+DP14-DQ14 -> 10 | DU14: =DR14+DS14-DT14 -> 10 | DX14: =DU14+DV14-DW14 -> 10 | EA14: =DX14+DY14-DZ14 -> 10 | ED14: =EA14+EB14-EC14 -> 10 | EG14: =ED14+EE14-EF14 -> 10 | EJ14: =EG14+EH14-EI14 -> 10 | EM14: =EJ14+EK14-EL14 -> 10 | EP14: =EM14+EN14-EO14 -> 10 | ES14: =EP14+EQ14-ER14 -> 10 | EV14: =ES14+ET14-EU14 -> 10 | EY14: =EV14+EW14-EX14 -> 10 | FB14: =EY14+EZ14-FA14 -> 10 | FE14: =FB14+FC14-FD14 -> 10 | FH14: =FE14+FF14-FG14 -> 10 | FK14: =FH14+FI14-FJ14 -> 10 | FN14: =FK14+FL14-FM14 -> 10 | FQ14: =FN14+FO14-FP14 -> 10 | FT14: =FQ14+FR14-FS14 -> 10 | FW14: =FT14+FU14-FV14 -> 10
A15: AGUILA LATA | B15: ='INV. FEB'!BX15 -> 0 | C15: 0 | D15: 0 | E15: =B15+C15-D15 -> 0 | F15: 0 | G15: 0 | H15: =E15+F15-G15 -> 0 | I15: 0 | J15: 0 | K15: =H15+I15-J15 -> 0 | L15: 0 | M15: 0 | N15: =K15+L15-M15 -> 0 | O15: 0 | P15: 0 | Q15: =N15+O15-P15 -> 0 | R15: 0 | S15: 0 | T15: =Q15+R15-S15 -> 0 | U15: 0 | V15: 0 | W15: =T15+U15-V15 -> 0 | X15: 0 | Y15: 0 | Z15: =W15+X15-Y15 -> 0 | AA15: 0 | AB15: 0 | AC15: =Z15+AA15-AB15 -> 0 | AD15: 0 | AE15: 0 | AF15: =AC15+AD15-AE15 -> 0 | AG15: 0 | AH15: 0 | AI15: =AF15+AG15-AH15 -> 0 | AJ15: 0 | AK15: 0 | AL15: =AI15+AJ15-AK15 -> 0 | AM15: 0 | AN15: 0 | AO15: =AL15+AM15-AN15 -> 0 | AP15: 0 | AQ15: 0 | AR15: =AO15+AP15-AQ15 -> 0 | AS15: 0 | AT15: 0 | AU15: =AR15+AS15-AT15 -> 0 | AV15: 0 | AW15: 0 | AX15: =AU15+AV15-AW15 -> 0 | AY15: 0 | AZ15: 0 | BA15: =AX15+AY15-AZ15 -> 0 | BB15: 0 | BC15: 0 | BD15: =BA15+BB15-BC15 -> 0 | BE15: 0 | BF15: 0 | BG15: =BD15+BE15-BF15 -> 0 | BH15: 0 | BI15: 0 | BJ15: =BG15+BH15-BI15 -> 0 | BK15: 0 | BL15: 0 | BM15: =BJ15+BK15-BL15 -> 0 | BN15: 0 | BO15: 0 | BP15: =BM15+BN15-BO15 -> 0 | BQ15: 0 | BR15: 0 | BS15: =BP15+BQ15-BR15 -> 0 | BT15: 0 | BU15: 0 | BV15: =BS15+BT15-BU15 -> 0 | BW15: 0 | BX15: 0 | BY15: =BV15+BW15-BX15 -> 0 | BZ15: 0 | CA15: 0 | CB15: =BY15+BZ15-CA15 -> 0 | CC15: 0 | CD15: 0 | CE15: 0 | CF15: 0 | CG15: 0 | CH15: =CE15+CF15-CG15 -> 0 | CI15: 0 | CJ15: 0 | CK15: =CH15+CI15-CJ15 -> 0 | CL15: 0 | CM15: 0 | CN15: =CK15+CL15-CM15 -> 0 | CO15: 0 | CP15: 0 | CQ15: =CN15+CO15-CP15 -> 0 | CR15: 0 | CS15: 0 | CT15: =CQ15+CR15-CS15 -> 0 | CU15: 0 | CV15: 0 | CW15: =CT15+CU15-CV15 -> 0 | CZ15: =CW15+CX15-CY15 -> 0 | DC15: =CZ15+DA15-DB15 -> 0 | DF15: =DC15+DD15-DE15 -> 0 | DI15: =DF15+DG15-DH15 -> 0 | DL15: =DI15+DJ15-DK15 -> 0 | DO15: =DL15+DM15-DN15 -> 0 | DR15: =DO15+DP15-DQ15 -> 0 | DU15: =DR15+DS15-DT15 -> 0 | DX15: =DU15+DV15-DW15 -> 0 | EA15: =DX15+DY15-DZ15 -> 0 | ED15: =EA15+EB15-EC15 -> 0 | EG15: =ED15+EE15-EF15 -> 0 | EJ15: =EG15+EH15-EI15 -> 0 | EM15: =EJ15+EK15-EL15 -> 0 | EP15: =EM15+EN15-EO15 -> 0 | ES15: =EP15+EQ15-ER15 -> 0 | EV15: =ES15+ET15-EU15 -> 0 | EY15: =EV15+EW15-EX15 -> 0 | FB15: =EY15+EZ15-FA15 -> 0 | FE15: =FB15+FC15-FD15 -> 0 | FH15: =FE15+FF15-FG15 -> 0 | FK15: =FH15+FI15-FJ15 -> 0 | FN15: =FK15+FL15-FM15 -> 0 | FQ15: =FN15+FO15-FP15 -> 0 | FT15: =FQ15+FR15-FS15 -> 0 | FW15: =FT15+FU15-FV15 -> 0
